Workbook
Name _top: 'Min. Intérieur'!$T$33
Name Applicabilité: #REF!
Name Applicable: #REF!
Name Aucun: #REF!
Name Défini: #REF!
Name FiscalYear: #REF!
Name Initial: #REF!
Name Maitrisé: #REF!
Name Niveau_de_conformité: #REF!
Name Niveau_de_maturité: #REF!
Name Optimisation: #REF!
Name Reproductible: #REF!

Sheet Revision History
B8: Document Revision History
B9: Project Name: | C9: QHCs et reporting qualité FY27
B11: Document Status (e.g. Draft, Final, Release #): | E11: Final
B13: Document Version | C13: Date | D13: Prepared / Modified By | E13: Approved by | F13: Section and Text Revised
C14: 46301 | D14: Quality Team | E14: Ilham ELFATEHI | F14: Evaluation des performances des comptes
C15: 46189 | D15: Farah ABID | E15: Ilham ELFATEHI | F15: Revue des formules des scores de maturité et badges de performances
B20: Template Revision History
B22: Change Request# | C22: Template Version | D22: Approval Date | E22: Modified By | F22: Section, Page(s) and Text Revised
B23: NA | C23: 1.0 | D23: 41962 | E23: Ilham ELFATEHI | F23: Création du document
B24: NA | C24: 1.1 | D24: 42794 | E24: Ilham ELFATEHI | F24: Revue du template (new logo HPE CDG)
B25: NA | C25: 1.2 | D25: 42901 | E25: Ilham ELFATEHI | F25: Revue du template (Logo DXC)
B26: NA | C26: 1.3 | D26: 44417 | E26: Ilham ELFATEHI | F26: Revue template (New logo DXC)
B27: NA | C27: 1.4 | D27: 44656 | E27: Farah ABID | F27: Revue template (Document classification)
B28: NA | C28: 1.5 | D28: 45224 | E28: Farah ABID | F28: Revue template et Rajout de la liste déroulante des clause ISO9K de la partie reporting
B29: NA | C29: 1.6 | D29: 45428 | E29: Imane KAICHOUH | F29: Template Review (New logo DXC CDG, New Document Classification)
B30: CR-112 | C30: 1.7 | D30: 45763 | E30: Quality Team | F30: Template Review (Labeling change Quality Health Checks instead of audit)
B31: CR-114 | C31: 1,8 | D31: 45996 | E31: Quality Team | F31: Rajout de la catégorie 4 des findings
B32: NA | C32: 1.9 | D32: 46146 | E32: Ilham ELFATEHI | F32: Automatisation du fichier ajout évaluation de maturité, régle de gestion et indicateurs de perfomance
B33: NA | C33: 2.0 | D33: 46164 | E33: Ilham ELFATEHI | F33: Revue du template et automatisation des KPI's
B34: NA | C34: 2.1 | D34: 46188 | E34: Ilham ELFATEHI | F34: Instaurer des nouveaux barémes de maturité conforme à ISO 9001

Sheet ACCUEIL
B2: QHC ISO 9001:2015 — FY27
B3: DXC Technology Morocco | Quality Health Check
B4: Préparé par: Ilham EL FATEHI | Approuvé par: Mohamed HADID
B6: 📋 20 Comptes | 37 Clauses | 21 Colonnes | Score 1-4 | Catégorisation CSAT
B12: Palette DXC :
B13: Midnight Blue | C13: #0E1020
B14: Royal | C14: #004AAC
B15: Sky | C15: #A1E6FF
B16: Red | C16: #D94000
B17: Gold | C17: #FFAE41
B18: Canvas | C18: #F6F3F0
B19: Peach | C19: #FFC082
B20: Charcoal | C20: #2B2B2B

Sheet REGLES DE GESTION
A1: RÈGLES DE GESTION — QHC ISO 9001:2015 FY27
A3: Scoring DE MATURITÉ ISO 9001 (Échelle 1 à 5)
A4: Score | B4: Niveau de Maturité | C4: Description
A5: 1 | B5: Non en place / Élémentaire | C5: Aucune approche structurée, pratiques ad hoc
A6: 2 | B6: Partiellement en place / Réactif | C6: Approche réactive, documentation partielle
A7: 3 | B7: Largement en place / Stable | C7: Processus formalisés, mis en œuvre de manière cohérente
A8: 4 | B8: Totalement en place / Proactif | C8: Amélioration continue, indicateurs suivis
A9: 5 | B9: Excellence / Meilleures pratiques | C9: Performance durable, benchmarking, innovation
A10: 2. CATÉGORISATION COMPTES (alignée CSAT/NPS)
A12: Badge | B12: Seuil Score maturité | C12: Couleur | D12: Signification | E12: Action Requise
A13: 🟢 Très Performant | B13: ≥ 4.5 | C13: Vert | D13: SMQ mature et efficace | E13: Maintenir, partager BP
A14: 🔵 Performant | B14: 3.5 à 4.4 | C14: Bleu | D14: SMQ en place avec axes d'amélioration | E14: Amélioration continue
A15: 🟡 A surveiller | B15: 2.5 à 3.4 | C15: Jaune | D15: SMQ partiel, en développement | E15: Plan amélioration structuré
A16: 🟠 À Risque | B16: 1.5 à 2.4 | C16: Orange | D16: SMQ insuffisant, risques identifiés | E16: Plan prioritaire mensuel
A17: 🔴 Critique | B17: < 1.5 | C17: Rouge | D17: SMQ défaillant, NC majeures | E17: Action immédiate 30j
A20: 3. CATÉGORISATION DES FINDING
A22: Catégorie | B22: Définition | C22: Impact | D22: Délai | E22: Couleur
A23: NC Majeure | B23: Absence complète ou défaillance majeure du SMQ | C23: Critique | D23: ≤ 30 jours | E23: Rouge
A24: NC Mineure | B24: Défaillance occasionnelle par rapport aux exigences | C24: Modéré | D24: ≤ 60 jours | E24: Orange
A25: Observation | B25: Constat général sur le SMQ, risque potentiel | C25: Faible | D25: ≤ 90 jours | E25: Jaune
A26: OFI | B26: Piste d'amélioration identifiée | C26: Positif | D26: Selon priorités | E26: Bleu
A27: Bonne Pratique | B27: Pratique exemplaire à valoriser | C27: Positif | D27: Partage immédiat | E27: Vert
A30: 4. GESTION DES ACTIONS CORRECTIVES
A32: Statut | B32: Définition | C32: Règle | D32: Couleur
A33: Ouvert | B33: Action définie, pas encore démarrée | C33: Délai obligatoire | D33: Rouge
A34: En cours | B34: Action en cours de réalisation | C34: Suivi hebdomadaire | D34: Orange
A35: Clôturé | B35: Action réalisée et efficacité vérifiée | C35: Preuve obligatoire | D35: Vert
A36: Non applicable | B36: Action non pertinente | C36: Justification documentée | D36: Gris
A39: 5. INDICATEURS ÂGE
A41: Indicateur | B41: Seuil | C41: Action
A42: 🟢 Normal | B42: ≤ 30 jours | C42: Suivi normal
A43: 🟠 Alerte | B43: ≤ 60 jours | C43: Relance, escalade N+1
A44: 🔴 Critique | B44: > 90 jours | C44: Escalade management
A46: 6. CATÉGORIE (Category)
A48: Catégorie | B48: Définition | C48: Exemple
A49: Entité | B49: Applicable au niveau de l'entité DXC Morocco | C49: Politique qualité, Revue de direction
A50: Entité et Compte | B50: Applicable à la fois entité et compte | C50: Gestion des risques, Compétences
A51: Compte | B51: Applicable uniquement au niveau du compte client | C51: Satisfaction client, Exigences client

Sheet DASHBOARD AUDITS
B1: DASHBOARD RÉALISATION DES AUDITS — FY27
B3: INDICATEURS DE RÉALISATION
B4: Audits Planifiés | D4: Audits Réalisés | F4: En Cours | H4: Non Démarrés | J4: % Avancement
B5: 20 | D5: =COUNTIF(H12:H31,"Réalisé") -> 6 | F5: =COUNTIF(H12:H31,"En cours") -> 4 | H5: =COUNTIF(H12:H31,"Planifié") -> 10 | J5: =IFERROR(COUNTIF(H12:H31,"Réalisé")/20,0) -> 0.3
B7: TOTAL FINDINGS
B8: NC Maj | D8: NC Min | F8: Obs | H8: OFI | J8: BP | L8: TOTAL
B9: ='CDG Sécurité'!D10+RAM!C10+'Min. Intérieur'!C10+'CDG Capital'!C10+AtlanticRe!C10+'Client A'!C10+Servier!C10+MEN!C10+ADM!C10+'CDG DC'!C10+'CDG ITOC'!C10+BPOST!C10+'Graphtalk AIA'!C10+'ONCF APPS'!C10+'ONCF MW'!C10+ANEF!C10+Carrefour!C10+'Vinci Construction'!C10+AXA!C10+OCP!C10 -> 1 | D9: ='CDG Sécurité'!E10+RAM!D10+'Min. Intérieur'!D10+'CDG Capital'!D10+AtlanticRe!D10+'Client A'!D10+Servier!D10+MEN!D10+ADM!D10+'CDG DC'!D10+'CDG ITOC'!D10+BPOST!D10+'Graphtalk AIA'!D10+'ONCF APPS'!D10+'ONCF MW'!D10+ANEF!D10+Carrefour!D10+'Vinci Construction'!D10+AXA!D10+OCP!D10 -> 44 | F9: ='CDG Sécurité'!F10+RAM!E10+'Min. Intérieur'!E10+'CDG Capital'!E10+AtlanticRe!E10+'Client A'!E10+Servier!E10+MEN!E10+ADM!E10+'CDG DC'!E10+'CDG ITOC'!E10+BPOST!E10+'Graphtalk AIA'!E10+'ONCF APPS'!E10+'ONCF MW'!E10+ANEF!E10+Carrefour!E10+'Vinci Construction'!E10+AXA!E10+OCP!E10 -> 6 | H9: ='CDG Sécurité'!G10+RAM!F10+'Min. Intérieur'!F10+'CDG Capital'!F10+AtlanticRe!F10+'Client A'!F10+Servier!F10+MEN!F10+ADM!F10+'CDG DC'!F10+'CDG ITOC'!F10+BPOST!F10+'Graphtalk AIA'!F10+'ONCF APPS'!F10+'ONCF MW'!F10+ANEF!F10+Carrefour!F10+'Vinci Construction'!F10+AXA!F10+OCP!F10 -> 0 | J9: ='CDG Sécurité'!H10+RAM!G10+'Min. Intérieur'!G10+'CDG Capital'!G10+AtlanticRe!G10+'Client A'!G10+Servier!G10+MEN!G10+ADM!G10+'CDG DC'!G10+'CDG ITOC'!G10+BPOST!G10+'Graphtalk AIA'!G10+'ONCF APPS'!G10+'ONCF MW'!G10+ANEF!G10+Carrefour!G10+'Vinci Construction'!G10+AXA!G10+OCP!G10 -> 7 | L9: =B9+D9+F9+H9+J9 -> 58
B11: N° | C11: Compte | D11: Auditeur | E11: Date Plan. | F11: Date Réelle | G11: Durée | H11: Statut | I11: Score | J11: Badge | K11: Total Find.
B12: 1 | C12: CDG Sécurité | D12: Farah ABID | E12: 46146 | F12: 46149 | H12: En cours | I12: ='CDG Sécurité'!B10 -> 2.3636364 | J12: ='CDG Sécurité'!C10 -> À Risque | K12: ='CDG Sécurité'!I10 -> 7
B13: 2 | C13: RAM | D13: Imane KAICHOUH | E13: 46147 | F13: 46153 | H13: Réalisé | I13: =RAM!A10 -> 3.1538462 | J13: =RAM!B10 -> A Surveiller | K13: =RAM!H10 -> 5
B14: 3 | C14: Min. Intérieur | D14: Farah ABID | E14: 46148 | F14: 46154 | H14: Réalisé | I14: ='Min. Intérieur'!A10 -> 3.3636364 | J14: ='Min. Intérieur'!B10 -> A Surveiller | K14: ='Min. Intérieur'!H10 -> 7
B15: 4 | C15: CDG Capital | D15: Imane KAICHOUH | E15: 46149 | F15: 46155 | H15: En cours | I15: ='CDG Capital'!A10 -> 2.4545455 | J15: ='CDG Capital'!B10 -> À Risque | K15: ='CDG Capital'!H10 -> 7
B16: 5 | C16: AtlanticRe | D16: Imane KAICHOUH | E16: 46146 | F16: 46147 | H16: Réalisé | I16: =AtlanticRe!A10 -> 2.9615385 | J16: =AtlanticRe!B10 -> A Surveiller | K16: =AtlanticRe!H10 -> 5
B17: 6 | C17: Client A | H17: Planifié | I17: ='Client A'!A10 -> 0 | J17: ='Client A'!B10 -> ⏳ Non audité | K17: ='Client A'!H10 -> 0
B18: 7 | C18: Servier | D18: Farah ABID | E18: 46157 | F18: 46174 | H18: Réalisé | I18: =Servier!A10 -> 3.6 | J18: =Servier!B10 -> Performant | K18: =Servier!H10 -> 4
B19: 8 | C19: MEN | H19: En cours | I19: =MEN!A10 -> 3.1538462 | J19: =MEN!B10 -> A Surveiller | K19: =MEN!H10 -> 5
B20: 9 | C20: ADM | H20: Planifié | I20: =ADM!A10 -> 0 | J20: =ADM!B10 -> ⏳ Non audité | K20: =ADM!H10 -> 0
B21: 10 | C21: CDG DC | H21: Planifié | I21: ='CDG DC'!A10 -> 0 | J21: ='CDG DC'!B10 -> ⏳ Non audité | K21: ='CDG DC'!H10 -> 0
B22: 11 | C22: CDG ITOC | H22: Planifié | I22: ='CDG ITOC'!A10 -> 0 | J22: ='CDG ITOC'!B10 -> ⏳ Non audité | K22: ='CDG ITOC'!H10 -> 0
B23: 12 | C23: BPOST | H23: Planifié | I23: =BPOST!A10 -> 0 | J23: =BPOST!B10 -> ⏳ Non audité | K23: =BPOST!H10 -> 0
B24: 13 | C24: Graphtalk AIA | H24: Planifié | I24: ='Graphtalk AIA'!A10 -> 0 | J24: ='Graphtalk AIA'!B10 -> ⏳ Non audité | K24: ='Graphtalk AIA'!H10 -> 0
B25: 14 | C25: ONCF APPS | H25: Réalisé | I25: ='ONCF APPS'!A10 -> 0 | J25: ='ONCF APPS'!B10 -> ⏳ Non audité | K25: ='ONCF APPS'!H10 -> 0
B26: 15 | C26: ONCF MW | H26: Réalisé | I26: ='ONCF MW'!A10 -> 3.1153846 | J26: ='ONCF MW'!B10 -> A Surveiller | K26: ='ONCF MW'!H10 -> 6
B27: 16 | C27: ANEF | H27: Planifié | I27: =ANEF!A10 -> 0 | J27: =ANEF!B10 -> ⏳ Non audité | K27: =ANEF!H10 -> 0
B28: 17 | C28: Carrefour | H28: Planifié | I28: =Carrefour!A10 -> 0 | J28: =Carrefour!B10 -> ⏳ Non audité | K28: =Carrefour!H10 -> 0
B29: 18 | C29: Vinci Construction | H29: Planifié | I29: ='Vinci Construction'!A10 -> 0 | J29: ='Vinci Construction'!B10 -> ⏳ Non audité | K29: ='Vinci Construction'!H10 -> 0
B30: 19 | C30: AXA | H30: Planifié | I30: =AXA!A10 -> 0 | J30: =AXA!B10 -> ⏳ Non audité | K30: =AXA!H10 -> 0
B31: 20 | C31: OCP | H31: En cours | I31: =OCP!A10 -> 3.1538462 | J31: =OCP!B10 -> A Surveiller | K31: =OCP!H10 -> 5

Sheet CONSOLIDATION
A1: CONSOLIDATION GLOBALE — FY27
A6: KPIs GLOBAUX
A7: Score Moyen | B7: NC Maj | C7: NC Min | D7: Obs | E7: OFI | F7: BP | G7: TOTAL
A8: =IFERROR(AVERAGE('CDG Sécurité'!B10,RAM!A10,'Min. Intérieur'!A10,'CDG Capital'!A10,AtlanticRe!A10,'Client A'!A10,Servier!A10,MEN!A10,ADM!A10,'CDG DC'!A10,'CDG ITOC'!A10,BPOST!A10,'Graphtalk AIA'!A10,'ONCF APPS'!A10,'ONCF MW'!A10,ANEF!A10,Carrefour!A10,'Vinci Construction'!A10,AXA!A10,OCP!A10),0) -> 1.366014 | B8: ='CDG Sécurité'!D10+RAM!C10+'Min. Intérieur'!C10+'CDG Capital'!C10+AtlanticRe!C10+'Client A'!C10+Servier!C10+MEN!C10+ADM!C10+'CDG DC'!C10+'CDG ITOC'!C10+BPOST!C10+'Graphtalk AIA'!C10+'ONCF APPS'!C10+'ONCF MW'!C10+ANEF!C10+Carrefour!C10+'Vinci Construction'!C10+AXA!C10+OCP!C10 -> 1 | C8: ='CDG Sécurité'!E10+RAM!D10+'Min. Intérieur'!D10+'CDG Capital'!D10+AtlanticRe!D10+'Client A'!D10+Servier!D10+MEN!D10+ADM!D10+'CDG DC'!D10+'CDG ITOC'!D10+BPOST!D10+'Graphtalk AIA'!D10+'ONCF APPS'!D10+'ONCF MW'!D10+ANEF!D10+Carrefour!D10+'Vinci Construction'!D10+AXA!D10+OCP!D10 -> 44 | D8: ='CDG Sécurité'!F10+RAM!E10+'Min. Intérieur'!E10+'CDG Capital'!E10+AtlanticRe!E10+'Client A'!E10+Servier!E10+MEN!E10+ADM!E10+'CDG DC'!E10+'CDG ITOC'!E10+BPOST!E10+'Graphtalk AIA'!E10+'ONCF APPS'!E10+'ONCF MW'!E10+ANEF!E10+Carrefour!E10+'Vinci Construction'!E10+AXA!E10+OCP!E10 -> 6 | E8: ='CDG Sécurité'!G10+RAM!F10+'Min. Intérieur'!F10+'CDG Capital'!F10+AtlanticRe!F10+'Client A'!F10+Servier!F10+MEN!F10+ADM!F10+'CDG DC'!F10+'CDG ITOC'!F10+BPOST!F10+'Graphtalk AIA'!F10+'ONCF APPS'!F10+'ONCF MW'!F10+ANEF!F10+Carrefour!F10+'Vinci Construction'!F10+AXA!F10+OCP!F10 -> 0 | F8: ='CDG Sécurité'!H10+RAM!G10+'Min. Intérieur'!G10+'CDG Capital'!G10+AtlanticRe!G10+'Client A'!G10+Servier!G10+MEN!G10+ADM!G10+'CDG DC'!G10+'CDG ITOC'!G10+BPOST!G10+'Graphtalk AIA'!G10+'ONCF APPS'!G10+'ONCF MW'!G10+ANEF!G10+Carrefour!G10+'Vinci Construction'!G10+AXA!G10+OCP!G10 -> 7 | G8: =B8+C8+D8+E8 -> 51
A10: SYNTHÈSE PAR COMPTE
A11: N° | B11: Compte | C11: Score | D11: Badge | E11: NC Maj | F11: NC Min | G11: Obs | H11: OFI | I11: BP | J11: Total | K11: % NC | L11: Priorité
A12: 1 | B12: CDG Sécurité | C12: ='CDG Sécurité'!B10 -> 2.3636364 | D12: ='DASHBOARD AUDITS'!J12 -> À Risque | E12: ='CDG Sécurité'!D10 -> 1 | F12: ='CDG Sécurité'!E10 -> 5 | G12: ='CDG Sécurité'!F10 -> 1 | H12: ='CDG Sécurité'!G10 -> 0 | I12: ='CDG Sécurité'!H10 -> 0 | J12: =E12+F12+G12+H12 -> 7 | K12: =IFERROR((E12+F12)/J12,0) -> 0.85714286 | L12: =IF(E12>0,"🔴 Critique",IF(J12>5,"🟠 Élevée",IF(J12>2,"🟡 Modérée","🟢 Faible"))) -> 🔴 Critique
A13: 2 | B13: RAM | C13: =RAM!A10 -> 3.1538462 | D13: ='DASHBOARD AUDITS'!J13 -> A Surveiller | E13: =RAM!C10 -> 0 | F13: =RAM!D10 -> 4 | G13: =RAM!E10 -> 1 | H13: =RAM!F10 -> 0 | I13: =RAM!G10 -> 1 | J13: =E13+F13+G13+H13 -> 5 | K13: =IFERROR((E13+F13)/J13,0) -> 0.8 | L13: =IF(E13>0,"🔴 Critique",IF(J13>5,"🟠 Élevée",IF(J13>2,"🟡 Modérée","🟢 Faible"))) -> 🟡 Modérée
A14: 3 | B14: Min. Intérieur | C14: ='Min. Intérieur'!A10 -> 3.3636364 | D14: ='DASHBOARD AUDITS'!J14 -> A Surveiller | E14: ='Min. Intérieur'!C10 -> 0 | F14: ='Min. Intérieur'!D10 -> 7 | G14: ='Min. Intérieur'!E10 -> 0 | H14: ='Min. Intérieur'!F10 -> 0 | I14: ='Min. Intérieur'!G10 -> 2 | J14: =E14+F14+G14+H14 -> 7 | K14: =IFERROR((E14+F14)/J14,0) -> 1 | L14: =IF(E14>0,"🔴 Critique",IF(J14>5,"🟠 Élevée",IF(J14>2,"🟡 Modérée","🟢 Faible"))) -> 🟠 Élevée
A15: 4 | B15: CDG Capital | C15: ='CDG Capital'!A10 -> 2.4545455 | D15: ='DASHBOARD AUDITS'!J15 -> À Risque | E15: ='CDG Capital'!C10 -> 0 | F15: ='CDG Capital'!D10 -> 5 | G15: ='CDG Capital'!E10 -> 2 | H15: ='CDG Capital'!F10 -> 0 | I15: ='CDG Capital'!G10 -> 0 | J15: =E15+F15+G15+H15 -> 7 | K15: =IFERROR((E15+F15)/J15,0) -> 0.71428571 | L15: =IF(E15>0,"🔴 Critique",IF(J15>5,"🟠 Élevée",IF(J15>2,"🟡 Modérée","🟢 Faible"))) -> 🟠 Élevée
A16: 5 | B16: AtlanticRe | C16: =AtlanticRe!A10 -> 2.9615385 | D16: ='DASHBOARD AUDITS'!J16 -> A Surveiller | E16: =AtlanticRe!C10 -> 0 | F16: =AtlanticRe!D10 -> 5 | G16: =AtlanticRe!E10 -> 0 | H16: =AtlanticRe!F10 -> 0 | I16: =AtlanticRe!G10 -> 2 | J16: =E16+F16+G16+H16 -> 5 | K16: =IFERROR((E16+F16)/J16,0) -> 1 | L16: =IF(E16>0,"🔴 Critique",IF(J16>5,"🟠 Élevée",IF(J16>2,"🟡 Modérée","🟢 Faible"))) -> 🟡 Modérée
A17: 6 | B17: Client A | C17: ='Client A'!A10 -> 0 | D17: ='DASHBOARD AUDITS'!J17 -> ⏳ Non audité | E17: ='Client A'!C10 -> 0 | F17: ='Client A'!D10 -> 0 | G17: ='Client A'!E10 -> 0 | H17: ='Client A'!F10 -> 0 | I17: ='Client A'!G10 -> 0 | J17: =E17+F17+G17+H17 -> 0 | K17: =IFERROR((E17+F17)/J17,0) -> 0 | L17: =IF(E17>0,"🔴 Critique",IF(J17>5,"🟠 Élevée",IF(J17>2,"🟡 Modérée","🟢 Faible"))) -> 🟢 Faible
A18: 7 | B18: Servier | C18: =Servier!A10 -> 3.6 | D18: ='DASHBOARD AUDITS'!J18 -> Performant | E18: =Servier!C10 -> 0 | F18: =Servier!D10 -> 4 | G18: =Servier!E10 -> 0 | H18: =Servier!F10 -> 0 | I18: =Servier!G10 -> 0 | J18: =E18+F18+G18+H18 -> 4 | K18: =IFERROR((E18+F18)/J18,0) -> 1 | L18: =IF(E18>0,"🔴 Critique",IF(J18>5,"🟠 Élevée",IF(J18>2,"🟡 Modérée","🟢 Faible"))) -> 🟡 Modérée
A19: 8 | B19: MEN | C19: =MEN!A10 -> 3.1538462 | D19: ='DASHBOARD AUDITS'!J19 -> A Surveiller | E19: =MEN!C10 -> 0 | F19: =MEN!D10 -> 5 | G19: =MEN!E10 -> 0 | H19: =MEN!F10 -> 0 | I19: =MEN!G10 -> 1 | J19: =E19+F19+G19+H19 -> 5 | K19: =IFERROR((E19+F19)/J19,0) -> 1 | L19: =IF(E19>0,"🔴 Critique",IF(J19>5,"🟠 Élevée",IF(J19>2,"🟡 Modérée","🟢 Faible"))) -> 🟡 Modérée
A20: 9 | B20: ADM | C20: =ADM!A10 -> 0 | D20: ='DASHBOARD AUDITS'!J20 -> ⏳ Non audité | E20: =ADM!C10 -> 0 | F20: =ADM!D10 -> 0 | G20: =ADM!E10 -> 0 | H20: =ADM!F10 -> 0 | I20: =ADM!G10 -> 0 | J20: =E20+F20+G20+H20 -> 0 | K20: =IFERROR((E20+F20)/J20,0) -> 0 | L20: =IF(E20>0,"🔴 Critique",IF(J20>5,"🟠 Élevée",IF(J20>2,"🟡 Modérée","🟢 Faible"))) -> 🟢 Faible
A21: 10 | B21: CDG DC | C21: ='CDG DC'!A10 -> 0 | D21: ='DASHBOARD AUDITS'!J21 -> ⏳ Non audité | E21: ='CDG DC'!C10 -> 0 | F21: ='CDG DC'!D10 -> 0 | G21: ='CDG DC'!E10 -> 0 | H21: ='CDG DC'!F10 -> 0 | I21: ='CDG DC'!G10 -> 0 | J21: =E21+F21+G21+H21 -> 0 | K21: =IFERROR((E21+F21)/J21,0) -> 0 | L21: =IF(E21>0,"🔴 Critique",IF(J21>5,"🟠 Élevée",IF(J21>2,"🟡 Modérée","🟢 Faible"))) -> 🟢 Faible
A22: 11 | B22: CDG ITOC | C22: ='CDG ITOC'!A10 -> 0 | D22: ='DASHBOARD AUDITS'!J22 -> ⏳ Non audité | E22: ='CDG ITOC'!C10 -> 0 | F22: ='CDG ITOC'!D10 -> 0 | G22: ='CDG ITOC'!E10 -> 0 | H22: ='CDG ITOC'!F10 -> 0 | I22: ='CDG ITOC'!G10 -> 0 | J22: =E22+F22+G22+H22 -> 0 | K22: =IFERROR((E22+F22)/J22,0) -> 0 | L22: =IF(E22>0,"🔴 Critique",IF(J22>5,"🟠 Élevée",IF(J22>2,"🟡 Modérée","🟢 Faible"))) -> 🟢 Faible
A23: 12 | B23: BPOST | C23: =BPOST!A10 -> 0 | D23: ='DASHBOARD AUDITS'!J23 -> ⏳ Non audité | E23: =BPOST!C10 -> 0 | F23: =BPOST!D10 -> 0 | G23: =BPOST!E10 -> 0 | H23: =BPOST!F10 -> 0 | I23: =BPOST!G10 -> 0 | J23: =E23+F23+G23+H23 -> 0 | K23: =IFERROR((E23+F23)/J23,0) -> 0 | L23: =IF(E23>0,"🔴 Critique",IF(J23>5,"🟠 Élevée",IF(J23>2,"🟡 Modérée","🟢 Faible"))) -> 🟢 Faible
A24: 13 | B24: Graphtalk AIA | C24: ='Graphtalk AIA'!A10 -> 0 | D24: ='DASHBOARD AUDITS'!J24 -> ⏳ Non audité | E24: ='Graphtalk AIA'!C10 -> 0 | F24: ='Graphtalk AIA'!D10 -> 0 | G24: ='Graphtalk AIA'!E10 -> 0 | H24: ='Graphtalk AIA'!F10 -> 0 | I24: ='Graphtalk AIA'!G10 -> 0 | J24: =E24+F24+G24+H24 -> 0 | K24: =IFERROR((E24+F24)/J24,0) -> 0 | L24: =IF(E24>0,"🔴 Critique",IF(J24>5,"🟠 Élevée",IF(J24>2,"🟡 Modérée","🟢 Faible"))) -> 🟢 Faible
A25: 14 | B25: ONCF APPS | C25: ='ONCF APPS'!A10 -> 0 | D25: ='DASHBOARD AUDITS'!J25 -> ⏳ Non audité | E25: ='ONCF APPS'!C10 -> 0 | F25: ='ONCF APPS'!D10 -> 0 | G25: ='ONCF APPS'!E10 -> 0 | H25: ='ONCF APPS'!F10 -> 0 | I25: ='ONCF APPS'!G10 -> 0 | J25: =E25+F25+G25+H25 -> 0 | K25: =IFERROR((E25+F25)/J25,0) -> 0 | L25: =IF(E25>0,"🔴 Critique",IF(J25>5,"🟠 Élevée",IF(J25>2,"🟡 Modérée","🟢 Faible"))) -> 🟢 Faible
A26: 15 | B26: ONCF MW | C26: ='ONCF MW'!A10 -> 3.1153846 | D26: ='DASHBOARD AUDITS'!J26 -> A Surveiller | E26: ='ONCF MW'!C10 -> 0 | F26: ='ONCF MW'!D10 -> 4 | G26: ='ONCF MW'!E10 -> 2 | H26: ='ONCF MW'!F10 -> 0 | I26: ='ONCF MW'!G10 -> 0 | J26: =E26+F26+G26+H26 -> 6 | K26: =IFERROR((E26+F26)/J26,0) -> 0.66666667 | L26: =IF(E26>0,"🔴 Critique",IF(J26>5,"🟠 Élevée",IF(J26>2,"🟡 Modérée","🟢 Faible"))) -> 🟠 Élevée
A27: 16 | B27: ANEF | C27: =ANEF!A10 -> 0 | D27: ='DASHBOARD AUDITS'!J27 -> ⏳ Non audité | E27: =ANEF!C10 -> 0 | F27: =ANEF!D10 -> 0 | G27: =ANEF!E10 -> 0 | H27: =ANEF!F10 -> 0 | I27: =ANEF!G10 -> 0 | J27: =E27+F27+G27+H27 -> 0 | K27: =IFERROR((E27+F27)/J27,0) -> 0 | L27: =IF(E27>0,"🔴 Critique",IF(J27>5,"🟠 Élevée",IF(J27>2,"🟡 Modérée","🟢 Faible"))) -> 🟢 Faible
A28: 17 | B28: Carrefour | C28: =Carrefour!A10 -> 0 | D28: ='DASHBOARD AUDITS'!J28 -> ⏳ Non audité | E28: =Carrefour!C10 -> 0 | F28: =Carrefour!D10 -> 0 | G28: =Carrefour!E10 -> 0 | H28: =Carrefour!F10 -> 0 | I28: =Carrefour!G10 -> 0 | J28: =E28+F28+G28+H28 -> 0 | K28: =IFERROR((E28+F28)/J28,0) -> 0 | L28: =IF(E28>0,"🔴 Critique",IF(J28>5,"🟠 Élevée",IF(J28>2,"🟡 Modérée","🟢 Faible"))) -> 🟢 Faible
A29: 18 | B29: Vinci Construction | C29: ='Vinci Construction'!A10 -> 0 | D29: ='DASHBOARD AUDITS'!J29 -> ⏳ Non audité | E29: ='Vinci Construction'!C10 -> 0 | F29: ='Vinci Construction'!D10 -> 0 | G29: ='Vinci Construction'!E10 -> 0 | H29: ='Vinci Construction'!F10 -> 0 | I29: ='Vinci Construction'!G10 -> 0 | J29: =E29+F29+G29+H29 -> 0 | K29: =IFERROR((E29+F29)/J29,0) -> 0 | L29: =IF(E29>0,"🔴 Critique",IF(J29>5,"🟠 Élevée",IF(J29>2,"🟡 Modérée","🟢 Faible"))) -> 🟢 Faible
A30: 19 | B30: AXA | C30: =AXA!A10 -> 0 | D30: ='DASHBOARD AUDITS'!J30 -> ⏳ Non audité | E30: =AXA!C10 -> 0 | F30: =AXA!D10 -> 0 | G30: =AXA!E10 -> 0 | H30: =AXA!F10 -> 0 | I30: =AXA!G10 -> 0 | J30: =E30+F30+G30+H30 -> 0 | K30: =IFERROR((E30+F30)/J30,0) -> 0 | L30: =IF(E30>0,"🔴 Critique",IF(J30>5,"🟠 Élevée",IF(J30>2,"🟡 Modérée","🟢 Faible"))) -> 🟢 Faible
A31: 20 | B31: OCP | C31: =OCP!A10 -> 3.1538462 | D31: ='DASHBOARD AUDITS'!J31 -> A Surveiller | E31: =OCP!C10 -> 0 | F31: =OCP!D10 -> 5 | G31: =OCP!E10 -> 0 | H31: =OCP!F10 -> 0 | I31: =OCP!G10 -> 1 | J31: =E31+F31+G31+H31 -> 5 | K31: =IFERROR((E31+F31)/J31,0) -> 1 | L31: =IF(E31>0,"🔴 Critique",IF(J31>5,"🟠 Élevée",IF(J31>2,"🟡 Modérée","🟢 Faible"))) -> 🟡 Modérée
A34: HEATMAP MATURITÉ PAR CHAPITRE
A35: Ch | B35: Libellé | C35: CDG Sé | D35: RAM | E35: Min. I | F35: CDG Ca | G35: Atlant | H35: Client A | I35: Servier | J35: MEN | K35: ADM | L35: CDG DC | M35: CDG IT | N35: BPOST | O35: Grapht | P35: ONCF A | Q35: OCP MW | R35: ANEF | S35: Carref | T35: Vinci | U35: AXA | V35: OCP | W35: Moy.
A36: Ch4 | B36: Contexte | C36: ='CDG Sécurité'!E55 -> 1 | D36: =RAM!D55 -> 3 | E36: ='Min. Intérieur'!D55 -> 2 | F36: ='CDG Capital'!D55 -> 1 | G36: =AtlanticRe!D55 -> 3 | H36: ='Client A'!D55 -> 0 | I36: =Servier!D55 -> 2.5 | J36: =MEN!D55 -> 3.5 | K36: =ADM!D55 -> 0 | L36: ='CDG DC'!D55 -> 0 | M36: ='CDG ITOC'!D55 -> 0 | N36: =BPOST!D55 -> 0 | O36: ='Graphtalk AIA'!D55 -> 0 | P36: ='ONCF APPS'!D55 -> 0 | Q36: ='ONCF MW'!D55 -> 3 | R36: =ANEF!D55 -> 0 | S36: =Carrefour!D55 -> 0 | T36: ='Vinci Construction'!D55 -> 0 | U36: =AXA!D55 -> 0 | V36: =OCP!D55 -> 3.5 | W36: =IFERROR(AVERAGE(C36:V36),0) -> 1.125
A37: Ch5 | B37: Leadership | C37: ='CDG Sécurité'!E56 -> 3 | D37: =RAM!D56 -> 3.5 | E37: ='Min. Intérieur'!D56 -> 4 | F37: ='CDG Capital'!D56 -> 0 | G37: =AtlanticRe!D56 -> 3.5 | H37: ='Client A'!D56 -> 0 | I37: =Servier!D56 -> 3 | J37: =MEN!D56 -> 3.5 | K37: =ADM!D56 -> 0 | L37: ='CDG DC'!D56 -> 0 | M37: ='CDG ITOC'!D56 -> 0 | N37: =BPOST!D56 -> 0 | O37: ='Graphtalk AIA'!D56 -> 0 | P37: ='ONCF APPS'!D56 -> 0 | Q37: ='ONCF MW'!D56 -> 3.5 | R37: =ANEF!D56 -> 0 | S37: =Carrefour!D56 -> 0 | T37: ='Vinci Construction'!D56 -> 0 | U37: =AXA!D56 -> 0 | V37: =OCP!D56 -> 3.5 | W37: =IFERROR(AVERAGE(C37:V37),0) -> 1.375
A38: Ch6 | B38: Planification | C38: ='CDG Sécurité'!E57 -> 2.3333333 | D38: =RAM!D57 -> 2.6666667 | E38: ='Min. Intérieur'!D57 -> 2 | F38: ='CDG Capital'!D57 -> 0 | G38: =AtlanticRe!D57 -> 2.6666667 | H38: ='Client A'!D57 -> 0 | I38: =Servier!D57 -> 3.5 | J38: =MEN!D57 -> 2.6666667 | K38: =ADM!D57 -> 0 | L38: ='CDG DC'!D57 -> 0 | M38: ='CDG ITOC'!D57 -> 0 | N38: =BPOST!D57 -> 0 | O38: ='Graphtalk AIA'!D57 -> 0 | P38: ='ONCF APPS'!D57 -> 0 | Q38: ='ONCF MW'!D57 -> 3 | R38: =ANEF!D57 -> 0 | S38: =Carrefour!D57 -> 0 | T38: ='Vinci Construction'!D57 -> 0 | U38: =AXA!D57 -> 0 | V38: =OCP!D57 -> 2.6666667 | W38: =IFERROR(AVERAGE(C38:V38),0) -> 1.075
A39: Ch7 | B39: Support | C39: ='CDG Sécurité'!E58 -> 2.3333333 | D39: =RAM!D58 -> 2 | E39: ='Min. Intérieur'!D58 -> 2 | F39: ='CDG Capital'!D58 -> 0 | G39: =AtlanticRe!D58 -> 2 | H39: ='Client A'!D58 -> 0 | I39: =Servier!D58 -> 3.6666667 | J39: =MEN!D58 -> 2.75 | K39: =ADM!D58 -> 0 | L39: ='CDG DC'!D58 -> 0 | M39: ='CDG ITOC'!D58 -> 0 | N39: =BPOST!D58 -> 0 | O39: ='Graphtalk AIA'!D58 -> 0 | P39: ='ONCF APPS'!D58 -> 0 | Q39: ='ONCF MW'!D58 -> 2.75 | R39: =ANEF!D58 -> 0 | S39: =Carrefour!D58 -> 0 | T39: ='Vinci Construction'!D58 -> 0 | U39: =AXA!D58 -> 0 | V39: =OCP!D58 -> 2.75 | W39: =IFERROR(AVERAGE(C39:V39),0) -> 1.0125
A40: Ch8 | B40: Réalisation | C40: ='CDG Sécurité'!E59 -> 0 | D40: =RAM!D59 -> 3.4 | E40: ='Min. Intérieur'!D59 -> 4 | F40: ='CDG Capital'!D59 -> 0 | G40: =AtlanticRe!D59 -> 3.1 | H40: ='Client A'!D59 -> 0 | I40: =Servier!D59 -> 3.3333333 | J40: =MEN!D59 -> 3.2 | K40: =ADM!D59 -> 0 | L40: ='CDG DC'!D59 -> 0 | M40: ='CDG ITOC'!D59 -> 0 | N40: =BPOST!D59 -> 0 | O40: ='Graphtalk AIA'!D59 -> 0 | P40: ='ONCF APPS'!D59 -> 0 | Q40: ='ONCF MW'!D59 -> 3.2 | R40: =ANEF!D59 -> 0 | S40: =Carrefour!D59 -> 0 | T40: ='Vinci Construction'!D59 -> 0 | U40: =AXA!D59 -> 0 | V40: =OCP!D59 -> 3.2 | W40: =IFERROR(AVERAGE(C40:V40),0) -> 1.1716667
A41: Ch9 | B41: Performance | C41: ='CDG Sécurité'!E60 -> 0 | D41: =RAM!D60 -> 3.6666667 | E41: ='Min. Intérieur'!D60 -> 4 | F41: ='CDG Capital'!D60 -> 0 | G41: =AtlanticRe!D60 -> 3.5 | H41: ='Client A'!D60 -> 0 | I41: =Servier!D60 -> 3.5 | J41: =MEN!D60 -> 3.6666667 | K41: =ADM!D60 -> 0 | L41: ='CDG DC'!D60 -> 0 | M41: ='CDG ITOC'!D60 -> 0 | N41: =BPOST!D60 -> 0 | O41: ='Graphtalk AIA'!D60 -> 0 | P41: ='ONCF APPS'!D60 -> 0 | Q41: ='ONCF MW'!D60 -> 3.3333333 | R41: =ANEF!D60 -> 0 | S41: =Carrefour!D60 -> 0 | T41: ='Vinci Construction'!D60 -> 0 | U41: =AXA!D60 -> 0 | V41: =OCP!D60 -> 3.6666667 | W41: =IFERROR(AVERAGE(C41:V41),0) -> 1.2666667
A42: Ch10 | B42: Amélioration | C42: ='CDG Sécurité'!E61 -> 0 | D42: =RAM!D61 -> 4 | E42: ='Min. Intérieur'!D61 -> 4 | F42: ='CDG Capital'!D61 -> 0 | G42: =AtlanticRe!D61 -> 3 | H42: ='Client A'!D61 -> 0 | I42: =Servier!D61 -> 3 | J42: =MEN!D61 -> 3 | K42: =ADM!D61 -> 0 | L42: ='CDG DC'!D61 -> 0 | M42: ='CDG ITOC'!D61 -> 0 | N42: =BPOST!D61 -> 0 | O42: ='Graphtalk AIA'!D61 -> 0 | P42: ='ONCF APPS'!D61 -> 0 | Q42: ='ONCF MW'!D61 -> 3 | R42: =ANEF!D61 -> 0 | S42: =Carrefour!D61 -> 0 | T42: ='Vinci Construction'!D61 -> 0 | U42: =AXA!D61 -> 0 | V42: =OCP!D61 -> 3 | W42: =IFERROR(AVERAGE(C42:V42),0) -> 1.15

Sheet ANALYSE FINDINGS
A1: ANALYSE DES FINDINGS PAR LIBELLÉ TERRAIN — FY27
A3: 1. NOMBRE DE FINDINGS PAR LIBELLÉ TERRAIN (GLOBAL)
A5: N° | B5: Clause | C5: Libellé Terrain | D5: NC Maj | E5: NC Min | F5: Obs | G5: OFI | H5: Total | I5: % Total | J5: Criticité
A6: 1 | B6: 4.1 | C6: Connaissance de notre environnement | D6: =COUNTIF('CDG Sécurité'!K15,"NC Majeure")+COUNTIF(RAM!J15,"NC Majeure")+COUNTIF('Min. Intérieur'!J15,"NC Majeure")+COUNTIF('CDG Capital'!J15,"NC Majeure")+COUNTIF(AtlanticRe!J15,"NC Majeure")+COUNTIF('Client A'!J15,"NC Majeure")+COUNTIF(Servier!J15,"NC Majeure")+COUNTIF(MEN!J15,"NC Majeure")+COUNTIF(ADM!J15,"NC Majeure")+COUNTIF('CDG DC'!J15,"NC Majeure")+COUNTIF('CDG ITOC'!J15,"NC Majeure")+COUNTIF(BPOST!J15,"NC Majeure")+COUNTIF('Graphtalk AIA'!J15,"NC Majeure")+COUNTIF('ONCF APPS'!J15,"NC Majeure")+COUNTIF('ONCF MW'!J15,"NC Majeure")+COUNTIF(ANEF!J15,"NC Majeure")+COUNTIF(Carrefour!J15,"NC Majeure")+COUNTIF('Vinci Construction'!J15,"NC Majeure")+COUNTIF(AXA!J15,"NC Majeure")+COUNTIF(OCP!J15,"NC Majeure") -> 1 | E6: =COUNTIF('CDG Sécurité'!K15,"NC Mineure")+COUNTIF(RAM!J15,"NC Mineure")+COUNTIF('Min. Intérieur'!J15,"NC Mineure")+COUNTIF('CDG Capital'!J15,"NC Mineure")+COUNTIF(AtlanticRe!J15,"NC Mineure")+COUNTIF('Client A'!J15,"NC Mineure")+COUNTIF(Servier!J15,"NC Mineure")+COUNTIF(MEN!J15,"NC Mineure")+COUNTIF(ADM!J15,"NC Mineure")+COUNTIF('CDG DC'!J15,"NC Mineure")+COUNTIF('CDG ITOC'!J15,"NC Mineure")+COUNTIF(BPOST!J15,"NC Mineure")+COUNTIF('Graphtalk AIA'!J15,"NC Mineure")+COUNTIF('ONCF APPS'!J15,"NC Mineure")+COUNTIF('ONCF MW'!J15,"NC Mineure")+COUNTIF(ANEF!J15,"NC Mineure")+COUNTIF(Carrefour!J15,"NC Mineure")+COUNTIF('Vinci Construction'!J15,"NC Mineure")+COUNTIF(AXA!J15,"NC Mineure")+COUNTIF(OCP!J15,"NC Mineure") -> 7 | F6: =COUNTIF('CDG Sécurité'!K15,"Observation")+COUNTIF(RAM!J15,"Observation")+COUNTIF('Min. Intérieur'!J15,"Observation")+COUNTIF('CDG Capital'!J15,"Observation")+COUNTIF(AtlanticRe!J15,"Observation")+COUNTIF('Client A'!J15,"Observation")+COUNTIF(Servier!J15,"Observation")+COUNTIF(MEN!J15,"Observation")+COUNTIF(ADM!J15,"Observation")+COUNTIF('CDG DC'!J15,"Observation")+COUNTIF('CDG ITOC'!J15,"Observation")+COUNTIF(BPOST!J15,"Observation")+COUNTIF('Graphtalk AIA'!J15,"Observation")+COUNTIF('ONCF APPS'!J15,"Observation")+COUNTIF('ONCF MW'!J15,"Observation")+COUNTIF(ANEF!J15,"Observation")+COUNTIF(Carrefour!J15,"Observation")+COUNTIF('Vinci Construction'!J15,"Observation")+COUNTIF(AXA!J15,"Observation")+COUNTIF(OCP!J15,"Observation") -> 1 | G6: =COUNTIF('CDG Sécurité'!K15,"OFI")+COUNTIF(RAM!J15,"OFI")+COUNTIF('Min. Intérieur'!J15,"OFI")+COUNTIF('CDG Capital'!J15,"OFI")+COUNTIF(AtlanticRe!J15,"OFI")+COUNTIF('Client A'!J15,"OFI")+COUNTIF(Servier!J15,"OFI")+COUNTIF(MEN!J15,"OFI")+COUNTIF(ADM!J15,"OFI")+COUNTIF('CDG DC'!J15,"OFI")+COUNTIF('CDG ITOC'!J15,"OFI")+COUNTIF(BPOST!J15,"OFI")+COUNTIF('Graphtalk AIA'!J15,"OFI")+COUNTIF('ONCF APPS'!J15,"OFI")+COUNTIF('ONCF MW'!J15,"OFI")+COUNTIF(ANEF!J15,"OFI")+COUNTIF(Carrefour!J15,"OFI")+COUNTIF('Vinci Construction'!J15,"OFI")+COUNTIF(AXA!J15,"OFI")+COUNTIF(OCP!J15,"OFI") -> 0 | H6: =D6+E6+F6+G6 -> 9 | I6: =IFERROR(H6/H43,0) -> 0.17647059 | J6: =IF(D6>0,"🔴 Critique",IF(H6>5,"🟠 Fort",IF(H6>2,"🟡 Modéré",IF(H6>0,"🔵 Faible","✅ Aucun")))) -> 🔴 Critique
A7: 2 | B7: 4.2 | C7: Écoute des parties prenantes | D7: =COUNTIF('CDG Sécurité'!K16,"NC Majeure")+COUNTIF(RAM!J16,"NC Majeure")+COUNTIF('Min. Intérieur'!J16,"NC Majeure")+COUNTIF('CDG Capital'!J18,"NC Majeure")+COUNTIF(AtlanticRe!J16,"NC Majeure")+COUNTIF('Client A'!J16,"NC Majeure")+COUNTIF(Servier!J16,"NC Majeure")+COUNTIF(MEN!J16,"NC Majeure")+COUNTIF(ADM!J16,"NC Majeure")+COUNTIF('CDG DC'!J16,"NC Majeure")+COUNTIF('CDG ITOC'!J16,"NC Majeure")+COUNTIF(BPOST!J16,"NC Majeure")+COUNTIF('Graphtalk AIA'!J16,"NC Majeure")+COUNTIF('ONCF APPS'!J16,"NC Majeure")+COUNTIF('ONCF MW'!J16,"NC Majeure")+COUNTIF(ANEF!J16,"NC Majeure")+COUNTIF(Carrefour!J16,"NC Majeure")+COUNTIF('Vinci Construction'!J16,"NC Majeure")+COUNTIF(AXA!J16,"NC Majeure")+COUNTIF(OCP!J16,"NC Majeure") -> 0 | E7: =COUNTIF('CDG Sécurité'!K16,"NC Mineure")+COUNTIF(RAM!J16,"NC Mineure")+COUNTIF('Min. Intérieur'!J16,"NC Mineure")+COUNTIF('CDG Capital'!J18,"NC Mineure")+COUNTIF(AtlanticRe!J16,"NC Mineure")+COUNTIF('Client A'!J16,"NC Mineure")+COUNTIF(Servier!J16,"NC Mineure")+COUNTIF(MEN!J16,"NC Mineure")+COUNTIF(ADM!J16,"NC Mineure")+COUNTIF('CDG DC'!J16,"NC Mineure")+COUNTIF('CDG ITOC'!J16,"NC Mineure")+COUNTIF(BPOST!J16,"NC Mineure")+COUNTIF('Graphtalk AIA'!J16,"NC Mineure")+COUNTIF('ONCF APPS'!J16,"NC Mineure")+COUNTIF('ONCF MW'!J16,"NC Mineure")+COUNTIF(ANEF!J16,"NC Mineure")+COUNTIF(Carrefour!J16,"NC Mineure")+COUNTIF('Vinci Construction'!J16,"NC Mineure")+COUNTIF(AXA!J16,"NC Mineure")+COUNTIF(OCP!J16,"NC Mineure") -> 1 | F7: =COUNTIF('CDG Sécurité'!K16,"Observation")+COUNTIF(RAM!J16,"Observation")+COUNTIF('Min. Intérieur'!J16,"Observation")+COUNTIF('CDG Capital'!J18,"Observation")+COUNTIF(AtlanticRe!J16,"Observation")+COUNTIF('Client A'!J16,"Observation")+COUNTIF(Servier!J16,"Observation")+COUNTIF(MEN!J16,"Observation")+COUNTIF(ADM!J16,"Observation")+COUNTIF('CDG DC'!J16,"Observation")+COUNTIF('CDG ITOC'!J16,"Observation")+COUNTIF(BPOST!J16,"Observation")+COUNTIF('Graphtalk AIA'!J16,"Observation")+COUNTIF('ONCF APPS'!J16,"Observation")+COUNTIF('ONCF MW'!J16,"Observation")+COUNTIF(ANEF!J16,"Observation")+COUNTIF(Carrefour!J16,"Observation")+COUNTIF('Vinci Construction'!J16,"Observation")+COUNTIF(AXA!J16,"Observation")+COUNTIF(OCP!J16,"Observation") -> 0 | G7: =COUNTIF('CDG Sécurité'!K16,"OFI")+COUNTIF(RAM!J16,"OFI")+COUNTIF('Min. Intérieur'!J16,"OFI")+COUNTIF('CDG Capital'!J18,"OFI")+COUNTIF(AtlanticRe!J16,"OFI")+COUNTIF('Client A'!J16,"OFI")+COUNTIF(Servier!J16,"OFI")+COUNTIF(MEN!J16,"OFI")+COUNTIF(ADM!J16,"OFI")+COUNTIF('CDG DC'!J16,"OFI")+COUNTIF('CDG ITOC'!J16,"OFI")+COUNTIF(BPOST!J16,"OFI")+COUNTIF('Graphtalk AIA'!J16,"OFI")+COUNTIF('ONCF APPS'!J16,"OFI")+COUNTIF('ONCF MW'!J16,"OFI")+COUNTIF(ANEF!J16,"OFI")+COUNTIF(Carrefour!J16,"OFI")+COUNTIF('Vinci Construction'!J16,"OFI")+COUNTIF(AXA!J16,"OFI")+COUNTIF(OCP!J16,"OFI") -> 0 | H7: =D7+E7+F7+G7 -> 1 | I7: =IFERROR(H7/H43,0) -> 0.019607843 | J7: =IF(D7>0,"🔴 Critique",IF(H7>5,"🟠 Fort",IF(H7>2,"🟡 Modéré",IF(H7>0,"🔵 Faible","✅ Aucun")))) -> 🔵 Faible
A8: 3 | B8: 4.3 | C8: Périmètre de notre système qualité | D8: =COUNTIF('CDG Sécurité'!K17,"NC Majeure")+COUNTIF(RAM!J17,"NC Majeure")+COUNTIF('Min. Intérieur'!J17,"NC Majeure")+COUNTIF('CDG Capital'!J20,"NC Majeure")+COUNTIF(AtlanticRe!J17,"NC Majeure")+COUNTIF('Client A'!J17,"NC Majeure")+COUNTIF(Servier!J17,"NC Majeure")+COUNTIF(MEN!J17,"NC Majeure")+COUNTIF(ADM!J17,"NC Majeure")+COUNTIF('CDG DC'!J17,"NC Majeure")+COUNTIF('CDG ITOC'!J17,"NC Majeure")+COUNTIF(BPOST!J17,"NC Majeure")+COUNTIF('Graphtalk AIA'!J17,"NC Majeure")+COUNTIF('ONCF APPS'!J17,"NC Majeure")+COUNTIF('ONCF MW'!J17,"NC Majeure")+COUNTIF(ANEF!J17,"NC Majeure")+COUNTIF(Carrefour!J17,"NC Majeure")+COUNTIF('Vinci Construction'!J17,"NC Majeure")+COUNTIF(AXA!J17,"NC Majeure")+COUNTIF(OCP!J17,"NC Majeure") -> 0 | E8: =COUNTIF('CDG Sécurité'!K17,"NC Mineure")+COUNTIF(RAM!J17,"NC Mineure")+COUNTIF('Min. Intérieur'!J17,"NC Mineure")+COUNTIF('CDG Capital'!J20,"NC Mineure")+COUNTIF(AtlanticRe!J17,"NC Mineure")+COUNTIF('Client A'!J17,"NC Mineure")+COUNTIF(Servier!J17,"NC Mineure")+COUNTIF(MEN!J17,"NC Mineure")+COUNTIF(ADM!J17,"NC Mineure")+COUNTIF('CDG DC'!J17,"NC Mineure")+COUNTIF('CDG ITOC'!J17,"NC Mineure")+COUNTIF(BPOST!J17,"NC Mineure")+COUNTIF('Graphtalk AIA'!J17,"NC Mineure")+COUNTIF('ONCF APPS'!J17,"NC Mineure")+COUNTIF('ONCF MW'!J17,"NC Mineure")+COUNTIF(ANEF!J17,"NC Mineure")+COUNTIF(Carrefour!J17,"NC Mineure")+COUNTIF('Vinci Construction'!J17,"NC Mineure")+COUNTIF(AXA!J17,"NC Mineure")+COUNTIF(OCP!J17,"NC Mineure") -> 0 | F8: =COUNTIF('CDG Sécurité'!K17,"Observation")+COUNTIF(RAM!J17,"Observation")+COUNTIF('Min. Intérieur'!J17,"Observation")+COUNTIF('CDG Capital'!J20,"Observation")+COUNTIF(AtlanticRe!J17,"Observation")+COUNTIF('Client A'!J17,"Observation")+COUNTIF(Servier!J17,"Observation")+COUNTIF(MEN!J17,"Observation")+COUNTIF(ADM!J17,"Observation")+COUNTIF('CDG DC'!J17,"Observation")+COUNTIF('CDG ITOC'!J17,"Observation")+COUNTIF(BPOST!J17,"Observation")+COUNTIF('Graphtalk AIA'!J17,"Observation")+COUNTIF('ONCF APPS'!J17,"Observation")+COUNTIF('ONCF MW'!J17,"Observation")+COUNTIF(ANEF!J17,"Observation")+COUNTIF(Carrefour!J17,"Observation")+COUNTIF('Vinci Construction'!J17,"Observation")+COUNTIF(AXA!J17,"Observation")+COUNTIF(OCP!J17,"Observation") -> 0 | G8: =COUNTIF('CDG Sécurité'!K17,"OFI")+COUNTIF(RAM!J17,"OFI")+COUNTIF('Min. Intérieur'!J17,"OFI")+COUNTIF('CDG Capital'!J20,"OFI")+COUNTIF(AtlanticRe!J17,"OFI")+COUNTIF('Client A'!J17,"OFI")+COUNTIF(Servier!J17,"OFI")+COUNTIF(MEN!J17,"OFI")+COUNTIF(ADM!J17,"OFI")+COUNTIF('CDG DC'!J17,"OFI")+COUNTIF('CDG ITOC'!J17,"OFI")+COUNTIF(BPOST!J17,"OFI")+COUNTIF('Graphtalk AIA'!J17,"OFI")+COUNTIF('ONCF APPS'!J17,"OFI")+COUNTIF('ONCF MW'!J17,"OFI")+COUNTIF(ANEF!J17,"OFI")+COUNTIF(Carrefour!J17,"OFI")+COUNTIF('Vinci Construction'!J17,"OFI")+COUNTIF(AXA!J17,"OFI")+COUNTIF(OCP!J17,"OFI") -> 0 | H8: =D8+E8+F8+G8 -> 0 | I8: =IFERROR(H8/H43,0) -> 0 | J8: =IF(D8>0,"🔴 Critique",IF(H8>5,"🟠 Fort",IF(H8>2,"🟡 Modéré",IF(H8>0,"🔵 Faible","✅ Aucun")))) -> ✅ Aucun
A9: 4 | B9: 4.4 | C9: Cartographie de nos processus | D9: =COUNTIF('CDG Sécurité'!K18,"NC Majeure")+COUNTIF(RAM!J18,"NC Majeure")+COUNTIF('Min. Intérieur'!J18,"NC Majeure")+COUNTIF('CDG Capital'!J21,"NC Majeure")+COUNTIF(AtlanticRe!J18,"NC Majeure")+COUNTIF('Client A'!J18,"NC Majeure")+COUNTIF(Servier!J18,"NC Majeure")+COUNTIF(MEN!J18,"NC Majeure")+COUNTIF(ADM!J18,"NC Majeure")+COUNTIF('CDG DC'!J18,"NC Majeure")+COUNTIF('CDG ITOC'!J18,"NC Majeure")+COUNTIF(BPOST!J18,"NC Majeure")+COUNTIF('Graphtalk AIA'!J18,"NC Majeure")+COUNTIF('ONCF APPS'!J18,"NC Majeure")+COUNTIF('ONCF MW'!J18,"NC Majeure")+COUNTIF(ANEF!J18,"NC Majeure")+COUNTIF(Carrefour!J18,"NC Majeure")+COUNTIF('Vinci Construction'!J18,"NC Majeure")+COUNTIF(AXA!J18,"NC Majeure")+COUNTIF(OCP!J18,"NC Majeure") -> 0 | E9: =COUNTIF('CDG Sécurité'!K18,"NC Mineure")+COUNTIF(RAM!J18,"NC Mineure")+COUNTIF('Min. Intérieur'!J18,"NC Mineure")+COUNTIF('CDG Capital'!J21,"NC Mineure")+COUNTIF(AtlanticRe!J18,"NC Mineure")+COUNTIF('Client A'!J18,"NC Mineure")+COUNTIF(Servier!J18,"NC Mineure")+COUNTIF(MEN!J18,"NC Mineure")+COUNTIF(ADM!J18,"NC Mineure")+COUNTIF('CDG DC'!J18,"NC Mineure")+COUNTIF('CDG ITOC'!J18,"NC Mineure")+COUNTIF(BPOST!J18,"NC Mineure")+COUNTIF('Graphtalk AIA'!J18,"NC Mineure")+COUNTIF('ONCF APPS'!J18,"NC Mineure")+COUNTIF('ONCF MW'!J18,"NC Mineure")+COUNTIF(ANEF!J18,"NC Mineure")+COUNTIF(Carrefour!J18,"NC Mineure")+COUNTIF('Vinci Construction'!J18,"NC Mineure")+COUNTIF(AXA!J18,"NC Mineure")+COUNTIF(OCP!J18,"NC Mineure") -> 1 | F9: =COUNTIF('CDG Sécurité'!K18,"Observation")+COUNTIF(RAM!J18,"Observation")+COUNTIF('Min. Intérieur'!J18,"Observation")+COUNTIF('CDG Capital'!J21,"Observation")+COUNTIF(AtlanticRe!J18,"Observation")+COUNTIF('Client A'!J18,"Observation")+COUNTIF(Servier!J18,"Observation")+COUNTIF(MEN!J18,"Observation")+COUNTIF(ADM!J18,"Observation")+COUNTIF('CDG DC'!J18,"Observation")+COUNTIF('CDG ITOC'!J18,"Observation")+COUNTIF(BPOST!J18,"Observation")+COUNTIF('Graphtalk AIA'!J18,"Observation")+COUNTIF('ONCF APPS'!J18,"Observation")+COUNTIF('ONCF MW'!J18,"Observation")+COUNTIF(ANEF!J18,"Observation")+COUNTIF(Carrefour!J18,"Observation")+COUNTIF('Vinci Construction'!J18,"Observation")+COUNTIF(AXA!J18,"Observation")+COUNTIF(OCP!J18,"Observation") -> 1 | G9: =COUNTIF('CDG Sécurité'!K18,"OFI")+COUNTIF(RAM!J18,"OFI")+COUNTIF('Min. Intérieur'!J18,"OFI")+COUNTIF('CDG Capital'!J21,"OFI")+COUNTIF(AtlanticRe!J18,"OFI")+COUNTIF('Client A'!J18,"OFI")+COUNTIF(Servier!J18,"OFI")+COUNTIF(MEN!J18,"OFI")+COUNTIF(ADM!J18,"OFI")+COUNTIF('CDG DC'!J18,"OFI")+COUNTIF('CDG ITOC'!J18,"OFI")+COUNTIF(BPOST!J18,"OFI")+COUNTIF('Graphtalk AIA'!J18,"OFI")+COUNTIF('ONCF APPS'!J18,"OFI")+COUNTIF('ONCF MW'!J18,"OFI")+COUNTIF(ANEF!J18,"OFI")+COUNTIF(Carrefour!J18,"OFI")+COUNTIF('Vinci Construction'!J18,"OFI")+COUNTIF(AXA!J18,"OFI")+COUNTIF(OCP!J18,"OFI") -> 0 | H9: =D9+E9+F9+G9 -> 2 | I9: =IFERROR(H9/H43,0) -> 0.039215686 | J9: =IF(D9>0,"🔴 Critique",IF(H9>5,"🟠 Fort",IF(H9>2,"🟡 Modéré",IF(H9>0,"🔵 Faible","✅ Aucun")))) -> 🔵 Faible
A10: 5 | B10: 5.1 | C10: Engagement de la direction | D10: =COUNTIF('CDG Sécurité'!K19,"NC Majeure")+COUNTIF(RAM!J19,"NC Majeure")+COUNTIF('Min. Intérieur'!J19,"NC Majeure")+COUNTIF('CDG Capital'!J22,"NC Majeure")+COUNTIF(AtlanticRe!J19,"NC Majeure")+COUNTIF('Client A'!J19,"NC Majeure")+COUNTIF(Servier!J19,"NC Majeure")+COUNTIF(MEN!J19,"NC Majeure")+COUNTIF(ADM!J19,"NC Majeure")+COUNTIF('CDG DC'!J19,"NC Majeure")+COUNTIF('CDG ITOC'!J19,"NC Majeure")+COUNTIF(BPOST!J19,"NC Majeure")+COUNTIF('Graphtalk AIA'!J19,"NC Majeure")+COUNTIF('ONCF APPS'!J19,"NC Majeure")+COUNTIF('ONCF MW'!J19,"NC Majeure")+COUNTIF(ANEF!J19,"NC Majeure")+COUNTIF(Carrefour!J19,"NC Majeure")+COUNTIF('Vinci Construction'!J19,"NC Majeure")+COUNTIF(AXA!J19,"NC Majeure")+COUNTIF(OCP!J19,"NC Majeure") -> 0 | E10: =COUNTIF('CDG Sécurité'!K19,"NC Mineure")+COUNTIF(RAM!J19,"NC Mineure")+COUNTIF('Min. Intérieur'!J19,"NC Mineure")+COUNTIF('CDG Capital'!J22,"NC Mineure")+COUNTIF(AtlanticRe!J19,"NC Mineure")+COUNTIF('Client A'!J19,"NC Mineure")+COUNTIF(Servier!J19,"NC Mineure")+COUNTIF(MEN!J19,"NC Mineure")+COUNTIF(ADM!J19,"NC Mineure")+COUNTIF('CDG DC'!J19,"NC Mineure")+COUNTIF('CDG ITOC'!J19,"NC Mineure")+COUNTIF(BPOST!J19,"NC Mineure")+COUNTIF('Graphtalk AIA'!J19,"NC Mineure")+COUNTIF('ONCF APPS'!J19,"NC Mineure")+COUNTIF('ONCF MW'!J19,"NC Mineure")+COUNTIF(ANEF!J19,"NC Mineure")+COUNTIF(Carrefour!J19,"NC Mineure")+COUNTIF('Vinci Construction'!J19,"NC Mineure")+COUNTIF(AXA!J19,"NC Mineure")+COUNTIF(OCP!J19,"NC Mineure") -> 1 | F10: =COUNTIF('CDG Sécurité'!K19,"Observation")+COUNTIF(RAM!J19,"Observation")+COUNTIF('Min. Intérieur'!J19,"Observation")+COUNTIF('CDG Capital'!J22,"Observation")+COUNTIF(AtlanticRe!J19,"Observation")+COUNTIF('Client A'!J19,"Observation")+COUNTIF(Servier!J19,"Observation")+COUNTIF(MEN!J19,"Observation")+COUNTIF(ADM!J19,"Observation")+COUNTIF('CDG DC'!J19,"Observation")+COUNTIF('CDG ITOC'!J19,"Observation")+COUNTIF(BPOST!J19,"Observation")+COUNTIF('Graphtalk AIA'!J19,"Observation")+COUNTIF('ONCF APPS'!J19,"Observation")+COUNTIF('ONCF MW'!J19,"Observation")+COUNTIF(ANEF!J19,"Observation")+COUNTIF(Carrefour!J19,"Observation")+COUNTIF('Vinci Construction'!J19,"Observation")+COUNTIF(AXA!J19,"Observation")+COUNTIF(OCP!J19,"Observation") -> 0 | G10: =COUNTIF('CDG Sécurité'!K19,"OFI")+COUNTIF(RAM!J19,"OFI")+COUNTIF('Min. Intérieur'!J19,"OFI")+COUNTIF('CDG Capital'!J22,"OFI")+COUNTIF(AtlanticRe!J19,"OFI")+COUNTIF('Client A'!J19,"OFI")+COUNTIF(Servier!J19,"OFI")+COUNTIF(MEN!J19,"OFI")+COUNTIF(ADM!J19,"OFI")+COUNTIF('CDG DC'!J19,"OFI")+COUNTIF('CDG ITOC'!J19,"OFI")+COUNTIF(BPOST!J19,"OFI")+COUNTIF('Graphtalk AIA'!J19,"OFI")+COUNTIF('ONCF APPS'!J19,"OFI")+COUNTIF('ONCF MW'!J19,"OFI")+COUNTIF(ANEF!J19,"OFI")+COUNTIF(Carrefour!J19,"OFI")+COUNTIF('Vinci Construction'!J19,"OFI")+COUNTIF(AXA!J19,"OFI")+COUNTIF(OCP!J19,"OFI") -> 0 | H10: =D10+E10+F10+G10 -> 1 | I10: =IFERROR(H10/H43,0) -> 0.019607843 | J10: =IF(D10>0,"🔴 Critique",IF(H10>5,"🟠 Fort",IF(H10>2,"🟡 Modéré",IF(H10>0,"🔵 Faible","✅ Aucun")))) -> 🔵 Faible
A11: 6 | B11: 5.2 | C11: Notre politique qualité | D11: =COUNTIF('CDG Sécurité'!K20,"NC Majeure")+COUNTIF(RAM!J20,"NC Majeure")+COUNTIF('Min. Intérieur'!J20,"NC Majeure")+COUNTIF('CDG Capital'!J23,"NC Majeure")+COUNTIF(AtlanticRe!J20,"NC Majeure")+COUNTIF('Client A'!J20,"NC Majeure")+COUNTIF(Servier!J20,"NC Majeure")+COUNTIF(MEN!J20,"NC Majeure")+COUNTIF(ADM!J20,"NC Majeure")+COUNTIF('CDG DC'!J20,"NC Majeure")+COUNTIF('CDG ITOC'!J20,"NC Majeure")+COUNTIF(BPOST!J20,"NC Majeure")+COUNTIF('Graphtalk AIA'!J20,"NC Majeure")+COUNTIF('ONCF APPS'!J20,"NC Majeure")+COUNTIF('ONCF MW'!J20,"NC Majeure")+COUNTIF(ANEF!J20,"NC Majeure")+COUNTIF(Carrefour!J20,"NC Majeure")+COUNTIF('Vinci Construction'!J20,"NC Majeure")+COUNTIF(AXA!J20,"NC Majeure")+COUNTIF(OCP!J20,"NC Majeure") -> 0 | E11: =COUNTIF('CDG Sécurité'!K20,"NC Mineure")+COUNTIF(RAM!J20,"NC Mineure")+COUNTIF('Min. Intérieur'!J20,"NC Mineure")+COUNTIF('CDG Capital'!J23,"NC Mineure")+COUNTIF(AtlanticRe!J20,"NC Mineure")+COUNTIF('Client A'!J20,"NC Mineure")+COUNTIF(Servier!J20,"NC Mineure")+COUNTIF(MEN!J20,"NC Mineure")+COUNTIF(ADM!J20,"NC Mineure")+COUNTIF('CDG DC'!J20,"NC Mineure")+COUNTIF('CDG ITOC'!J20,"NC Mineure")+COUNTIF(BPOST!J20,"NC Mineure")+COUNTIF('Graphtalk AIA'!J20,"NC Mineure")+COUNTIF('ONCF APPS'!J20,"NC Mineure")+COUNTIF('ONCF MW'!J20,"NC Mineure")+COUNTIF(ANEF!J20,"NC Mineure")+COUNTIF(Carrefour!J20,"NC Mineure")+COUNTIF('Vinci Construction'!J20,"NC Mineure")+COUNTIF(AXA!J20,"NC Mineure")+COUNTIF(OCP!J20,"NC Mineure") -> 0 | F11: =COUNTIF('CDG Sécurité'!K20,"Observation")+COUNTIF(RAM!J20,"Observation")+COUNTIF('Min. Intérieur'!J20,"Observation")+COUNTIF('CDG Capital'!J23,"Observation")+COUNTIF(AtlanticRe!J20,"Observation")+COUNTIF('Client A'!J20,"Observation")+COUNTIF(Servier!J20,"Observation")+COUNTIF(MEN!J20,"Observation")+COUNTIF(ADM!J20,"Observation")+COUNTIF('CDG DC'!J20,"Observation")+COUNTIF('CDG ITOC'!J20,"Observation")+COUNTIF(BPOST!J20,"Observation")+COUNTIF('Graphtalk AIA'!J20,"Observation")+COUNTIF('ONCF APPS'!J20,"Observation")+COUNTIF('ONCF MW'!J20,"Observation")+COUNTIF(ANEF!J20,"Observation")+COUNTIF(Carrefour!J20,"Observation")+COUNTIF('Vinci Construction'!J20,"Observation")+COUNTIF(AXA!J20,"Observation")+COUNTIF(OCP!J20,"Observation") -> 0 | G11: =COUNTIF('CDG Sécurité'!K20,"OFI")+COUNTIF(RAM!J20,"OFI")+COUNTIF('Min. Intérieur'!J20,"OFI")+COUNTIF('CDG Capital'!J23,"OFI")+COUNTIF(AtlanticRe!J20,"OFI")+COUNTIF('Client A'!J20,"OFI")+COUNTIF(Servier!J20,"OFI")+COUNTIF(MEN!J20,"OFI")+COUNTIF(ADM!J20,"OFI")+COUNTIF('CDG DC'!J20,"OFI")+COUNTIF('CDG ITOC'!J20,"OFI")+COUNTIF(BPOST!J20,"OFI")+COUNTIF('Graphtalk AIA'!J20,"OFI")+COUNTIF('ONCF APPS'!J20,"OFI")+COUNTIF('ONCF MW'!J20,"OFI")+COUNTIF(ANEF!J20,"OFI")+COUNTIF(Carrefour!J20,"OFI")+COUNTIF('Vinci Construction'!J20,"OFI")+COUNTIF(AXA!J20,"OFI")+COUNTIF(OCP!J20,"OFI") -> 0 | H11: =D11+E11+F11+G11 -> 0 | I11: =IFERROR(H11/H43,0) -> 0 | J11: =IF(D11>0,"🔴 Critique",IF(H11>5,"🟠 Fort",IF(H11>2,"🟡 Modéré",IF(H11>0,"🔵 Faible","✅ Aucun")))) -> ✅ Aucun
A12: 7 | B12: 5.3 | C12: Qui fait quoi ? | D12: =COUNTIF('CDG Sécurité'!K21,"NC Majeure")+COUNTIF(RAM!J21,"NC Majeure")+COUNTIF('Min. Intérieur'!J21,"NC Majeure")+COUNTIF('CDG Capital'!J24,"NC Majeure")+COUNTIF(AtlanticRe!J21,"NC Majeure")+COUNTIF('Client A'!J21,"NC Majeure")+COUNTIF(Servier!J21,"NC Majeure")+COUNTIF(MEN!J21,"NC Majeure")+COUNTIF(ADM!J21,"NC Majeure")+COUNTIF('CDG DC'!J21,"NC Majeure")+COUNTIF('CDG ITOC'!J21,"NC Majeure")+COUNTIF(BPOST!J21,"NC Majeure")+COUNTIF('Graphtalk AIA'!J21,"NC Majeure")+COUNTIF('ONCF APPS'!J21,"NC Majeure")+COUNTIF('ONCF MW'!J21,"NC Majeure")+COUNTIF(ANEF!J21,"NC Majeure")+COUNTIF(Carrefour!J21,"NC Majeure")+COUNTIF('Vinci Construction'!J21,"NC Majeure")+COUNTIF(AXA!J21,"NC Majeure")+COUNTIF(OCP!J21,"NC Majeure") -> 0 | E12: =COUNTIF('CDG Sécurité'!K21,"NC Mineure")+COUNTIF(RAM!J21,"NC Mineure")+COUNTIF('Min. Intérieur'!J21,"NC Mineure")+COUNTIF('CDG Capital'!J24,"NC Mineure")+COUNTIF(AtlanticRe!J21,"NC Mineure")+COUNTIF('Client A'!J21,"NC Mineure")+COUNTIF(Servier!J21,"NC Mineure")+COUNTIF(MEN!J21,"NC Mineure")+COUNTIF(ADM!J21,"NC Mineure")+COUNTIF('CDG DC'!J21,"NC Mineure")+COUNTIF('CDG ITOC'!J21,"NC Mineure")+COUNTIF(BPOST!J21,"NC Mineure")+COUNTIF('Graphtalk AIA'!J21,"NC Mineure")+COUNTIF('ONCF APPS'!J21,"NC Mineure")+COUNTIF('ONCF MW'!J21,"NC Mineure")+COUNTIF(ANEF!J21,"NC Mineure")+COUNTIF(Carrefour!J21,"NC Mineure")+COUNTIF('Vinci Construction'!J21,"NC Mineure")+COUNTIF(AXA!J21,"NC Mineure")+COUNTIF(OCP!J21,"NC Mineure") -> 0 | F12: =COUNTIF('CDG Sécurité'!K21,"Observation")+COUNTIF(RAM!J21,"Observation")+COUNTIF('Min. Intérieur'!J21,"Observation")+COUNTIF('CDG Capital'!J24,"Observation")+COUNTIF(AtlanticRe!J21,"Observation")+COUNTIF('Client A'!J21,"Observation")+COUNTIF(Servier!J21,"Observation")+COUNTIF(MEN!J21,"Observation")+COUNTIF(ADM!J21,"Observation")+COUNTIF('CDG DC'!J21,"Observation")+COUNTIF('CDG ITOC'!J21,"Observation")+COUNTIF(BPOST!J21,"Observation")+COUNTIF('Graphtalk AIA'!J21,"Observation")+COUNTIF('ONCF APPS'!J21,"Observation")+COUNTIF('ONCF MW'!J21,"Observation")+COUNTIF(ANEF!J21,"Observation")+COUNTIF(Carrefour!J21,"Observation")+COUNTIF('Vinci Construction'!J21,"Observation")+COUNTIF(AXA!J21,"Observation")+COUNTIF(OCP!J21,"Observation") -> 1 | G12: =COUNTIF('CDG Sécurité'!K21,"OFI")+COUNTIF(RAM!J21,"OFI")+COUNTIF('Min. Intérieur'!J21,"OFI")+COUNTIF('CDG Capital'!J24,"OFI")+COUNTIF(AtlanticRe!J21,"OFI")+COUNTIF('Client A'!J21,"OFI")+COUNTIF(Servier!J21,"OFI")+COUNTIF(MEN!J21,"OFI")+COUNTIF(ADM!J21,"OFI")+COUNTIF('CDG DC'!J21,"OFI")+COUNTIF('CDG ITOC'!J21,"OFI")+COUNTIF(BPOST!J21,"OFI")+COUNTIF('Graphtalk AIA'!J21,"OFI")+COUNTIF('ONCF APPS'!J21,"OFI")+COUNTIF('ONCF MW'!J21,"OFI")+COUNTIF(ANEF!J21,"OFI")+COUNTIF(Carrefour!J21,"OFI")+COUNTIF('Vinci Construction'!J21,"OFI")+COUNTIF(AXA!J21,"OFI")+COUNTIF(OCP!J21,"OFI") -> 0 | H12: =D12+E12+F12+G12 -> 1 | I12: =IFERROR(H12/H43,0) -> 0.019607843 | J12: =IF(D12>0,"🔴 Critique",IF(H12>5,"🟠 Fort",IF(H12>2,"🟡 Modéré",IF(H12>0,"🔵 Faible","✅ Aucun")))) -> 🔵 Faible
A13: 8 | B13: 6.1 | C13: Gestion des risques et opportunités | D13: =COUNTIF('CDG Sécurité'!K22,"NC Majeure")+COUNTIF(RAM!J22,"NC Majeure")+COUNTIF('Min. Intérieur'!J22,"NC Majeure")+COUNTIF('CDG Capital'!J25,"NC Majeure")+COUNTIF(AtlanticRe!J22,"NC Majeure")+COUNTIF('Client A'!J22,"NC Majeure")+COUNTIF(Servier!J22,"NC Majeure")+COUNTIF(MEN!J22,"NC Majeure")+COUNTIF(ADM!J22,"NC Majeure")+COUNTIF('CDG DC'!J22,"NC Majeure")+COUNTIF('CDG ITOC'!J22,"NC Majeure")+COUNTIF(BPOST!J22,"NC Majeure")+COUNTIF('Graphtalk AIA'!J22,"NC Majeure")+COUNTIF('ONCF APPS'!J22,"NC Majeure")+COUNTIF('ONCF MW'!J22,"NC Majeure")+COUNTIF(ANEF!J22,"NC Majeure")+COUNTIF(Carrefour!J22,"NC Majeure")+COUNTIF('Vinci Construction'!J22,"NC Majeure")+COUNTIF(AXA!J22,"NC Majeure")+COUNTIF(OCP!J22,"NC Majeure") -> 0 | E13: =COUNTIF('CDG Sécurité'!K22,"NC Mineure")+COUNTIF(RAM!J22,"NC Mineure")+COUNTIF('Min. Intérieur'!J22,"NC Mineure")+COUNTIF('CDG Capital'!J25,"NC Mineure")+COUNTIF(AtlanticRe!J22,"NC Mineure")+COUNTIF('Client A'!J22,"NC Mineure")+COUNTIF(Servier!J22,"NC Mineure")+COUNTIF(MEN!J22,"NC Mineure")+COUNTIF(ADM!J22,"NC Mineure")+COUNTIF('CDG DC'!J22,"NC Mineure")+COUNTIF('CDG ITOC'!J22,"NC Mineure")+COUNTIF(BPOST!J22,"NC Mineure")+COUNTIF('Graphtalk AIA'!J22,"NC Mineure")+COUNTIF('ONCF APPS'!J22,"NC Mineure")+COUNTIF('ONCF MW'!J22,"NC Mineure")+COUNTIF(ANEF!J22,"NC Mineure")+COUNTIF(Carrefour!J22,"NC Mineure")+COUNTIF('Vinci Construction'!J22,"NC Mineure")+COUNTIF(AXA!J22,"NC Mineure")+COUNTIF(OCP!J22,"NC Mineure") -> 8 | F13: =COUNTIF('CDG Sécurité'!K22,"Observation")+COUNTIF(RAM!J22,"Observation")+COUNTIF('Min. Intérieur'!J22,"Observation")+COUNTIF('CDG Capital'!J25,"Observation")+COUNTIF(AtlanticRe!J22,"Observation")+COUNTIF('Client A'!J22,"Observation")+COUNTIF(Servier!J22,"Observation")+COUNTIF(MEN!J22,"Observation")+COUNTIF(ADM!J22,"Observation")+COUNTIF('CDG DC'!J22,"Observation")+COUNTIF('CDG ITOC'!J22,"Observation")+COUNTIF(BPOST!J22,"Observation")+COUNTIF('Graphtalk AIA'!J22,"Observation")+COUNTIF('ONCF APPS'!J22,"Observation")+COUNTIF('ONCF MW'!J22,"Observation")+COUNTIF(ANEF!J22,"Observation")+COUNTIF(Carrefour!J22,"Observation")+COUNTIF('Vinci Construction'!J22,"Observation")+COUNTIF(AXA!J22,"Observation")+COUNTIF(OCP!J22,"Observation") -> 0 | G13: =COUNTIF('CDG Sécurité'!K22,"OFI")+COUNTIF(RAM!J22,"OFI")+COUNTIF('Min. Intérieur'!J22,"OFI")+COUNTIF('CDG Capital'!J25,"OFI")+COUNTIF(AtlanticRe!J22,"OFI")+COUNTIF('Client A'!J22,"OFI")+COUNTIF(Servier!J22,"OFI")+COUNTIF(MEN!J22,"OFI")+COUNTIF(ADM!J22,"OFI")+COUNTIF('CDG DC'!J22,"OFI")+COUNTIF('CDG ITOC'!J22,"OFI")+COUNTIF(BPOST!J22,"OFI")+COUNTIF('Graphtalk AIA'!J22,"OFI")+COUNTIF('ONCF APPS'!J22,"OFI")+COUNTIF('ONCF MW'!J22,"OFI")+COUNTIF(ANEF!J22,"OFI")+COUNTIF(Carrefour!J22,"OFI")+COUNTIF('Vinci Construction'!J22,"OFI")+COUNTIF(AXA!J22,"OFI")+COUNTIF(OCP!J22,"OFI") -> 0 | H13: =D13+E13+F13+G13 -> 8 | I13: =IFERROR(H13/H43,0) -> 0.15686275 | J13: =IF(D13>0,"🔴 Critique",IF(H13>5,"🟠 Fort",IF(H13>2,"🟡 Modéré",IF(H13>0,"🔵 Faible","✅ Aucun")))) -> 🟠 Fort
A14: 9 | B14: 6.2 | C14: Planification des objectifs | D14: =COUNTIF('CDG Sécurité'!K23,"NC Majeure")+COUNTIF(RAM!J23,"NC Majeure")+COUNTIF('Min. Intérieur'!J23,"NC Majeure")+COUNTIF('CDG Capital'!J29,"NC Majeure")+COUNTIF(AtlanticRe!J23,"NC Majeure")+COUNTIF('Client A'!J23,"NC Majeure")+COUNTIF(Servier!J23,"NC Majeure")+COUNTIF(MEN!J23,"NC Majeure")+COUNTIF(ADM!J23,"NC Majeure")+COUNTIF('CDG DC'!J23,"NC Majeure")+COUNTIF('CDG ITOC'!J23,"NC Majeure")+COUNTIF(BPOST!J23,"NC Majeure")+COUNTIF('Graphtalk AIA'!J23,"NC Majeure")+COUNTIF('ONCF APPS'!J23,"NC Majeure")+COUNTIF('ONCF MW'!J23,"NC Majeure")+COUNTIF(ANEF!J23,"NC Majeure")+COUNTIF(Carrefour!J23,"NC Majeure")+COUNTIF('Vinci Construction'!J23,"NC Majeure")+COUNTIF(AXA!J23,"NC Majeure")+COUNTIF(OCP!J23,"NC Majeure") -> 0 | E14: =COUNTIF('CDG Sécurité'!K23,"NC Mineure")+COUNTIF(RAM!J23,"NC Mineure")+COUNTIF('Min. Intérieur'!J23,"NC Mineure")+COUNTIF('CDG Capital'!J29,"NC Mineure")+COUNTIF(AtlanticRe!J23,"NC Mineure")+COUNTIF('Client A'!J23,"NC Mineure")+COUNTIF(Servier!J23,"NC Mineure")+COUNTIF(MEN!J23,"NC Mineure")+COUNTIF(ADM!J23,"NC Mineure")+COUNTIF('CDG DC'!J23,"NC Mineure")+COUNTIF('CDG ITOC'!J23,"NC Mineure")+COUNTIF(BPOST!J23,"NC Mineure")+COUNTIF('Graphtalk AIA'!J23,"NC Mineure")+COUNTIF('ONCF APPS'!J23,"NC Mineure")+COUNTIF('ONCF MW'!J23,"NC Mineure")+COUNTIF(ANEF!J23,"NC Mineure")+COUNTIF(Carrefour!J23,"NC Mineure")+COUNTIF('Vinci Construction'!J23,"NC Mineure")+COUNTIF(AXA!J23,"NC Mineure")+COUNTIF(OCP!J23,"NC Mineure") -> 2 | F14: =COUNTIF('CDG Sécurité'!K23,"Observation")+COUNTIF(RAM!J23,"Observation")+COUNTIF('Min. Intérieur'!J23,"Observation")+COUNTIF('CDG Capital'!J29,"Observation")+COUNTIF(AtlanticRe!J23,"Observation")+COUNTIF('Client A'!J23,"Observation")+COUNTIF(Servier!J23,"Observation")+COUNTIF(MEN!J23,"Observation")+COUNTIF(ADM!J23,"Observation")+COUNTIF('CDG DC'!J23,"Observation")+COUNTIF('CDG ITOC'!J23,"Observation")+COUNTIF(BPOST!J23,"Observation")+COUNTIF('Graphtalk AIA'!J23,"Observation")+COUNTIF('ONCF APPS'!J23,"Observation")+COUNTIF('ONCF MW'!J23,"Observation")+COUNTIF(ANEF!J23,"Observation")+COUNTIF(Carrefour!J23,"Observation")+COUNTIF('Vinci Construction'!J23,"Observation")+COUNTIF(AXA!J23,"Observation")+COUNTIF(OCP!J23,"Observation") -> 0 | G14: =COUNTIF('CDG Sécurité'!K23,"OFI")+COUNTIF(RAM!J23,"OFI")+COUNTIF('Min. Intérieur'!J23,"OFI")+COUNTIF('CDG Capital'!J29,"OFI")+COUNTIF(AtlanticRe!J23,"OFI")+COUNTIF('Client A'!J23,"OFI")+COUNTIF(Servier!J23,"OFI")+COUNTIF(MEN!J23,"OFI")+COUNTIF(ADM!J23,"OFI")+COUNTIF('CDG DC'!J23,"OFI")+COUNTIF('CDG ITOC'!J23,"OFI")+COUNTIF(BPOST!J23,"OFI")+COUNTIF('Graphtalk AIA'!J23,"OFI")+COUNTIF('ONCF APPS'!J23,"OFI")+COUNTIF('ONCF MW'!J23,"OFI")+COUNTIF(ANEF!J23,"OFI")+COUNTIF(Carrefour!J23,"OFI")+COUNTIF('Vinci Construction'!J23,"OFI")+COUNTIF(AXA!J23,"OFI")+COUNTIF(OCP!J23,"OFI") -> 0 | H14: =D14+E14+F14+G14 -> 2 | I14: =IFERROR(H14/H43,0) -> 0.039215686 | J14: =IF(D14>0,"🔴 Critique",IF(H14>5,"🟠 Fort",IF(H14>2,"🟡 Modéré",IF(H14>0,"🔵 Faible","✅ Aucun")))) -> 🔵 Faible
A15: 10 | B15: 6.3 | C15: Gestion des changements | D15: =COUNTIF('CDG Sécurité'!K24,"NC Majeure")+COUNTIF(RAM!J24,"NC Majeure")+COUNTIF('Min. Intérieur'!J24,"NC Majeure")+COUNTIF('CDG Capital'!J30,"NC Majeure")+COUNTIF(AtlanticRe!J24,"NC Majeure")+COUNTIF('Client A'!J24,"NC Majeure")+COUNTIF(Servier!J24,"NC Majeure")+COUNTIF(MEN!J24,"NC Majeure")+COUNTIF(ADM!J24,"NC Majeure")+COUNTIF('CDG DC'!J24,"NC Majeure")+COUNTIF('CDG ITOC'!J24,"NC Majeure")+COUNTIF(BPOST!J24,"NC Majeure")+COUNTIF('Graphtalk AIA'!J24,"NC Majeure")+COUNTIF('ONCF APPS'!J24,"NC Majeure")+COUNTIF('ONCF MW'!J24,"NC Majeure")+COUNTIF(ANEF!J24,"NC Majeure")+COUNTIF(Carrefour!J24,"NC Majeure")+COUNTIF('Vinci Construction'!J24,"NC Majeure")+COUNTIF(AXA!J24,"NC Majeure")+COUNTIF(OCP!J24,"NC Majeure") -> 0 | E15: =COUNTIF('CDG Sécurité'!K24,"NC Mineure")+COUNTIF(RAM!J24,"NC Mineure")+COUNTIF('Min. Intérieur'!J24,"NC Mineure")+COUNTIF('CDG Capital'!J30,"NC Mineure")+COUNTIF(AtlanticRe!J24,"NC Mineure")+COUNTIF('Client A'!J24,"NC Mineure")+COUNTIF(Servier!J24,"NC Mineure")+COUNTIF(MEN!J24,"NC Mineure")+COUNTIF(ADM!J24,"NC Mineure")+COUNTIF('CDG DC'!J24,"NC Mineure")+COUNTIF('CDG ITOC'!J24,"NC Mineure")+COUNTIF(BPOST!J24,"NC Mineure")+COUNTIF('Graphtalk AIA'!J24,"NC Mineure")+COUNTIF('ONCF APPS'!J24,"NC Mineure")+COUNTIF('ONCF MW'!J24,"NC Mineure")+COUNTIF(ANEF!J24,"NC Mineure")+COUNTIF(Carrefour!J24,"NC Mineure")+COUNTIF('Vinci Construction'!J24,"NC Mineure")+COUNTIF(AXA!J24,"NC Mineure")+COUNTIF(OCP!J24,"NC Mineure") -> 3 | F15: =COUNTIF('CDG Sécurité'!K24,"Observation")+COUNTIF(RAM!J24,"Observation")+COUNTIF('Min. Intérieur'!J24,"Observation")+COUNTIF('CDG Capital'!J30,"Observation")+COUNTIF(AtlanticRe!J24,"Observation")+COUNTIF('Client A'!J24,"Observation")+COUNTIF(Servier!J24,"Observation")+COUNTIF(MEN!J24,"Observation")+COUNTIF(ADM!J24,"Observation")+COUNTIF('CDG DC'!J24,"Observation")+COUNTIF('CDG ITOC'!J24,"Observation")+COUNTIF(BPOST!J24,"Observation")+COUNTIF('Graphtalk AIA'!J24,"Observation")+COUNTIF('ONCF APPS'!J24,"Observation")+COUNTIF('ONCF MW'!J24,"Observation")+COUNTIF(ANEF!J24,"Observation")+COUNTIF(Carrefour!J24,"Observation")+COUNTIF('Vinci Construction'!J24,"Observation")+COUNTIF(AXA!J24,"Observation")+COUNTIF(OCP!J24,"Observation") -> 0 | G15: =COUNTIF('CDG Sécurité'!K24,"OFI")+COUNTIF(RAM!J24,"OFI")+COUNTIF('Min. Intérieur'!J24,"OFI")+COUNTIF('CDG Capital'!J30,"OFI")+COUNTIF(AtlanticRe!J24,"OFI")+COUNTIF('Client A'!J24,"OFI")+COUNTIF(Servier!J24,"OFI")+COUNTIF(MEN!J24,"OFI")+COUNTIF(ADM!J24,"OFI")+COUNTIF('CDG DC'!J24,"OFI")+COUNTIF('CDG ITOC'!J24,"OFI")+COUNTIF(BPOST!J24,"OFI")+COUNTIF('Graphtalk AIA'!J24,"OFI")+COUNTIF('ONCF APPS'!J24,"OFI")+COUNTIF('ONCF MW'!J24,"OFI")+COUNTIF(ANEF!J24,"OFI")+COUNTIF(Carrefour!J24,"OFI")+COUNTIF('Vinci Construction'!J24,"OFI")+COUNTIF(AXA!J24,"OFI")+COUNTIF(OCP!J24,"OFI") -> 0 | H15: =D15+E15+F15+G15 -> 3 | I15: =IFERROR(H15/H43,0) -> 0.058823529 | J15: =IF(D15>0,"🔴 Critique",IF(H15>5,"🟠 Fort",IF(H15>2,"🟡 Modéré",IF(H15>0,"🔵 Faible","✅ Aucun")))) -> 🟡 Modéré
A16: 11 | B16: 7.1.1 | C16: Disponibilité des ressources humaines | D16: =COUNTIF('CDG Sécurité'!K25,"NC Majeure")+COUNTIF(RAM!J25,"NC Majeure")+COUNTIF('Min. Intérieur'!J25,"NC Majeure")+COUNTIF('CDG Capital'!J31,"NC Majeure")+COUNTIF(AtlanticRe!J25,"NC Majeure")+COUNTIF('Client A'!J25,"NC Majeure")+COUNTIF(Servier!J25,"NC Majeure")+COUNTIF(MEN!J25,"NC Majeure")+COUNTIF(ADM!J25,"NC Majeure")+COUNTIF('CDG DC'!J25,"NC Majeure")+COUNTIF('CDG ITOC'!J25,"NC Majeure")+COUNTIF(BPOST!J25,"NC Majeure")+COUNTIF('Graphtalk AIA'!J25,"NC Majeure")+COUNTIF('ONCF APPS'!J25,"NC Majeure")+COUNTIF('ONCF MW'!J25,"NC Majeure")+COUNTIF(ANEF!J25,"NC Majeure")+COUNTIF(Carrefour!J25,"NC Majeure")+COUNTIF('Vinci Construction'!J25,"NC Majeure")+COUNTIF(AXA!J25,"NC Majeure")+COUNTIF(OCP!J25,"NC Majeure") -> 0 | E16: =COUNTIF('CDG Sécurité'!K25,"NC Mineure")+COUNTIF(RAM!J25,"NC Mineure")+COUNTIF('Min. Intérieur'!J25,"NC Mineure")+COUNTIF('CDG Capital'!J31,"NC Mineure")+COUNTIF(AtlanticRe!J25,"NC Mineure")+COUNTIF('Client A'!J25,"NC Mineure")+COUNTIF(Servier!J25,"NC Mineure")+COUNTIF(MEN!J25,"NC Mineure")+COUNTIF(ADM!J25,"NC Mineure")+COUNTIF('CDG DC'!J25,"NC Mineure")+COUNTIF('CDG ITOC'!J25,"NC Mineure")+COUNTIF(BPOST!J25,"NC Mineure")+COUNTIF('Graphtalk AIA'!J25,"NC Mineure")+COUNTIF('ONCF APPS'!J25,"NC Mineure")+COUNTIF('ONCF MW'!J25,"NC Mineure")+COUNTIF(ANEF!J25,"NC Mineure")+COUNTIF(Carrefour!J25,"NC Mineure")+COUNTIF('Vinci Construction'!J25,"NC Mineure")+COUNTIF(AXA!J25,"NC Mineure")+COUNTIF(OCP!J25,"NC Mineure") -> 0 | F16: =COUNTIF('CDG Sécurité'!K25,"Observation")+COUNTIF(RAM!J25,"Observation")+COUNTIF('Min. Intérieur'!J25,"Observation")+COUNTIF('CDG Capital'!J31,"Observation")+COUNTIF(AtlanticRe!J25,"Observation")+COUNTIF('Client A'!J25,"Observation")+COUNTIF(Servier!J25,"Observation")+COUNTIF(MEN!J25,"Observation")+COUNTIF(ADM!J25,"Observation")+COUNTIF('CDG DC'!J25,"Observation")+COUNTIF('CDG ITOC'!J25,"Observation")+COUNTIF(BPOST!J25,"Observation")+COUNTIF('Graphtalk AIA'!J25,"Observation")+COUNTIF('ONCF APPS'!J25,"Observation")+COUNTIF('ONCF MW'!J25,"Observation")+COUNTIF(ANEF!J25,"Observation")+COUNTIF(Carrefour!J25,"Observation")+COUNTIF('Vinci Construction'!J25,"Observation")+COUNTIF(AXA!J25,"Observation")+COUNTIF(OCP!J25,"Observation") -> 1 | G16: =COUNTIF('CDG Sécurité'!K25,"OFI")+COUNTIF(RAM!J25,"OFI")+COUNTIF('Min. Intérieur'!J25,"OFI")+COUNTIF('CDG Capital'!J31,"OFI")+COUNTIF(AtlanticRe!J25,"OFI")+COUNTIF('Client A'!J25,"OFI")+COUNTIF(Servier!J25,"OFI")+COUNTIF(MEN!J25,"OFI")+COUNTIF(ADM!J25,"OFI")+COUNTIF('CDG DC'!J25,"OFI")+COUNTIF('CDG ITOC'!J25,"OFI")+COUNTIF(BPOST!J25,"OFI")+COUNTIF('Graphtalk AIA'!J25,"OFI")+COUNTIF('ONCF APPS'!J25,"OFI")+COUNTIF('ONCF MW'!J25,"OFI")+COUNTIF(ANEF!J25,"OFI")+COUNTIF(Carrefour!J25,"OFI")+COUNTIF('Vinci Construction'!J25,"OFI")+COUNTIF(AXA!J25,"OFI")+COUNTIF(OCP!J25,"OFI") -> 0 | H16: =D16+E16+F16+G16 -> 1 | I16: =IFERROR(H16/H43,0) -> 0.019607843 | J16: =IF(D16>0,"🔴 Critique",IF(H16>5,"🟠 Fort",IF(H16>2,"🟡 Modéré",IF(H16>0,"🔵 Faible","✅ Aucun")))) -> 🔵 Faible
A17: 12 | B17: 7.1.2 | C17: Disponibilité des infrastructures | D17: =COUNTIF('CDG Sécurité'!K26,"NC Majeure")+COUNTIF(RAM!J26,"NC Majeure")+COUNTIF('Min. Intérieur'!J26,"NC Majeure")+COUNTIF('CDG Capital'!J32,"NC Majeure")+COUNTIF(AtlanticRe!J26,"NC Majeure")+COUNTIF('Client A'!J26,"NC Majeure")+COUNTIF(Servier!J26,"NC Majeure")+COUNTIF(MEN!J26,"NC Majeure")+COUNTIF(ADM!J26,"NC Majeure")+COUNTIF('CDG DC'!J26,"NC Majeure")+COUNTIF('CDG ITOC'!J26,"NC Majeure")+COUNTIF(BPOST!J26,"NC Majeure")+COUNTIF('Graphtalk AIA'!J26,"NC Majeure")+COUNTIF('ONCF APPS'!J26,"NC Majeure")+COUNTIF('ONCF MW'!J26,"NC Majeure")+COUNTIF(ANEF!J26,"NC Majeure")+COUNTIF(Carrefour!J26,"NC Majeure")+COUNTIF('Vinci Construction'!J26,"NC Majeure")+COUNTIF(AXA!J26,"NC Majeure")+COUNTIF(OCP!J26,"NC Majeure") -> 0 | E17: =COUNTIF('CDG Sécurité'!K26,"NC Mineure")+COUNTIF(RAM!J26,"NC Mineure")+COUNTIF('Min. Intérieur'!J26,"NC Mineure")+COUNTIF('CDG Capital'!J32,"NC Mineure")+COUNTIF(AtlanticRe!J26,"NC Mineure")+COUNTIF('Client A'!J26,"NC Mineure")+COUNTIF(Servier!J26,"NC Mineure")+COUNTIF(MEN!J26,"NC Mineure")+COUNTIF(ADM!J26,"NC Mineure")+COUNTIF('CDG DC'!J26,"NC Mineure")+COUNTIF('CDG ITOC'!J26,"NC Mineure")+COUNTIF(BPOST!J26,"NC Mineure")+COUNTIF('Graphtalk AIA'!J26,"NC Mineure")+COUNTIF('ONCF APPS'!J26,"NC Mineure")+COUNTIF('ONCF MW'!J26,"NC Mineure")+COUNTIF(ANEF!J26,"NC Mineure")+COUNTIF(Carrefour!J26,"NC Mineure")+COUNTIF('Vinci Construction'!J26,"NC Mineure")+COUNTIF(AXA!J26,"NC Mineure")+COUNTIF(OCP!J26,"NC Mineure") -> 1 | F17: =COUNTIF('CDG Sécurité'!K26,"Observation")+COUNTIF(RAM!J26,"Observation")+COUNTIF('Min. Intérieur'!J26,"Observation")+COUNTIF('CDG Capital'!J32,"Observation")+COUNTIF(AtlanticRe!J26,"Observation")+COUNTIF('Client A'!J26,"Observation")+COUNTIF(Servier!J26,"Observation")+COUNTIF(MEN!J26,"Observation")+COUNTIF(ADM!J26,"Observation")+COUNTIF('CDG DC'!J26,"Observation")+COUNTIF('CDG ITOC'!J26,"Observation")+COUNTIF(BPOST!J26,"Observation")+COUNTIF('Graphtalk AIA'!J26,"Observation")+COUNTIF('ONCF APPS'!J26,"Observation")+COUNTIF('ONCF MW'!J26,"Observation")+COUNTIF(ANEF!J26,"Observation")+COUNTIF(Carrefour!J26,"Observation")+COUNTIF('Vinci Construction'!J26,"Observation")+COUNTIF(AXA!J26,"Observation")+COUNTIF(OCP!J26,"Observation") -> 0 | G17: =COUNTIF('CDG Sécurité'!K26,"OFI")+COUNTIF(RAM!J26,"OFI")+COUNTIF('Min. Intérieur'!J26,"OFI")+COUNTIF('CDG Capital'!J32,"OFI")+COUNTIF(AtlanticRe!J26,"OFI")+COUNTIF('Client A'!J26,"OFI")+COUNTIF(Servier!J26,"OFI")+COUNTIF(MEN!J26,"OFI")+COUNTIF(ADM!J26,"OFI")+COUNTIF('CDG DC'!J26,"OFI")+COUNTIF('CDG ITOC'!J26,"OFI")+COUNTIF(BPOST!J26,"OFI")+COUNTIF('Graphtalk AIA'!J26,"OFI")+COUNTIF('ONCF APPS'!J26,"OFI")+COUNTIF('ONCF MW'!J26,"OFI")+COUNTIF(ANEF!J26,"OFI")+COUNTIF(Carrefour!J26,"OFI")+COUNTIF('Vinci Construction'!J26,"OFI")+COUNTIF(AXA!J26,"OFI")+COUNTIF(OCP!J26,"OFI") -> 0 | H17: =D17+E17+F17+G17 -> 1 | I17: =IFERROR(H17/H43,0) -> 0.019607843 | J17: =IF(D17>0,"🔴 Critique",IF(H17>5,"🟠 Fort",IF(H17>2,"🟡 Modéré",IF(H17>0,"🔵 Faible","✅ Aucun")))) -> 🔵 Faible
A18: 13 | B18: 7.1.5 | C18: Outils de mesure et de contrôle | D18: =COUNTIF('CDG Sécurité'!K27,"NC Majeure")+COUNTIF(RAM!J27,"NC Majeure")+COUNTIF('Min. Intérieur'!J27,"NC Majeure")+COUNTIF('CDG Capital'!J33,"NC Majeure")+COUNTIF(AtlanticRe!J27,"NC Majeure")+COUNTIF('Client A'!J27,"NC Majeure")+COUNTIF(Servier!J27,"NC Majeure")+COUNTIF(MEN!J27,"NC Majeure")+COUNTIF(ADM!J27,"NC Majeure")+COUNTIF('CDG DC'!J27,"NC Majeure")+COUNTIF('CDG ITOC'!J27,"NC Majeure")+COUNTIF(BPOST!J27,"NC Majeure")+COUNTIF('Graphtalk AIA'!J27,"NC Majeure")+COUNTIF('ONCF APPS'!J27,"NC Majeure")+COUNTIF('ONCF MW'!J27,"NC Majeure")+COUNTIF(ANEF!J27,"NC Majeure")+COUNTIF(Carrefour!J27,"NC Majeure")+COUNTIF('Vinci Construction'!J27,"NC Majeure")+COUNTIF(AXA!J27,"NC Majeure")+COUNTIF(OCP!J27,"NC Majeure") -> 0 | E18: =COUNTIF('CDG Sécurité'!K27,"NC Mineure")+COUNTIF(RAM!J27,"NC Mineure")+COUNTIF('Min. Intérieur'!J27,"NC Mineure")+COUNTIF('CDG Capital'!J33,"NC Mineure")+COUNTIF(AtlanticRe!J27,"NC Mineure")+COUNTIF('Client A'!J27,"NC Mineure")+COUNTIF(Servier!J27,"NC Mineure")+COUNTIF(MEN!J27,"NC Mineure")+COUNTIF(ADM!J27,"NC Mineure")+COUNTIF('CDG DC'!J27,"NC Mineure")+COUNTIF('CDG ITOC'!J27,"NC Mineure")+COUNTIF(BPOST!J27,"NC Mineure")+COUNTIF('Graphtalk AIA'!J27,"NC Mineure")+COUNTIF('ONCF APPS'!J27,"NC Mineure")+COUNTIF('ONCF MW'!J27,"NC Mineure")+COUNTIF(ANEF!J27,"NC Mineure")+COUNTIF(Carrefour!J27,"NC Mineure")+COUNTIF('Vinci Construction'!J27,"NC Mineure")+COUNTIF(AXA!J27,"NC Mineure")+COUNTIF(OCP!J27,"NC Mineure") -> 0 | F18: =COUNTIF('CDG Sécurité'!K27,"Observation")+COUNTIF(RAM!J27,"Observation")+COUNTIF('Min. Intérieur'!J27,"Observation")+COUNTIF('CDG Capital'!J33,"Observation")+COUNTIF(AtlanticRe!J27,"Observation")+COUNTIF('Client A'!J27,"Observation")+COUNTIF(Servier!J27,"Observation")+COUNTIF(MEN!J27,"Observation")+COUNTIF(ADM!J27,"Observation")+COUNTIF('CDG DC'!J27,"Observation")+COUNTIF('CDG ITOC'!J27,"Observation")+COUNTIF(BPOST!J27,"Observation")+COUNTIF('Graphtalk AIA'!J27,"Observation")+COUNTIF('ONCF APPS'!J27,"Observation")+COUNTIF('ONCF MW'!J27,"Observation")+COUNTIF(ANEF!J27,"Observation")+COUNTIF(Carrefour!J27,"Observation")+COUNTIF('Vinci Construction'!J27,"Observation")+COUNTIF(AXA!J27,"Observation")+COUNTIF(OCP!J27,"Observation") -> 0 | G18: =COUNTIF('CDG Sécurité'!K27,"OFI")+COUNTIF(RAM!J27,"OFI")+COUNTIF('Min. Intérieur'!J27,"OFI")+COUNTIF('CDG Capital'!J33,"OFI")+COUNTIF(AtlanticRe!J27,"OFI")+COUNTIF('Client A'!J27,"OFI")+COUNTIF(Servier!J27,"OFI")+COUNTIF(MEN!J27,"OFI")+COUNTIF(ADM!J27,"OFI")+COUNTIF('CDG DC'!J27,"OFI")+COUNTIF('CDG ITOC'!J27,"OFI")+COUNTIF(BPOST!J27,"OFI")+COUNTIF('Graphtalk AIA'!J27,"OFI")+COUNTIF('ONCF APPS'!J27,"OFI")+COUNTIF('ONCF MW'!J27,"OFI")+COUNTIF(ANEF!J27,"OFI")+COUNTIF(Carrefour!J27,"OFI")+COUNTIF('Vinci Construction'!J27,"OFI")+COUNTIF(AXA!J27,"OFI")+COUNTIF(OCP!J27,"OFI") -> 0 | H18: =D18+E18+F18+G18 -> 0 | I18: =IFERROR(H18/H43,0) -> 0 | J18: =IF(D18>0,"🔴 Critique",IF(H18>5,"🟠 Fort",IF(H18>2,"🟡 Modéré",IF(H18>0,"🔵 Faible","✅ Aucun")))) -> ✅ Aucun
A19: 14 | B19: 7.1.6 | C19: Gestion des connaissances | D19: =COUNTIF('CDG Sécurité'!K28,"NC Majeure")+COUNTIF(RAM!J28,"NC Majeure")+COUNTIF('Min. Intérieur'!J28,"NC Majeure")+COUNTIF('CDG Capital'!J34,"NC Majeure")+COUNTIF(AtlanticRe!J28,"NC Majeure")+COUNTIF('Client A'!J28,"NC Majeure")+COUNTIF(Servier!J28,"NC Majeure")+COUNTIF(MEN!J28,"NC Majeure")+COUNTIF(ADM!J28,"NC Majeure")+COUNTIF('CDG DC'!J28,"NC Majeure")+COUNTIF('CDG ITOC'!J28,"NC Majeure")+COUNTIF(BPOST!J28,"NC Majeure")+COUNTIF('Graphtalk AIA'!J28,"NC Majeure")+COUNTIF('ONCF APPS'!J28,"NC Majeure")+COUNTIF('ONCF MW'!J28,"NC Majeure")+COUNTIF(ANEF!J28,"NC Majeure")+COUNTIF(Carrefour!J28,"NC Majeure")+COUNTIF('Vinci Construction'!J28,"NC Majeure")+COUNTIF(AXA!J28,"NC Majeure")+COUNTIF(OCP!J28,"NC Majeure") -> 0 | E19: =COUNTIF('CDG Sécurité'!K28,"NC Mineure")+COUNTIF(RAM!J28,"NC Mineure")+COUNTIF('Min. Intérieur'!J28,"NC Mineure")+COUNTIF('CDG Capital'!J34,"NC Mineure")+COUNTIF(AtlanticRe!J28,"NC Mineure")+COUNTIF('Client A'!J28,"NC Mineure")+COUNTIF(Servier!J28,"NC Mineure")+COUNTIF(MEN!J28,"NC Mineure")+COUNTIF(ADM!J28,"NC Mineure")+COUNTIF('CDG DC'!J28,"NC Mineure")+COUNTIF('CDG ITOC'!J28,"NC Mineure")+COUNTIF(BPOST!J28,"NC Mineure")+COUNTIF('Graphtalk AIA'!J28,"NC Mineure")+COUNTIF('ONCF APPS'!J28,"NC Mineure")+COUNTIF('ONCF MW'!J28,"NC Mineure")+COUNTIF(ANEF!J28,"NC Mineure")+COUNTIF(Carrefour!J28,"NC Mineure")+COUNTIF('Vinci Construction'!J28,"NC Mineure")+COUNTIF(AXA!J28,"NC Mineure")+COUNTIF(OCP!J28,"NC Mineure") -> 0 | F19: =COUNTIF('CDG Sécurité'!K28,"Observation")+COUNTIF(RAM!J28,"Observation")+COUNTIF('Min. Intérieur'!J28,"Observation")+COUNTIF('CDG Capital'!J34,"Observation")+COUNTIF(AtlanticRe!J28,"Observation")+COUNTIF('Client A'!J28,"Observation")+COUNTIF(Servier!J28,"Observation")+COUNTIF(MEN!J28,"Observation")+COUNTIF(ADM!J28,"Observation")+COUNTIF('CDG DC'!J28,"Observation")+COUNTIF('CDG ITOC'!J28,"Observation")+COUNTIF(BPOST!J28,"Observation")+COUNTIF('Graphtalk AIA'!J28,"Observation")+COUNTIF('ONCF APPS'!J28,"Observation")+COUNTIF('ONCF MW'!J28,"Observation")+COUNTIF(ANEF!J28,"Observation")+COUNTIF(Carrefour!J28,"Observation")+COUNTIF('Vinci Construction'!J28,"Observation")+COUNTIF(AXA!J28,"Observation")+COUNTIF(OCP!J28,"Observation") -> 0 | G19: =COUNTIF('CDG Sécurité'!K28,"OFI")+COUNTIF(RAM!J28,"OFI")+COUNTIF('Min. Intérieur'!J28,"OFI")+COUNTIF('CDG Capital'!J34,"OFI")+COUNTIF(AtlanticRe!J28,"OFI")+COUNTIF('Client A'!J28,"OFI")+COUNTIF(Servier!J28,"OFI")+COUNTIF(MEN!J28,"OFI")+COUNTIF(ADM!J28,"OFI")+COUNTIF('CDG DC'!J28,"OFI")+COUNTIF('CDG ITOC'!J28,"OFI")+COUNTIF(BPOST!J28,"OFI")+COUNTIF('Graphtalk AIA'!J28,"OFI")+COUNTIF('ONCF APPS'!J28,"OFI")+COUNTIF('ONCF MW'!J28,"OFI")+COUNTIF(ANEF!J28,"OFI")+COUNTIF(Carrefour!J28,"OFI")+COUNTIF('Vinci Construction'!J28,"OFI")+COUNTIF(AXA!J28,"OFI")+COUNTIF(OCP!J28,"OFI") -> 0 | H19: =D19+E19+F19+G19 -> 0 | I19: =IFERROR(H19/H43,0) -> 0 | J19: =IF(D19>0,"🔴 Critique",IF(H19>5,"🟠 Fort",IF(H19>2,"🟡 Modéré",IF(H19>0,"🔵 Faible","✅ Aucun")))) -> ✅ Aucun
A20: 15 | B20: 7.2 | C20: Compétences de l'équipe | D20: =COUNTIF('CDG Sécurité'!K29,"NC Majeure")+COUNTIF(RAM!J29,"NC Majeure")+COUNTIF('Min. Intérieur'!J29,"NC Majeure")+COUNTIF('CDG Capital'!J35,"NC Majeure")+COUNTIF(AtlanticRe!J29,"NC Majeure")+COUNTIF('Client A'!J29,"NC Majeure")+COUNTIF(Servier!J29,"NC Majeure")+COUNTIF(MEN!J29,"NC Majeure")+COUNTIF(ADM!J29,"NC Majeure")+COUNTIF('CDG DC'!J29,"NC Majeure")+COUNTIF('CDG ITOC'!J29,"NC Majeure")+COUNTIF(BPOST!J29,"NC Majeure")+COUNTIF('Graphtalk AIA'!J29,"NC Majeure")+COUNTIF('ONCF APPS'!J29,"NC Majeure")+COUNTIF('ONCF MW'!J29,"NC Majeure")+COUNTIF(ANEF!J29,"NC Majeure")+COUNTIF(Carrefour!J29,"NC Majeure")+COUNTIF('Vinci Construction'!J29,"NC Majeure")+COUNTIF(AXA!J29,"NC Majeure")+COUNTIF(OCP!J29,"NC Majeure") -> 0 | E20: =COUNTIF('CDG Sécurité'!K29,"NC Mineure")+COUNTIF(RAM!J29,"NC Mineure")+COUNTIF('Min. Intérieur'!J29,"NC Mineure")+COUNTIF('CDG Capital'!J35,"NC Mineure")+COUNTIF(AtlanticRe!J29,"NC Mineure")+COUNTIF('Client A'!J29,"NC Mineure")+COUNTIF(Servier!J29,"NC Mineure")+COUNTIF(MEN!J29,"NC Mineure")+COUNTIF(ADM!J29,"NC Mineure")+COUNTIF('CDG DC'!J29,"NC Mineure")+COUNTIF('CDG ITOC'!J29,"NC Mineure")+COUNTIF(BPOST!J29,"NC Mineure")+COUNTIF('Graphtalk AIA'!J29,"NC Mineure")+COUNTIF('ONCF APPS'!J29,"NC Mineure")+COUNTIF('ONCF MW'!J29,"NC Mineure")+COUNTIF(ANEF!J29,"NC Mineure")+COUNTIF(Carrefour!J29,"NC Mineure")+COUNTIF('Vinci Construction'!J29,"NC Mineure")+COUNTIF(AXA!J29,"NC Mineure")+COUNTIF(OCP!J29,"NC Mineure") -> 7 | F20: =COUNTIF('CDG Sécurité'!K29,"Observation")+COUNTIF(RAM!J29,"Observation")+COUNTIF('Min. Intérieur'!J29,"Observation")+COUNTIF('CDG Capital'!J35,"Observation")+COUNTIF(AtlanticRe!J29,"Observation")+COUNTIF('Client A'!J29,"Observation")+COUNTIF(Servier!J29,"Observation")+COUNTIF(MEN!J29,"Observation")+COUNTIF(ADM!J29,"Observation")+COUNTIF('CDG DC'!J29,"Observation")+COUNTIF('CDG ITOC'!J29,"Observation")+COUNTIF(BPOST!J29,"Observation")+COUNTIF('Graphtalk AIA'!J29,"Observation")+COUNTIF('ONCF APPS'!J29,"Observation")+COUNTIF('ONCF MW'!J29,"Observation")+COUNTIF(ANEF!J29,"Observation")+COUNTIF(Carrefour!J29,"Observation")+COUNTIF('Vinci Construction'!J29,"Observation")+COUNTIF(AXA!J29,"Observation")+COUNTIF(OCP!J29,"Observation") -> 0 | G20: =COUNTIF('CDG Sécurité'!K29,"OFI")+COUNTIF(RAM!J29,"OFI")+COUNTIF('Min. Intérieur'!J29,"OFI")+COUNTIF('CDG Capital'!J35,"OFI")+COUNTIF(AtlanticRe!J29,"OFI")+COUNTIF('Client A'!J29,"OFI")+COUNTIF(Servier!J29,"OFI")+COUNTIF(MEN!J29,"OFI")+COUNTIF(ADM!J29,"OFI")+COUNTIF('CDG DC'!J29,"OFI")+COUNTIF('CDG ITOC'!J29,"OFI")+COUNTIF(BPOST!J29,"OFI")+COUNTIF('Graphtalk AIA'!J29,"OFI")+COUNTIF('ONCF APPS'!J29,"OFI")+COUNTIF('ONCF MW'!J29,"OFI")+COUNTIF(ANEF!J29,"OFI")+COUNTIF(Carrefour!J29,"OFI")+COUNTIF('Vinci Construction'!J29,"OFI")+COUNTIF(AXA!J29,"OFI")+COUNTIF(OCP!J29,"OFI") -> 0 | H20: =D20+E20+F20+G20 -> 7 | I20: =IFERROR(H20/H43,0) -> 0.1372549 | J20: =IF(D20>0,"🔴 Critique",IF(H20>5,"🟠 Fort",IF(H20>2,"🟡 Modéré",IF(H20>0,"🔵 Faible","✅ Aucun")))) -> 🟠 Fort
A21: 16 | B21: 7.3 | C21: Sensibilisation qualité | D21: =COUNTIF('CDG Sécurité'!K30,"NC Majeure")+COUNTIF(RAM!J30,"NC Majeure")+COUNTIF('Min. Intérieur'!J30,"NC Majeure")+COUNTIF('CDG Capital'!J36,"NC Majeure")+COUNTIF(AtlanticRe!J30,"NC Majeure")+COUNTIF('Client A'!J30,"NC Majeure")+COUNTIF(Servier!J30,"NC Majeure")+COUNTIF(MEN!J30,"NC Majeure")+COUNTIF(ADM!J30,"NC Majeure")+COUNTIF('CDG DC'!J30,"NC Majeure")+COUNTIF('CDG ITOC'!J30,"NC Majeure")+COUNTIF(BPOST!J30,"NC Majeure")+COUNTIF('Graphtalk AIA'!J30,"NC Majeure")+COUNTIF('ONCF APPS'!J30,"NC Majeure")+COUNTIF('ONCF MW'!J30,"NC Majeure")+COUNTIF(ANEF!J30,"NC Majeure")+COUNTIF(Carrefour!J30,"NC Majeure")+COUNTIF('Vinci Construction'!J30,"NC Majeure")+COUNTIF(AXA!J30,"NC Majeure")+COUNTIF(OCP!J30,"NC Majeure") -> 0 | E21: =COUNTIF('CDG Sécurité'!K30,"NC Mineure")+COUNTIF(RAM!J30,"NC Mineure")+COUNTIF('Min. Intérieur'!J30,"NC Mineure")+COUNTIF('CDG Capital'!J36,"NC Mineure")+COUNTIF(AtlanticRe!J30,"NC Mineure")+COUNTIF('Client A'!J30,"NC Mineure")+COUNTIF(Servier!J30,"NC Mineure")+COUNTIF(MEN!J30,"NC Mineure")+COUNTIF(ADM!J30,"NC Mineure")+COUNTIF('CDG DC'!J30,"NC Mineure")+COUNTIF('CDG ITOC'!J30,"NC Mineure")+COUNTIF(BPOST!J30,"NC Mineure")+COUNTIF('Graphtalk AIA'!J30,"NC Mineure")+COUNTIF('ONCF APPS'!J30,"NC Mineure")+COUNTIF('ONCF MW'!J30,"NC Mineure")+COUNTIF(ANEF!J30,"NC Mineure")+COUNTIF(Carrefour!J30,"NC Mineure")+COUNTIF('Vinci Construction'!J30,"NC Mineure")+COUNTIF(AXA!J30,"NC Mineure")+COUNTIF(OCP!J30,"NC Mineure") -> 0 | F21: =COUNTIF('CDG Sécurité'!K30,"Observation")+COUNTIF(RAM!J30,"Observation")+COUNTIF('Min. Intérieur'!J30,"Observation")+COUNTIF('CDG Capital'!J36,"Observation")+COUNTIF(AtlanticRe!J30,"Observation")+COUNTIF('Client A'!J30,"Observation")+COUNTIF(Servier!J30,"Observation")+COUNTIF(MEN!J30,"Observation")+COUNTIF(ADM!J30,"Observation")+COUNTIF('CDG DC'!J30,"Observation")+COUNTIF('CDG ITOC'!J30,"Observation")+COUNTIF(BPOST!J30,"Observation")+COUNTIF('Graphtalk AIA'!J30,"Observation")+COUNTIF('ONCF APPS'!J30,"Observation")+COUNTIF('ONCF MW'!J30,"Observation")+COUNTIF(ANEF!J30,"Observation")+COUNTIF(Carrefour!J30,"Observation")+COUNTIF('Vinci Construction'!J30,"Observation")+COUNTIF(AXA!J30,"Observation")+COUNTIF(OCP!J30,"Observation") -> 0 | G21: =COUNTIF('CDG Sécurité'!K30,"OFI")+COUNTIF(RAM!J30,"OFI")+COUNTIF('Min. Intérieur'!J30,"OFI")+COUNTIF('CDG Capital'!J36,"OFI")+COUNTIF(AtlanticRe!J30,"OFI")+COUNTIF('Client A'!J30,"OFI")+COUNTIF(Servier!J30,"OFI")+COUNTIF(MEN!J30,"OFI")+COUNTIF(ADM!J30,"OFI")+COUNTIF('CDG DC'!J30,"OFI")+COUNTIF('CDG ITOC'!J30,"OFI")+COUNTIF(BPOST!J30,"OFI")+COUNTIF('Graphtalk AIA'!J30,"OFI")+COUNTIF('ONCF APPS'!J30,"OFI")+COUNTIF('ONCF MW'!J30,"OFI")+COUNTIF(ANEF!J30,"OFI")+COUNTIF(Carrefour!J30,"OFI")+COUNTIF('Vinci Construction'!J30,"OFI")+COUNTIF(AXA!J30,"OFI")+COUNTIF(OCP!J30,"OFI") -> 0 | H21: =D21+E21+F21+G21 -> 0 | I21: =IFERROR(H21/H43,0) -> 0 | J21: =IF(D21>0,"🔴 Critique",IF(H21>5,"🟠 Fort",IF(H21>2,"🟡 Modéré",IF(H21>0,"🔵 Faible","✅ Aucun")))) -> ✅ Aucun
A22: 17 | B22: 7.4 | C22: Plan de communication | D22: =COUNTIF('CDG Sécurité'!K31,"NC Majeure")+COUNTIF(RAM!J31,"NC Majeure")+COUNTIF('Min. Intérieur'!J31,"NC Majeure")+COUNTIF('CDG Capital'!J37,"NC Majeure")+COUNTIF(AtlanticRe!J31,"NC Majeure")+COUNTIF('Client A'!J31,"NC Majeure")+COUNTIF(Servier!J31,"NC Majeure")+COUNTIF(MEN!J31,"NC Majeure")+COUNTIF(ADM!J31,"NC Majeure")+COUNTIF('CDG DC'!J31,"NC Majeure")+COUNTIF('CDG ITOC'!J31,"NC Majeure")+COUNTIF(BPOST!J31,"NC Majeure")+COUNTIF('Graphtalk AIA'!J31,"NC Majeure")+COUNTIF('ONCF APPS'!J31,"NC Majeure")+COUNTIF('ONCF MW'!J31,"NC Majeure")+COUNTIF(ANEF!J31,"NC Majeure")+COUNTIF(Carrefour!J31,"NC Majeure")+COUNTIF('Vinci Construction'!J31,"NC Majeure")+COUNTIF(AXA!J31,"NC Majeure")+COUNTIF(OCP!J31,"NC Majeure") -> 0 | E22: =COUNTIF('CDG Sécurité'!K31,"NC Mineure")+COUNTIF(RAM!J31,"NC Mineure")+COUNTIF('Min. Intérieur'!J31,"NC Mineure")+COUNTIF('CDG Capital'!J37,"NC Mineure")+COUNTIF(AtlanticRe!J31,"NC Mineure")+COUNTIF('Client A'!J31,"NC Mineure")+COUNTIF(Servier!J31,"NC Mineure")+COUNTIF(MEN!J31,"NC Mineure")+COUNTIF(ADM!J31,"NC Mineure")+COUNTIF('CDG DC'!J31,"NC Mineure")+COUNTIF('CDG ITOC'!J31,"NC Mineure")+COUNTIF(BPOST!J31,"NC Mineure")+COUNTIF('Graphtalk AIA'!J31,"NC Mineure")+COUNTIF('ONCF APPS'!J31,"NC Mineure")+COUNTIF('ONCF MW'!J31,"NC Mineure")+COUNTIF(ANEF!J31,"NC Mineure")+COUNTIF(Carrefour!J31,"NC Mineure")+COUNTIF('Vinci Construction'!J31,"NC Mineure")+COUNTIF(AXA!J31,"NC Mineure")+COUNTIF(OCP!J31,"NC Mineure") -> 6 | F22: =COUNTIF('CDG Sécurité'!K31,"Observation")+COUNTIF(RAM!J31,"Observation")+COUNTIF('Min. Intérieur'!J31,"Observation")+COUNTIF('CDG Capital'!J37,"Observation")+COUNTIF(AtlanticRe!J31,"Observation")+COUNTIF('Client A'!J31,"Observation")+COUNTIF(Servier!J31,"Observation")+COUNTIF(MEN!J31,"Observation")+COUNTIF(ADM!J31,"Observation")+COUNTIF('CDG DC'!J31,"Observation")+COUNTIF('CDG ITOC'!J31,"Observation")+COUNTIF(BPOST!J31,"Observation")+COUNTIF('Graphtalk AIA'!J31,"Observation")+COUNTIF('ONCF APPS'!J31,"Observation")+COUNTIF('ONCF MW'!J31,"Observation")+COUNTIF(ANEF!J31,"Observation")+COUNTIF(Carrefour!J31,"Observation")+COUNTIF('Vinci Construction'!J31,"Observation")+COUNTIF(AXA!J31,"Observation")+COUNTIF(OCP!J31,"Observation") -> 2 | G22: =COUNTIF('CDG Sécurité'!K31,"OFI")+COUNTIF(RAM!J31,"OFI")+COUNTIF('Min. Intérieur'!J31,"OFI")+COUNTIF('CDG Capital'!J37,"OFI")+COUNTIF(AtlanticRe!J31,"OFI")+COUNTIF('Client A'!J31,"OFI")+COUNTIF(Servier!J31,"OFI")+COUNTIF(MEN!J31,"OFI")+COUNTIF(ADM!J31,"OFI")+COUNTIF('CDG DC'!J31,"OFI")+COUNTIF('CDG ITOC'!J31,"OFI")+COUNTIF(BPOST!J31,"OFI")+COUNTIF('Graphtalk AIA'!J31,"OFI")+COUNTIF('ONCF APPS'!J31,"OFI")+COUNTIF('ONCF MW'!J31,"OFI")+COUNTIF(ANEF!J31,"OFI")+COUNTIF(Carrefour!J31,"OFI")+COUNTIF('Vinci Construction'!J31,"OFI")+COUNTIF(AXA!J31,"OFI")+COUNTIF(OCP!J31,"OFI") -> 0 | H22: =D22+E22+F22+G22 -> 8 | I22: =IFERROR(H22/H43,0) -> 0.15686275 | J22: =IF(D22>0,"🔴 Critique",IF(H22>5,"🟠 Fort",IF(H22>2,"🟡 Modéré",IF(H22>0,"🔵 Faible","✅ Aucun")))) -> 🟠 Fort
A23: 18 | B23: 7.5 | C23: Gestion documentaire | D23: =COUNTIF('CDG Sécurité'!K32,"NC Majeure")+COUNTIF(RAM!J32,"NC Majeure")+COUNTIF('Min. Intérieur'!J32,"NC Majeure")+COUNTIF('CDG Capital'!J38,"NC Majeure")+COUNTIF(AtlanticRe!J32,"NC Majeure")+COUNTIF('Client A'!J32,"NC Majeure")+COUNTIF(Servier!J32,"NC Majeure")+COUNTIF(MEN!J32,"NC Majeure")+COUNTIF(ADM!J32,"NC Majeure")+COUNTIF('CDG DC'!J32,"NC Majeure")+COUNTIF('CDG ITOC'!J32,"NC Majeure")+COUNTIF(BPOST!J32,"NC Majeure")+COUNTIF('Graphtalk AIA'!J32,"NC Majeure")+COUNTIF('ONCF APPS'!J32,"NC Majeure")+COUNTIF('ONCF MW'!J32,"NC Majeure")+COUNTIF(ANEF!J32,"NC Majeure")+COUNTIF(Carrefour!J32,"NC Majeure")+COUNTIF('Vinci Construction'!J32,"NC Majeure")+COUNTIF(AXA!J32,"NC Majeure")+COUNTIF(OCP!J32,"NC Majeure") -> 0 | E23: =COUNTIF('CDG Sécurité'!K32,"NC Mineure")+COUNTIF(RAM!J32,"NC Mineure")+COUNTIF('Min. Intérieur'!J32,"NC Mineure")+COUNTIF('CDG Capital'!J38,"NC Mineure")+COUNTIF(AtlanticRe!J32,"NC Mineure")+COUNTIF('Client A'!J32,"NC Mineure")+COUNTIF(Servier!J32,"NC Mineure")+COUNTIF(MEN!J32,"NC Mineure")+COUNTIF(ADM!J32,"NC Mineure")+COUNTIF('CDG DC'!J32,"NC Mineure")+COUNTIF('CDG ITOC'!J32,"NC Mineure")+COUNTIF(BPOST!J32,"NC Mineure")+COUNTIF('Graphtalk AIA'!J32,"NC Mineure")+COUNTIF('ONCF APPS'!J32,"NC Mineure")+COUNTIF('ONCF MW'!J32,"NC Mineure")+COUNTIF(ANEF!J32,"NC Mineure")+COUNTIF(Carrefour!J32,"NC Mineure")+COUNTIF('Vinci Construction'!J32,"NC Mineure")+COUNTIF(AXA!J32,"NC Mineure")+COUNTIF(OCP!J32,"NC Mineure") -> 7 | F23: =COUNTIF('CDG Sécurité'!K32,"Observation")+COUNTIF(RAM!J32,"Observation")+COUNTIF('Min. Intérieur'!J32,"Observation")+COUNTIF('CDG Capital'!J38,"Observation")+COUNTIF(AtlanticRe!J32,"Observation")+COUNTIF('Client A'!J32,"Observation")+COUNTIF(Servier!J32,"Observation")+COUNTIF(MEN!J32,"Observation")+COUNTIF(ADM!J32,"Observation")+COUNTIF('CDG DC'!J32,"Observation")+COUNTIF('CDG ITOC'!J32,"Observation")+COUNTIF(BPOST!J32,"Observation")+COUNTIF('Graphtalk AIA'!J32,"Observation")+COUNTIF('ONCF APPS'!J32,"Observation")+COUNTIF('ONCF MW'!J32,"Observation")+COUNTIF(ANEF!J32,"Observation")+COUNTIF(Carrefour!J32,"Observation")+COUNTIF('Vinci Construction'!J32,"Observation")+COUNTIF(AXA!J32,"Observation")+COUNTIF(OCP!J32,"Observation") -> 0 | G23: =COUNTIF('CDG Sécurité'!K32,"OFI")+COUNTIF(RAM!J32,"OFI")+COUNTIF('Min. Intérieur'!J32,"OFI")+COUNTIF('CDG Capital'!J38,"OFI")+COUNTIF(AtlanticRe!J32,"OFI")+COUNTIF('Client A'!J32,"OFI")+COUNTIF(Servier!J32,"OFI")+COUNTIF(MEN!J32,"OFI")+COUNTIF(ADM!J32,"OFI")+COUNTIF('CDG DC'!J32,"OFI")+COUNTIF('CDG ITOC'!J32,"OFI")+COUNTIF(BPOST!J32,"OFI")+COUNTIF('Graphtalk AIA'!J32,"OFI")+COUNTIF('ONCF APPS'!J32,"OFI")+COUNTIF('ONCF MW'!J32,"OFI")+COUNTIF(ANEF!J32,"OFI")+COUNTIF(Carrefour!J32,"OFI")+COUNTIF('Vinci Construction'!J32,"OFI")+COUNTIF(AXA!J32,"OFI")+COUNTIF(OCP!J32,"OFI") -> 0 | H23: =D23+E23+F23+G23 -> 7 | I23: =IFERROR(H23/H43,0) -> 0.1372549 | J23: =IF(D23>0,"🔴 Critique",IF(H23>5,"🟠 Fort",IF(H23>2,"🟡 Modéré",IF(H23>0,"🔵 Faible","✅ Aucun")))) -> 🟠 Fort
A24: 19 | B24: 8.1 | C24: Planification des opérations | D24: =COUNTIF('CDG Sécurité'!K33,"NC Majeure")+COUNTIF(RAM!J33,"NC Majeure")+COUNTIF('Min. Intérieur'!J33,"NC Majeure")+COUNTIF('CDG Capital'!J33,"NC Majeure")+COUNTIF(AtlanticRe!J33,"NC Majeure")+COUNTIF('Client A'!J33,"NC Majeure")+COUNTIF(Servier!J33,"NC Majeure")+COUNTIF(MEN!J33,"NC Majeure")+COUNTIF(ADM!J33,"NC Majeure")+COUNTIF('CDG DC'!J33,"NC Majeure")+COUNTIF('CDG ITOC'!J33,"NC Majeure")+COUNTIF(BPOST!J33,"NC Majeure")+COUNTIF('Graphtalk AIA'!J33,"NC Majeure")+COUNTIF('ONCF APPS'!J33,"NC Majeure")+COUNTIF('ONCF MW'!J33,"NC Majeure")+COUNTIF(ANEF!J33,"NC Majeure")+COUNTIF(Carrefour!J33,"NC Majeure")+COUNTIF('Vinci Construction'!J33,"NC Majeure")+COUNTIF(AXA!J33,"NC Majeure")+COUNTIF(OCP!J33,"NC Majeure") -> 0 | E24: =COUNTIF('CDG Sécurité'!K33,"NC Mineure")+COUNTIF(RAM!J33,"NC Mineure")+COUNTIF('Min. Intérieur'!J33,"NC Mineure")+COUNTIF('CDG Capital'!J33,"NC Mineure")+COUNTIF(AtlanticRe!J33,"NC Mineure")+COUNTIF('Client A'!J33,"NC Mineure")+COUNTIF(Servier!J33,"NC Mineure")+COUNTIF(MEN!J33,"NC Mineure")+COUNTIF(ADM!J33,"NC Mineure")+COUNTIF('CDG DC'!J33,"NC Mineure")+COUNTIF('CDG ITOC'!J33,"NC Mineure")+COUNTIF(BPOST!J33,"NC Mineure")+COUNTIF('Graphtalk AIA'!J33,"NC Mineure")+COUNTIF('ONCF APPS'!J33,"NC Mineure")+COUNTIF('ONCF MW'!J33,"NC Mineure")+COUNTIF(ANEF!J33,"NC Mineure")+COUNTIF(Carrefour!J33,"NC Mineure")+COUNTIF('Vinci Construction'!J33,"NC Mineure")+COUNTIF(AXA!J33,"NC Mineure")+COUNTIF(OCP!J33,"NC Mineure") -> 0 | F24: =COUNTIF('CDG Sécurité'!K33,"Observation")+COUNTIF(RAM!J33,"Observation")+COUNTIF('Min. Intérieur'!J33,"Observation")+COUNTIF('CDG Capital'!J33,"Observation")+COUNTIF(AtlanticRe!J33,"Observation")+COUNTIF('Client A'!J33,"Observation")+COUNTIF(Servier!J33,"Observation")+COUNTIF(MEN!J33,"Observation")+COUNTIF(ADM!J33,"Observation")+COUNTIF('CDG DC'!J33,"Observation")+COUNTIF('CDG ITOC'!J33,"Observation")+COUNTIF(BPOST!J33,"Observation")+COUNTIF('Graphtalk AIA'!J33,"Observation")+COUNTIF('ONCF APPS'!J33,"Observation")+COUNTIF('ONCF MW'!J33,"Observation")+COUNTIF(ANEF!J33,"Observation")+COUNTIF(Carrefour!J33,"Observation")+COUNTIF('Vinci Construction'!J33,"Observation")+COUNTIF(AXA!J33,"Observation")+COUNTIF(OCP!J33,"Observation") -> 0 | G24: =COUNTIF('CDG Sécurité'!K33,"OFI")+COUNTIF(RAM!J33,"OFI")+COUNTIF('Min. Intérieur'!J33,"OFI")+COUNTIF('CDG Capital'!J33,"OFI")+COUNTIF(AtlanticRe!J33,"OFI")+COUNTIF('Client A'!J33,"OFI")+COUNTIF(Servier!J33,"OFI")+COUNTIF(MEN!J33,"OFI")+COUNTIF(ADM!J33,"OFI")+COUNTIF('CDG DC'!J33,"OFI")+COUNTIF('CDG ITOC'!J33,"OFI")+COUNTIF(BPOST!J33,"OFI")+COUNTIF('Graphtalk AIA'!J33,"OFI")+COUNTIF('ONCF APPS'!J33,"OFI")+COUNTIF('ONCF MW'!J33,"OFI")+COUNTIF(ANEF!J33,"OFI")+COUNTIF(Carrefour!J33,"OFI")+COUNTIF('Vinci Construction'!J33,"OFI")+COUNTIF(AXA!J33,"OFI")+COUNTIF(OCP!J33,"OFI") -> 0 | H24: =D24+E24+F24+G24 -> 0 | I24: =IFERROR(H24/H43,0) -> 0 | J24: =IF(D24>0,"🔴 Critique",IF(H24>5,"🟠 Fort",IF(H24>2,"🟡 Modéré",IF(H24>0,"🔵 Faible","✅ Aucun")))) -> ✅ Aucun
A25: 20 | B25: 8.2.1 | C25: Communication avec le client | D25: =COUNTIF('CDG Sécurité'!K34,"NC Majeure")+COUNTIF(RAM!J34,"NC Majeure")+COUNTIF('Min. Intérieur'!J34,"NC Majeure")+COUNTIF('CDG Capital'!J34,"NC Majeure")+COUNTIF(AtlanticRe!J34,"NC Majeure")+COUNTIF('Client A'!J34,"NC Majeure")+COUNTIF(Servier!J34,"NC Majeure")+COUNTIF(MEN!J34,"NC Majeure")+COUNTIF(ADM!J34,"NC Majeure")+COUNTIF('CDG DC'!J34,"NC Majeure")+COUNTIF('CDG ITOC'!J34,"NC Majeure")+COUNTIF(BPOST!J34,"NC Majeure")+COUNTIF('Graphtalk AIA'!J34,"NC Majeure")+COUNTIF('ONCF APPS'!J34,"NC Majeure")+COUNTIF('ONCF MW'!J34,"NC Majeure")+COUNTIF(ANEF!J34,"NC Majeure")+COUNTIF(Carrefour!J34,"NC Majeure")+COUNTIF('Vinci Construction'!J34,"NC Majeure")+COUNTIF(AXA!J34,"NC Majeure")+COUNTIF(OCP!J34,"NC Majeure") -> 0 | E25: =COUNTIF('CDG Sécurité'!K34,"NC Mineure")+COUNTIF(RAM!J34,"NC Mineure")+COUNTIF('Min. Intérieur'!J34,"NC Mineure")+COUNTIF('CDG Capital'!J34,"NC Mineure")+COUNTIF(AtlanticRe!J34,"NC Mineure")+COUNTIF('Client A'!J34,"NC Mineure")+COUNTIF(Servier!J34,"NC Mineure")+COUNTIF(MEN!J34,"NC Mineure")+COUNTIF(ADM!J34,"NC Mineure")+COUNTIF('CDG DC'!J34,"NC Mineure")+COUNTIF('CDG ITOC'!J34,"NC Mineure")+COUNTIF(BPOST!J34,"NC Mineure")+COUNTIF('Graphtalk AIA'!J34,"NC Mineure")+COUNTIF('ONCF APPS'!J34,"NC Mineure")+COUNTIF('ONCF MW'!J34,"NC Mineure")+COUNTIF(ANEF!J34,"NC Mineure")+COUNTIF(Carrefour!J34,"NC Mineure")+COUNTIF('Vinci Construction'!J34,"NC Mineure")+COUNTIF(AXA!J34,"NC Mineure")+COUNTIF(OCP!J34,"NC Mineure") -> 0 | F25: =COUNTIF('CDG Sécurité'!K34,"Observation")+COUNTIF(RAM!J34,"Observation")+COUNTIF('Min. Intérieur'!J34,"Observation")+COUNTIF('CDG Capital'!J34,"Observation")+COUNTIF(AtlanticRe!J34,"Observation")+COUNTIF('Client A'!J34,"Observation")+COUNTIF(Servier!J34,"Observation")+COUNTIF(MEN!J34,"Observation")+COUNTIF(ADM!J34,"Observation")+COUNTIF('CDG DC'!J34,"Observation")+COUNTIF('CDG ITOC'!J34,"Observation")+COUNTIF(BPOST!J34,"Observation")+COUNTIF('Graphtalk AIA'!J34,"Observation")+COUNTIF('ONCF APPS'!J34,"Observation")+COUNTIF('ONCF MW'!J34,"Observation")+COUNTIF(ANEF!J34,"Observation")+COUNTIF(Carrefour!J34,"Observation")+COUNTIF('Vinci Construction'!J34,"Observation")+COUNTIF(AXA!J34,"Observation")+COUNTIF(OCP!J34,"Observation") -> 0 | G25: =COUNTIF('CDG Sécurité'!K34,"OFI")+COUNTIF(RAM!J34,"OFI")+COUNTIF('Min. Intérieur'!J34,"OFI")+COUNTIF('CDG Capital'!J34,"OFI")+COUNTIF(AtlanticRe!J34,"OFI")+COUNTIF('Client A'!J34,"OFI")+COUNTIF(Servier!J34,"OFI")+COUNTIF(MEN!J34,"OFI")+COUNTIF(ADM!J34,"OFI")+COUNTIF('CDG DC'!J34,"OFI")+COUNTIF('CDG ITOC'!J34,"OFI")+COUNTIF(BPOST!J34,"OFI")+COUNTIF('Graphtalk AIA'!J34,"OFI")+COUNTIF('ONCF APPS'!J34,"OFI")+COUNTIF('ONCF MW'!J34,"OFI")+COUNTIF(ANEF!J34,"OFI")+COUNTIF(Carrefour!J34,"OFI")+COUNTIF('Vinci Construction'!J34,"OFI")+COUNTIF(AXA!J34,"OFI")+COUNTIF(OCP!J34,"OFI") -> 0 | H25: =D25+E25+F25+G25 -> 0 | I25: =IFERROR(H25/H43,0) -> 0 | J25: =IF(D25>0,"🔴 Critique",IF(H25>5,"🟠 Fort",IF(H25>2,"🟡 Modéré",IF(H25>0,"🔵 Faible","✅ Aucun")))) -> ✅ Aucun
A26: 21 | B26: 8.2.2 | C26: Recueil des exigences client | D26: =COUNTIF('CDG Sécurité'!K35,"NC Majeure")+COUNTIF(RAM!J35,"NC Majeure")+COUNTIF('Min. Intérieur'!J35,"NC Majeure")+COUNTIF('CDG Capital'!J35,"NC Majeure")+COUNTIF(AtlanticRe!J35,"NC Majeure")+COUNTIF('Client A'!J35,"NC Majeure")+COUNTIF(Servier!J35,"NC Majeure")+COUNTIF(MEN!J35,"NC Majeure")+COUNTIF(ADM!J35,"NC Majeure")+COUNTIF('CDG DC'!J35,"NC Majeure")+COUNTIF('CDG ITOC'!J35,"NC Majeure")+COUNTIF(BPOST!J35,"NC Majeure")+COUNTIF('Graphtalk AIA'!J35,"NC Majeure")+COUNTIF('ONCF APPS'!J35,"NC Majeure")+COUNTIF('ONCF MW'!J35,"NC Majeure")+COUNTIF(ANEF!J35,"NC Majeure")+COUNTIF(Carrefour!J35,"NC Majeure")+COUNTIF('Vinci Construction'!J35,"NC Majeure")+COUNTIF(AXA!J35,"NC Majeure")+COUNTIF(OCP!J35,"NC Majeure") -> 0 | E26: =COUNTIF('CDG Sécurité'!K35,"NC Mineure")+COUNTIF(RAM!J35,"NC Mineure")+COUNTIF('Min. Intérieur'!J35,"NC Mineure")+COUNTIF('CDG Capital'!J35,"NC Mineure")+COUNTIF(AtlanticRe!J35,"NC Mineure")+COUNTIF('Client A'!J35,"NC Mineure")+COUNTIF(Servier!J35,"NC Mineure")+COUNTIF(MEN!J35,"NC Mineure")+COUNTIF(ADM!J35,"NC Mineure")+COUNTIF('CDG DC'!J35,"NC Mineure")+COUNTIF('CDG ITOC'!J35,"NC Mineure")+COUNTIF(BPOST!J35,"NC Mineure")+COUNTIF('Graphtalk AIA'!J35,"NC Mineure")+COUNTIF('ONCF APPS'!J35,"NC Mineure")+COUNTIF('ONCF MW'!J35,"NC Mineure")+COUNTIF(ANEF!J35,"NC Mineure")+COUNTIF(Carrefour!J35,"NC Mineure")+COUNTIF('Vinci Construction'!J35,"NC Mineure")+COUNTIF(AXA!J35,"NC Mineure")+COUNTIF(OCP!J35,"NC Mineure") -> 0 | F26: =COUNTIF('CDG Sécurité'!K35,"Observation")+COUNTIF(RAM!J35,"Observation")+COUNTIF('Min. Intérieur'!J35,"Observation")+COUNTIF('CDG Capital'!J35,"Observation")+COUNTIF(AtlanticRe!J35,"Observation")+COUNTIF('Client A'!J35,"Observation")+COUNTIF(Servier!J35,"Observation")+COUNTIF(MEN!J35,"Observation")+COUNTIF(ADM!J35,"Observation")+COUNTIF('CDG DC'!J35,"Observation")+COUNTIF('CDG ITOC'!J35,"Observation")+COUNTIF(BPOST!J35,"Observation")+COUNTIF('Graphtalk AIA'!J35,"Observation")+COUNTIF('ONCF APPS'!J35,"Observation")+COUNTIF('ONCF MW'!J35,"Observation")+COUNTIF(ANEF!J35,"Observation")+COUNTIF(Carrefour!J35,"Observation")+COUNTIF('Vinci Construction'!J35,"Observation")+COUNTIF(AXA!J35,"Observation")+COUNTIF(OCP!J35,"Observation") -> 0 | G26: =COUNTIF('CDG Sécurité'!K35,"OFI")+COUNTIF(RAM!J35,"OFI")+COUNTIF('Min. Intérieur'!J35,"OFI")+COUNTIF('CDG Capital'!J35,"OFI")+COUNTIF(AtlanticRe!J35,"OFI")+COUNTIF('Client A'!J35,"OFI")+COUNTIF(Servier!J35,"OFI")+COUNTIF(MEN!J35,"OFI")+COUNTIF(ADM!J35,"OFI")+COUNTIF('CDG DC'!J35,"OFI")+COUNTIF('CDG ITOC'!J35,"OFI")+COUNTIF(BPOST!J35,"OFI")+COUNTIF('Graphtalk AIA'!J35,"OFI")+COUNTIF('ONCF APPS'!J35,"OFI")+COUNTIF('ONCF MW'!J35,"OFI")+COUNTIF(ANEF!J35,"OFI")+COUNTIF(Carrefour!J35,"OFI")+COUNTIF('Vinci Construction'!J35,"OFI")+COUNTIF(AXA!J35,"OFI")+COUNTIF(OCP!J35,"OFI") -> 0 | H26: =D26+E26+F26+G26 -> 0 | I26: =IFERROR(H26/H43,0) -> 0 | J26: =IF(D26>0,"🔴 Critique",IF(H26>5,"🟠 Fort",IF(H26>2,"🟡 Modéré",IF(H26>0,"🔵 Faible","✅ Aucun")))) -> ✅ Aucun
A27: 22 | B27: 8.2.3 | C27: Revue avant engagement | D27: =COUNTIF('CDG Sécurité'!K36,"NC Majeure")+COUNTIF(RAM!J36,"NC Majeure")+COUNTIF('Min. Intérieur'!J36,"NC Majeure")+COUNTIF('CDG Capital'!J36,"NC Majeure")+COUNTIF(AtlanticRe!J36,"NC Majeure")+COUNTIF('Client A'!J36,"NC Majeure")+COUNTIF(Servier!J36,"NC Majeure")+COUNTIF(MEN!J36,"NC Majeure")+COUNTIF(ADM!J36,"NC Majeure")+COUNTIF('CDG DC'!J36,"NC Majeure")+COUNTIF('CDG ITOC'!J36,"NC Majeure")+COUNTIF(BPOST!J36,"NC Majeure")+COUNTIF('Graphtalk AIA'!J36,"NC Majeure")+COUNTIF('ONCF APPS'!J36,"NC Majeure")+COUNTIF('ONCF MW'!J36,"NC Majeure")+COUNTIF(ANEF!J36,"NC Majeure")+COUNTIF(Carrefour!J36,"NC Majeure")+COUNTIF('Vinci Construction'!J36,"NC Majeure")+COUNTIF(AXA!J36,"NC Majeure")+COUNTIF(OCP!J36,"NC Majeure") -> 0 | E27: =COUNTIF('CDG Sécurité'!K36,"NC Mineure")+COUNTIF(RAM!J36,"NC Mineure")+COUNTIF('Min. Intérieur'!J36,"NC Mineure")+COUNTIF('CDG Capital'!J36,"NC Mineure")+COUNTIF(AtlanticRe!J36,"NC Mineure")+COUNTIF('Client A'!J36,"NC Mineure")+COUNTIF(Servier!J36,"NC Mineure")+COUNTIF(MEN!J36,"NC Mineure")+COUNTIF(ADM!J36,"NC Mineure")+COUNTIF('CDG DC'!J36,"NC Mineure")+COUNTIF('CDG ITOC'!J36,"NC Mineure")+COUNTIF(BPOST!J36,"NC Mineure")+COUNTIF('Graphtalk AIA'!J36,"NC Mineure")+COUNTIF('ONCF APPS'!J36,"NC Mineure")+COUNTIF('ONCF MW'!J36,"NC Mineure")+COUNTIF(ANEF!J36,"NC Mineure")+COUNTIF(Carrefour!J36,"NC Mineure")+COUNTIF('Vinci Construction'!J36,"NC Mineure")+COUNTIF(AXA!J36,"NC Mineure")+COUNTIF(OCP!J36,"NC Mineure") -> 0 | F27: =COUNTIF('CDG Sécurité'!K36,"Observation")+COUNTIF(RAM!J36,"Observation")+COUNTIF('Min. Intérieur'!J36,"Observation")+COUNTIF('CDG Capital'!J36,"Observation")+COUNTIF(AtlanticRe!J36,"Observation")+COUNTIF('Client A'!J36,"Observation")+COUNTIF(Servier!J36,"Observation")+COUNTIF(MEN!J36,"Observation")+COUNTIF(ADM!J36,"Observation")+COUNTIF('CDG DC'!J36,"Observation")+COUNTIF('CDG ITOC'!J36,"Observation")+COUNTIF(BPOST!J36,"Observation")+COUNTIF('Graphtalk AIA'!J36,"Observation")+COUNTIF('ONCF APPS'!J36,"Observation")+COUNTIF('ONCF MW'!J36,"Observation")+COUNTIF(ANEF!J36,"Observation")+COUNTIF(Carrefour!J36,"Observation")+COUNTIF('Vinci Construction'!J36,"Observation")+COUNTIF(AXA!J36,"Observation")+COUNTIF(OCP!J36,"Observation") -> 0 | G27: =COUNTIF('CDG Sécurité'!K36,"OFI")+COUNTIF(RAM!J36,"OFI")+COUNTIF('Min. Intérieur'!J36,"OFI")+COUNTIF('CDG Capital'!J36,"OFI")+COUNTIF(AtlanticRe!J36,"OFI")+COUNTIF('Client A'!J36,"OFI")+COUNTIF(Servier!J36,"OFI")+COUNTIF(MEN!J36,"OFI")+COUNTIF(ADM!J36,"OFI")+COUNTIF('CDG DC'!J36,"OFI")+COUNTIF('CDG ITOC'!J36,"OFI")+COUNTIF(BPOST!J36,"OFI")+COUNTIF('Graphtalk AIA'!J36,"OFI")+COUNTIF('ONCF APPS'!J36,"OFI")+COUNTIF('ONCF MW'!J36,"OFI")+COUNTIF(ANEF!J36,"OFI")+COUNTIF(Carrefour!J36,"OFI")+COUNTIF('Vinci Construction'!J36,"OFI")+COUNTIF(AXA!J36,"OFI")+COUNTIF(OCP!J36,"OFI") -> 0 | H27: =D27+E27+F27+G27 -> 0 | I27: =IFERROR(H27/H43,0) -> 0 | J27: =IF(D27>0,"🔴 Critique",IF(H27>5,"🟠 Fort",IF(H27>2,"🟡 Modéré",IF(H27>0,"🔵 Faible","✅ Aucun")))) -> ✅ Aucun
A28: 23 | B28: 8.2.4 | C28: Gestion des modifications contractuelles | D28: =COUNTIF('CDG Sécurité'!K37,"NC Majeure")+COUNTIF(RAM!J37,"NC Majeure")+COUNTIF('Min. Intérieur'!J37,"NC Majeure")+COUNTIF('CDG Capital'!J37,"NC Majeure")+COUNTIF(AtlanticRe!J37,"NC Majeure")+COUNTIF('Client A'!J37,"NC Majeure")+COUNTIF(Servier!J37,"NC Majeure")+COUNTIF(MEN!J37,"NC Majeure")+COUNTIF(ADM!J37,"NC Majeure")+COUNTIF('CDG DC'!J37,"NC Majeure")+COUNTIF('CDG ITOC'!J37,"NC Majeure")+COUNTIF(BPOST!J37,"NC Majeure")+COUNTIF('Graphtalk AIA'!J37,"NC Majeure")+COUNTIF('ONCF APPS'!J37,"NC Majeure")+COUNTIF('ONCF MW'!J37,"NC Majeure")+COUNTIF(ANEF!J37,"NC Majeure")+COUNTIF(Carrefour!J37,"NC Majeure")+COUNTIF('Vinci Construction'!J37,"NC Majeure")+COUNTIF(AXA!J37,"NC Majeure")+COUNTIF(OCP!J37,"NC Majeure") -> 0 | E28: =COUNTIF('CDG Sécurité'!K37,"NC Mineure")+COUNTIF(RAM!J37,"NC Mineure")+COUNTIF('Min. Intérieur'!J37,"NC Mineure")+COUNTIF('CDG Capital'!J37,"NC Mineure")+COUNTIF(AtlanticRe!J37,"NC Mineure")+COUNTIF('Client A'!J37,"NC Mineure")+COUNTIF(Servier!J37,"NC Mineure")+COUNTIF(MEN!J37,"NC Mineure")+COUNTIF(ADM!J37,"NC Mineure")+COUNTIF('CDG DC'!J37,"NC Mineure")+COUNTIF('CDG ITOC'!J37,"NC Mineure")+COUNTIF(BPOST!J37,"NC Mineure")+COUNTIF('Graphtalk AIA'!J37,"NC Mineure")+COUNTIF('ONCF APPS'!J37,"NC Mineure")+COUNTIF('ONCF MW'!J37,"NC Mineure")+COUNTIF(ANEF!J37,"NC Mineure")+COUNTIF(Carrefour!J37,"NC Mineure")+COUNTIF('Vinci Construction'!J37,"NC Mineure")+COUNTIF(AXA!J37,"NC Mineure")+COUNTIF(OCP!J37,"NC Mineure") -> 0 | F28: =COUNTIF('CDG Sécurité'!K37,"Observation")+COUNTIF(RAM!J37,"Observation")+COUNTIF('Min. Intérieur'!J37,"Observation")+COUNTIF('CDG Capital'!J37,"Observation")+COUNTIF(AtlanticRe!J37,"Observation")+COUNTIF('Client A'!J37,"Observation")+COUNTIF(Servier!J37,"Observation")+COUNTIF(MEN!J37,"Observation")+COUNTIF(ADM!J37,"Observation")+COUNTIF('CDG DC'!J37,"Observation")+COUNTIF('CDG ITOC'!J37,"Observation")+COUNTIF(BPOST!J37,"Observation")+COUNTIF('Graphtalk AIA'!J37,"Observation")+COUNTIF('ONCF APPS'!J37,"Observation")+COUNTIF('ONCF MW'!J37,"Observation")+COUNTIF(ANEF!J37,"Observation")+COUNTIF(Carrefour!J37,"Observation")+COUNTIF('Vinci Construction'!J37,"Observation")+COUNTIF(AXA!J37,"Observation")+COUNTIF(OCP!J37,"Observation") -> 0 | G28: =COUNTIF('CDG Sécurité'!K37,"OFI")+COUNTIF(RAM!J37,"OFI")+COUNTIF('Min. Intérieur'!J37,"OFI")+COUNTIF('CDG Capital'!J37,"OFI")+COUNTIF(AtlanticRe!J37,"OFI")+COUNTIF('Client A'!J37,"OFI")+COUNTIF(Servier!J37,"OFI")+COUNTIF(MEN!J37,"OFI")+COUNTIF(ADM!J37,"OFI")+COUNTIF('CDG DC'!J37,"OFI")+COUNTIF('CDG ITOC'!J37,"OFI")+COUNTIF(BPOST!J37,"OFI")+COUNTIF('Graphtalk AIA'!J37,"OFI")+COUNTIF('ONCF APPS'!J37,"OFI")+COUNTIF('ONCF MW'!J37,"OFI")+COUNTIF(ANEF!J37,"OFI")+COUNTIF(Carrefour!J37,"OFI")+COUNTIF('Vinci Construction'!J37,"OFI")+COUNTIF(AXA!J37,"OFI")+COUNTIF(OCP!J37,"OFI") -> 0 | H28: =D28+E28+F28+G28 -> 0 | I28: =IFERROR(H28/H43,0) -> 0 | J28: =IF(D28>0,"🔴 Critique",IF(H28>5,"🟠 Fort",IF(H28>2,"🟡 Modéré",IF(H28>0,"🔵 Faible","✅ Aucun")))) -> ✅ Aucun
A29: 24 | B29: 8.4 | C29: Maîtrise des sous-traitants | D29: =COUNTIF('CDG Sécurité'!K38,"NC Majeure")+COUNTIF(RAM!J38,"NC Majeure")+COUNTIF('Min. Intérieur'!J38,"NC Majeure")+COUNTIF('CDG Capital'!J38,"NC Majeure")+COUNTIF(AtlanticRe!J38,"NC Majeure")+COUNTIF('Client A'!J38,"NC Majeure")+COUNTIF(Servier!J38,"NC Majeure")+COUNTIF(MEN!J38,"NC Majeure")+COUNTIF(ADM!J38,"NC Majeure")+COUNTIF('CDG DC'!J38,"NC Majeure")+COUNTIF('CDG ITOC'!J38,"NC Majeure")+COUNTIF(BPOST!J38,"NC Majeure")+COUNTIF('Graphtalk AIA'!J38,"NC Majeure")+COUNTIF('ONCF APPS'!J38,"NC Majeure")+COUNTIF('ONCF MW'!J38,"NC Majeure")+COUNTIF(ANEF!J38,"NC Majeure")+COUNTIF(Carrefour!J38,"NC Majeure")+COUNTIF('Vinci Construction'!J38,"NC Majeure")+COUNTIF(AXA!J38,"NC Majeure")+COUNTIF(OCP!J38,"NC Majeure") -> 0 | E29: =COUNTIF('CDG Sécurité'!K38,"NC Mineure")+COUNTIF(RAM!J38,"NC Mineure")+COUNTIF('Min. Intérieur'!J38,"NC Mineure")+COUNTIF('CDG Capital'!J38,"NC Mineure")+COUNTIF(AtlanticRe!J38,"NC Mineure")+COUNTIF('Client A'!J38,"NC Mineure")+COUNTIF(Servier!J38,"NC Mineure")+COUNTIF(MEN!J38,"NC Mineure")+COUNTIF(ADM!J38,"NC Mineure")+COUNTIF('CDG DC'!J38,"NC Mineure")+COUNTIF('CDG ITOC'!J38,"NC Mineure")+COUNTIF(BPOST!J38,"NC Mineure")+COUNTIF('Graphtalk AIA'!J38,"NC Mineure")+COUNTIF('ONCF APPS'!J38,"NC Mineure")+COUNTIF('ONCF MW'!J38,"NC Mineure")+COUNTIF(ANEF!J38,"NC Mineure")+COUNTIF(Carrefour!J38,"NC Mineure")+COUNTIF('Vinci Construction'!J38,"NC Mineure")+COUNTIF(AXA!J38,"NC Mineure")+COUNTIF(OCP!J38,"NC Mineure") -> 0 | F29: =COUNTIF('CDG Sécurité'!K38,"Observation")+COUNTIF(RAM!J38,"Observation")+COUNTIF('Min. Intérieur'!J38,"Observation")+COUNTIF('CDG Capital'!J38,"Observation")+COUNTIF(AtlanticRe!J38,"Observation")+COUNTIF('Client A'!J38,"Observation")+COUNTIF(Servier!J38,"Observation")+COUNTIF(MEN!J38,"Observation")+COUNTIF(ADM!J38,"Observation")+COUNTIF('CDG DC'!J38,"Observation")+COUNTIF('CDG ITOC'!J38,"Observation")+COUNTIF(BPOST!J38,"Observation")+COUNTIF('Graphtalk AIA'!J38,"Observation")+COUNTIF('ONCF APPS'!J38,"Observation")+COUNTIF('ONCF MW'!J38,"Observation")+COUNTIF(ANEF!J38,"Observation")+COUNTIF(Carrefour!J38,"Observation")+COUNTIF('Vinci Construction'!J38,"Observation")+COUNTIF(AXA!J38,"Observation")+COUNTIF(OCP!J38,"Observation") -> 0 | G29: =COUNTIF('CDG Sécurité'!K38,"OFI")+COUNTIF(RAM!J38,"OFI")+COUNTIF('Min. Intérieur'!J38,"OFI")+COUNTIF('CDG Capital'!J38,"OFI")+COUNTIF(AtlanticRe!J38,"OFI")+COUNTIF('Client A'!J38,"OFI")+COUNTIF(Servier!J38,"OFI")+COUNTIF(MEN!J38,"OFI")+COUNTIF(ADM!J38,"OFI")+COUNTIF('CDG DC'!J38,"OFI")+COUNTIF('CDG ITOC'!J38,"OFI")+COUNTIF(BPOST!J38,"OFI")+COUNTIF('Graphtalk AIA'!J38,"OFI")+COUNTIF('ONCF APPS'!J38,"OFI")+COUNTIF('ONCF MW'!J38,"OFI")+COUNTIF(ANEF!J38,"OFI")+COUNTIF(Carrefour!J38,"OFI")+COUNTIF('Vinci Construction'!J38,"OFI")+COUNTIF(AXA!J38,"OFI")+COUNTIF(OCP!J38,"OFI") -> 0 | H29: =D29+E29+F29+G29 -> 0 | I29: =IFERROR(H29/H43,0) -> 0 | J29: =IF(D29>0,"🔴 Critique",IF(H29>5,"🟠 Fort",IF(H29>2,"🟡 Modéré",IF(H29>0,"🔵 Faible","✅ Aucun")))) -> ✅ Aucun
A30: 25 | B30: 8.5.1 | C30: Contrôle de la réalisation du service | D30: =COUNTIF('CDG Sécurité'!K39,"NC Majeure")+COUNTIF(RAM!J39,"NC Majeure")+COUNTIF('Min. Intérieur'!J39,"NC Majeure")+COUNTIF('CDG Capital'!J39,"NC Majeure")+COUNTIF(AtlanticRe!J39,"NC Majeure")+COUNTIF('Client A'!J39,"NC Majeure")+COUNTIF(Servier!J39,"NC Majeure")+COUNTIF(MEN!J39,"NC Majeure")+COUNTIF(ADM!J39,"NC Majeure")+COUNTIF('CDG DC'!J39,"NC Majeure")+COUNTIF('CDG ITOC'!J39,"NC Majeure")+COUNTIF(BPOST!J39,"NC Majeure")+COUNTIF('Graphtalk AIA'!J39,"NC Majeure")+COUNTIF('ONCF APPS'!J39,"NC Majeure")+COUNTIF('ONCF MW'!J39,"NC Majeure")+COUNTIF(ANEF!J39,"NC Majeure")+COUNTIF(Carrefour!J39,"NC Majeure")+COUNTIF('Vinci Construction'!J39,"NC Majeure")+COUNTIF(AXA!J39,"NC Majeure")+COUNTIF(OCP!J39,"NC Majeure") -> 0 | E30: =COUNTIF('CDG Sécurité'!K39,"NC Mineure")+COUNTIF(RAM!J39,"NC Mineure")+COUNTIF('Min. Intérieur'!J39,"NC Mineure")+COUNTIF('CDG Capital'!J39,"NC Mineure")+COUNTIF(AtlanticRe!J39,"NC Mineure")+COUNTIF('Client A'!J39,"NC Mineure")+COUNTIF(Servier!J39,"NC Mineure")+COUNTIF(MEN!J39,"NC Mineure")+COUNTIF(ADM!J39,"NC Mineure")+COUNTIF('CDG DC'!J39,"NC Mineure")+COUNTIF('CDG ITOC'!J39,"NC Mineure")+COUNTIF(BPOST!J39,"NC Mineure")+COUNTIF('Graphtalk AIA'!J39,"NC Mineure")+COUNTIF('ONCF APPS'!J39,"NC Mineure")+COUNTIF('ONCF MW'!J39,"NC Mineure")+COUNTIF(ANEF!J39,"NC Mineure")+COUNTIF(Carrefour!J39,"NC Mineure")+COUNTIF('Vinci Construction'!J39,"NC Mineure")+COUNTIF(AXA!J39,"NC Mineure")+COUNTIF(OCP!J39,"NC Mineure") -> 0 | F30: =COUNTIF('CDG Sécurité'!K39,"Observation")+COUNTIF(RAM!J39,"Observation")+COUNTIF('Min. Intérieur'!J39,"Observation")+COUNTIF('CDG Capital'!J39,"Observation")+COUNTIF(AtlanticRe!J39,"Observation")+COUNTIF('Client A'!J39,"Observation")+COUNTIF(Servier!J39,"Observation")+COUNTIF(MEN!J39,"Observation")+COUNTIF(ADM!J39,"Observation")+COUNTIF('CDG DC'!J39,"Observation")+COUNTIF('CDG ITOC'!J39,"Observation")+COUNTIF(BPOST!J39,"Observation")+COUNTIF('Graphtalk AIA'!J39,"Observation")+COUNTIF('ONCF APPS'!J39,"Observation")+COUNTIF('ONCF MW'!J39,"Observation")+COUNTIF(ANEF!J39,"Observation")+COUNTIF(Carrefour!J39,"Observation")+COUNTIF('Vinci Construction'!J39,"Observation")+COUNTIF(AXA!J39,"Observation")+COUNTIF(OCP!J39,"Observation") -> 0 | G30: =COUNTIF('CDG Sécurité'!K39,"OFI")+COUNTIF(RAM!J39,"OFI")+COUNTIF('Min. Intérieur'!J39,"OFI")+COUNTIF('CDG Capital'!J39,"OFI")+COUNTIF(AtlanticRe!J39,"OFI")+COUNTIF('Client A'!J39,"OFI")+COUNTIF(Servier!J39,"OFI")+COUNTIF(MEN!J39,"OFI")+COUNTIF(ADM!J39,"OFI")+COUNTIF('CDG DC'!J39,"OFI")+COUNTIF('CDG ITOC'!J39,"OFI")+COUNTIF(BPOST!J39,"OFI")+COUNTIF('Graphtalk AIA'!J39,"OFI")+COUNTIF('ONCF APPS'!J39,"OFI")+COUNTIF('ONCF MW'!J39,"OFI")+COUNTIF(ANEF!J39,"OFI")+COUNTIF(Carrefour!J39,"OFI")+COUNTIF('Vinci Construction'!J39,"OFI")+COUNTIF(AXA!J39,"OFI")+COUNTIF(OCP!J39,"OFI") -> 0 | H30: =D30+E30+F30+G30 -> 0 | I30: =IFERROR(H30/H43,0) -> 0 | J30: =IF(D30>0,"🔴 Critique",IF(H30>5,"🟠 Fort",IF(H30>2,"🟡 Modéré",IF(H30>0,"🔵 Faible","✅ Aucun")))) -> ✅ Aucun
A31: 26 | B31: 8.5.2 | C31: Identification et traçabilité | D31: =COUNTIF('CDG Sécurité'!K40,"NC Majeure")+COUNTIF(RAM!J40,"NC Majeure")+COUNTIF('Min. Intérieur'!J40,"NC Majeure")+COUNTIF('CDG Capital'!J40,"NC Majeure")+COUNTIF(AtlanticRe!J40,"NC Majeure")+COUNTIF('Client A'!J40,"NC Majeure")+COUNTIF(Servier!J40,"NC Majeure")+COUNTIF(MEN!J40,"NC Majeure")+COUNTIF(ADM!J40,"NC Majeure")+COUNTIF('CDG DC'!J40,"NC Majeure")+COUNTIF('CDG ITOC'!J40,"NC Majeure")+COUNTIF(BPOST!J40,"NC Majeure")+COUNTIF('Graphtalk AIA'!J40,"NC Majeure")+COUNTIF('ONCF APPS'!J40,"NC Majeure")+COUNTIF('ONCF MW'!J40,"NC Majeure")+COUNTIF(ANEF!J40,"NC Majeure")+COUNTIF(Carrefour!J40,"NC Majeure")+COUNTIF('Vinci Construction'!J40,"NC Majeure")+COUNTIF(AXA!J40,"NC Majeure")+COUNTIF(OCP!J40,"NC Majeure") -> 0 | E31: =COUNTIF('CDG Sécurité'!K40,"NC Mineure")+COUNTIF(RAM!J40,"NC Mineure")+COUNTIF('Min. Intérieur'!J40,"NC Mineure")+COUNTIF('CDG Capital'!J40,"NC Mineure")+COUNTIF(AtlanticRe!J40,"NC Mineure")+COUNTIF('Client A'!J40,"NC Mineure")+COUNTIF(Servier!J40,"NC Mineure")+COUNTIF(MEN!J40,"NC Mineure")+COUNTIF(ADM!J40,"NC Mineure")+COUNTIF('CDG DC'!J40,"NC Mineure")+COUNTIF('CDG ITOC'!J40,"NC Mineure")+COUNTIF(BPOST!J40,"NC Mineure")+COUNTIF('Graphtalk AIA'!J40,"NC Mineure")+COUNTIF('ONCF APPS'!J40,"NC Mineure")+COUNTIF('ONCF MW'!J40,"NC Mineure")+COUNTIF(ANEF!J40,"NC Mineure")+COUNTIF(Carrefour!J40,"NC Mineure")+COUNTIF('Vinci Construction'!J40,"NC Mineure")+COUNTIF(AXA!J40,"NC Mineure")+COUNTIF(OCP!J40,"NC Mineure") -> 0 | F31: =COUNTIF('CDG Sécurité'!K40,"Observation")+COUNTIF(RAM!J40,"Observation")+COUNTIF('Min. Intérieur'!J40,"Observation")+COUNTIF('CDG Capital'!J40,"Observation")+COUNTIF(AtlanticRe!J40,"Observation")+COUNTIF('Client A'!J40,"Observation")+COUNTIF(Servier!J40,"Observation")+COUNTIF(MEN!J40,"Observation")+COUNTIF(ADM!J40,"Observation")+COUNTIF('CDG DC'!J40,"Observation")+COUNTIF('CDG ITOC'!J40,"Observation")+COUNTIF(BPOST!J40,"Observation")+COUNTIF('Graphtalk AIA'!J40,"Observation")+COUNTIF('ONCF APPS'!J40,"Observation")+COUNTIF('ONCF MW'!J40,"Observation")+COUNTIF(ANEF!J40,"Observation")+COUNTIF(Carrefour!J40,"Observation")+COUNTIF('Vinci Construction'!J40,"Observation")+COUNTIF(AXA!J40,"Observation")+COUNTIF(OCP!J40,"Observation") -> 0 | G31: =COUNTIF('CDG Sécurité'!K40,"OFI")+COUNTIF(RAM!J40,"OFI")+COUNTIF('Min. Intérieur'!J40,"OFI")+COUNTIF('CDG Capital'!J40,"OFI")+COUNTIF(AtlanticRe!J40,"OFI")+COUNTIF('Client A'!J40,"OFI")+COUNTIF(Servier!J40,"OFI")+COUNTIF(MEN!J40,"OFI")+COUNTIF(ADM!J40,"OFI")+COUNTIF('CDG DC'!J40,"OFI")+COUNTIF('CDG ITOC'!J40,"OFI")+COUNTIF(BPOST!J40,"OFI")+COUNTIF('Graphtalk AIA'!J40,"OFI")+COUNTIF('ONCF APPS'!J40,"OFI")+COUNTIF('ONCF MW'!J40,"OFI")+COUNTIF(ANEF!J40,"OFI")+COUNTIF(Carrefour!J40,"OFI")+COUNTIF('Vinci Construction'!J40,"OFI")+COUNTIF(AXA!J40,"OFI")+COUNTIF(OCP!J40,"OFI") -> 0 | H31: =D31+E31+F31+G31 -> 0 | I31: =IFERROR(H31/H43,0) -> 0 | J31: =IF(D31>0,"🔴 Critique",IF(H31>5,"🟠 Fort",IF(H31>2,"🟡 Modéré",IF(H31>0,"🔵 Faible","✅ Aucun")))) -> ✅ Aucun
A32: 27 | B32: 8.5.4 | C32: Protection des données client | D32: =COUNTIF('CDG Sécurité'!K41,"NC Majeure")+COUNTIF(RAM!J41,"NC Majeure")+COUNTIF('Min. Intérieur'!J41,"NC Majeure")+COUNTIF('CDG Capital'!J41,"NC Majeure")+COUNTIF(AtlanticRe!J41,"NC Majeure")+COUNTIF('Client A'!J41,"NC Majeure")+COUNTIF(Servier!J41,"NC Majeure")+COUNTIF(MEN!J41,"NC Majeure")+COUNTIF(ADM!J41,"NC Majeure")+COUNTIF('CDG DC'!J41,"NC Majeure")+COUNTIF('CDG ITOC'!J41,"NC Majeure")+COUNTIF(BPOST!J41,"NC Majeure")+COUNTIF('Graphtalk AIA'!J41,"NC Majeure")+COUNTIF('ONCF APPS'!J41,"NC Majeure")+COUNTIF('ONCF MW'!J41,"NC Majeure")+COUNTIF(ANEF!J41,"NC Majeure")+COUNTIF(Carrefour!J41,"NC Majeure")+COUNTIF('Vinci Construction'!J41,"NC Majeure")+COUNTIF(AXA!J41,"NC Majeure")+COUNTIF(OCP!J41,"NC Majeure") -> 0 | E32: =COUNTIF('CDG Sécurité'!K41,"NC Mineure")+COUNTIF(RAM!J41,"NC Mineure")+COUNTIF('Min. Intérieur'!J41,"NC Mineure")+COUNTIF('CDG Capital'!J41,"NC Mineure")+COUNTIF(AtlanticRe!J41,"NC Mineure")+COUNTIF('Client A'!J41,"NC Mineure")+COUNTIF(Servier!J41,"NC Mineure")+COUNTIF(MEN!J41,"NC Mineure")+COUNTIF(ADM!J41,"NC Mineure")+COUNTIF('CDG DC'!J41,"NC Mineure")+COUNTIF('CDG ITOC'!J41,"NC Mineure")+COUNTIF(BPOST!J41,"NC Mineure")+COUNTIF('Graphtalk AIA'!J41,"NC Mineure")+COUNTIF('ONCF APPS'!J41,"NC Mineure")+COUNTIF('ONCF MW'!J41,"NC Mineure")+COUNTIF(ANEF!J41,"NC Mineure")+COUNTIF(Carrefour!J41,"NC Mineure")+COUNTIF('Vinci Construction'!J41,"NC Mineure")+COUNTIF(AXA!J41,"NC Mineure")+COUNTIF(OCP!J41,"NC Mineure") -> 0 | F32: =COUNTIF('CDG Sécurité'!K41,"Observation")+COUNTIF(RAM!J41,"Observation")+COUNTIF('Min. Intérieur'!J41,"Observation")+COUNTIF('CDG Capital'!J41,"Observation")+COUNTIF(AtlanticRe!J41,"Observation")+COUNTIF('Client A'!J41,"Observation")+COUNTIF(Servier!J41,"Observation")+COUNTIF(MEN!J41,"Observation")+COUNTIF(ADM!J41,"Observation")+COUNTIF('CDG DC'!J41,"Observation")+COUNTIF('CDG ITOC'!J41,"Observation")+COUNTIF(BPOST!J41,"Observation")+COUNTIF('Graphtalk AIA'!J41,"Observation")+COUNTIF('ONCF APPS'!J41,"Observation")+COUNTIF('ONCF MW'!J41,"Observation")+COUNTIF(ANEF!J41,"Observation")+COUNTIF(Carrefour!J41,"Observation")+COUNTIF('Vinci Construction'!J41,"Observation")+COUNTIF(AXA!J41,"Observation")+COUNTIF(OCP!J41,"Observation") -> 0 | G32: =COUNTIF('CDG Sécurité'!K41,"OFI")+COUNTIF(RAM!J41,"OFI")+COUNTIF('Min. Intérieur'!J41,"OFI")+COUNTIF('CDG Capital'!J41,"OFI")+COUNTIF(AtlanticRe!J41,"OFI")+COUNTIF('Client A'!J41,"OFI")+COUNTIF(Servier!J41,"OFI")+COUNTIF(MEN!J41,"OFI")+COUNTIF(ADM!J41,"OFI")+COUNTIF('CDG DC'!J41,"OFI")+COUNTIF('CDG ITOC'!J41,"OFI")+COUNTIF(BPOST!J41,"OFI")+COUNTIF('Graphtalk AIA'!J41,"OFI")+COUNTIF('ONCF APPS'!J41,"OFI")+COUNTIF('ONCF MW'!J41,"OFI")+COUNTIF(ANEF!J41,"OFI")+COUNTIF(Carrefour!J41,"OFI")+COUNTIF('Vinci Construction'!J41,"OFI")+COUNTIF(AXA!J41,"OFI")+COUNTIF(OCP!J41,"OFI") -> 0 | H32: =D32+E32+F32+G32 -> 0 | I32: =IFERROR(H32/H43,0) -> 0 | J32: =IF(D32>0,"🔴 Critique",IF(H32>5,"🟠 Fort",IF(H32>2,"🟡 Modéré",IF(H32>0,"🔵 Faible","✅ Aucun")))) -> ✅ Aucun
A33: 28 | B33: 8.5.6 | C33: Contrôle des modifications de service | D33: =COUNTIF('CDG Sécurité'!K42,"NC Majeure")+COUNTIF(RAM!J42,"NC Majeure")+COUNTIF('Min. Intérieur'!J42,"NC Majeure")+COUNTIF('CDG Capital'!J42,"NC Majeure")+COUNTIF(AtlanticRe!J42,"NC Majeure")+COUNTIF('Client A'!J42,"NC Majeure")+COUNTIF(Servier!J42,"NC Majeure")+COUNTIF(MEN!J42,"NC Majeure")+COUNTIF(ADM!J42,"NC Majeure")+COUNTIF('CDG DC'!J42,"NC Majeure")+COUNTIF('CDG ITOC'!J42,"NC Majeure")+COUNTIF(BPOST!J42,"NC Majeure")+COUNTIF('Graphtalk AIA'!J42,"NC Majeure")+COUNTIF('ONCF APPS'!J42,"NC Majeure")+COUNTIF('ONCF MW'!J42,"NC Majeure")+COUNTIF(ANEF!J42,"NC Majeure")+COUNTIF(Carrefour!J42,"NC Majeure")+COUNTIF('Vinci Construction'!J42,"NC Majeure")+COUNTIF(AXA!J42,"NC Majeure")+COUNTIF(OCP!J42,"NC Majeure") -> 0 | E33: =COUNTIF('CDG Sécurité'!K42,"NC Mineure")+COUNTIF(RAM!J42,"NC Mineure")+COUNTIF('Min. Intérieur'!J42,"NC Mineure")+COUNTIF('CDG Capital'!J42,"NC Mineure")+COUNTIF(AtlanticRe!J42,"NC Mineure")+COUNTIF('Client A'!J42,"NC Mineure")+COUNTIF(Servier!J42,"NC Mineure")+COUNTIF(MEN!J42,"NC Mineure")+COUNTIF(ADM!J42,"NC Mineure")+COUNTIF('CDG DC'!J42,"NC Mineure")+COUNTIF('CDG ITOC'!J42,"NC Mineure")+COUNTIF(BPOST!J42,"NC Mineure")+COUNTIF('Graphtalk AIA'!J42,"NC Mineure")+COUNTIF('ONCF APPS'!J42,"NC Mineure")+COUNTIF('ONCF MW'!J42,"NC Mineure")+COUNTIF(ANEF!J42,"NC Mineure")+COUNTIF(Carrefour!J42,"NC Mineure")+COUNTIF('Vinci Construction'!J42,"NC Mineure")+COUNTIF(AXA!J42,"NC Mineure")+COUNTIF(OCP!J42,"NC Mineure") -> 0 | F33: =COUNTIF('CDG Sécurité'!K42,"Observation")+COUNTIF(RAM!J42,"Observation")+COUNTIF('Min. Intérieur'!J42,"Observation")+COUNTIF('CDG Capital'!J42,"Observation")+COUNTIF(AtlanticRe!J42,"Observation")+COUNTIF('Client A'!J42,"Observation")+COUNTIF(Servier!J42,"Observation")+COUNTIF(MEN!J42,"Observation")+COUNTIF(ADM!J42,"Observation")+COUNTIF('CDG DC'!J42,"Observation")+COUNTIF('CDG ITOC'!J42,"Observation")+COUNTIF(BPOST!J42,"Observation")+COUNTIF('Graphtalk AIA'!J42,"Observation")+COUNTIF('ONCF APPS'!J42,"Observation")+COUNTIF('ONCF MW'!J42,"Observation")+COUNTIF(ANEF!J42,"Observation")+COUNTIF(Carrefour!J42,"Observation")+COUNTIF('Vinci Construction'!J42,"Observation")+COUNTIF(AXA!J42,"Observation")+COUNTIF(OCP!J42,"Observation") -> 0 | G33: =COUNTIF('CDG Sécurité'!K42,"OFI")+COUNTIF(RAM!J42,"OFI")+COUNTIF('Min. Intérieur'!J42,"OFI")+COUNTIF('CDG Capital'!J42,"OFI")+COUNTIF(AtlanticRe!J42,"OFI")+COUNTIF('Client A'!J42,"OFI")+COUNTIF(Servier!J42,"OFI")+COUNTIF(MEN!J42,"OFI")+COUNTIF(ADM!J42,"OFI")+COUNTIF('CDG DC'!J42,"OFI")+COUNTIF('CDG ITOC'!J42,"OFI")+COUNTIF(BPOST!J42,"OFI")+COUNTIF('Graphtalk AIA'!J42,"OFI")+COUNTIF('ONCF APPS'!J42,"OFI")+COUNTIF('ONCF MW'!J42,"OFI")+COUNTIF(ANEF!J42,"OFI")+COUNTIF(Carrefour!J42,"OFI")+COUNTIF('Vinci Construction'!J42,"OFI")+COUNTIF(AXA!J42,"OFI")+COUNTIF(OCP!J42,"OFI") -> 0 | H33: =D33+E33+F33+G33 -> 0 | I33: =IFERROR(H33/H43,0) -> 0 | J33: =IF(D33>0,"🔴 Critique",IF(H33>5,"🟠 Fort",IF(H33>2,"🟡 Modéré",IF(H33>0,"🔵 Faible","✅ Aucun")))) -> ✅ Aucun
A34: 29 | B34: 8.6 | C34: Contrôle avant livraison | D34: =COUNTIF('CDG Sécurité'!K43,"NC Majeure")+COUNTIF(RAM!J43,"NC Majeure")+COUNTIF('Min. Intérieur'!J43,"NC Majeure")+COUNTIF('CDG Capital'!J43,"NC Majeure")+COUNTIF(AtlanticRe!J43,"NC Majeure")+COUNTIF('Client A'!J43,"NC Majeure")+COUNTIF(Servier!J43,"NC Majeure")+COUNTIF(MEN!J43,"NC Majeure")+COUNTIF(ADM!J43,"NC Majeure")+COUNTIF('CDG DC'!J43,"NC Majeure")+COUNTIF('CDG ITOC'!J43,"NC Majeure")+COUNTIF(BPOST!J43,"NC Majeure")+COUNTIF('Graphtalk AIA'!J43,"NC Majeure")+COUNTIF('ONCF APPS'!J43,"NC Majeure")+COUNTIF('ONCF MW'!J43,"NC Majeure")+COUNTIF(ANEF!J43,"NC Majeure")+COUNTIF(Carrefour!J43,"NC Majeure")+COUNTIF('Vinci Construction'!J43,"NC Majeure")+COUNTIF(AXA!J43,"NC Majeure")+COUNTIF(OCP!J43,"NC Majeure") -> 0 | E34: =COUNTIF('CDG Sécurité'!K43,"NC Mineure")+COUNTIF(RAM!J43,"NC Mineure")+COUNTIF('Min. Intérieur'!J43,"NC Mineure")+COUNTIF('CDG Capital'!J43,"NC Mineure")+COUNTIF(AtlanticRe!J43,"NC Mineure")+COUNTIF('Client A'!J43,"NC Mineure")+COUNTIF(Servier!J43,"NC Mineure")+COUNTIF(MEN!J43,"NC Mineure")+COUNTIF(ADM!J43,"NC Mineure")+COUNTIF('CDG DC'!J43,"NC Mineure")+COUNTIF('CDG ITOC'!J43,"NC Mineure")+COUNTIF(BPOST!J43,"NC Mineure")+COUNTIF('Graphtalk AIA'!J43,"NC Mineure")+COUNTIF('ONCF APPS'!J43,"NC Mineure")+COUNTIF('ONCF MW'!J43,"NC Mineure")+COUNTIF(ANEF!J43,"NC Mineure")+COUNTIF(Carrefour!J43,"NC Mineure")+COUNTIF('Vinci Construction'!J43,"NC Mineure")+COUNTIF(AXA!J43,"NC Mineure")+COUNTIF(OCP!J43,"NC Mineure") -> 0 | F34: =COUNTIF('CDG Sécurité'!K43,"Observation")+COUNTIF(RAM!J43,"Observation")+COUNTIF('Min. Intérieur'!J43,"Observation")+COUNTIF('CDG Capital'!J43,"Observation")+COUNTIF(AtlanticRe!J43,"Observation")+COUNTIF('Client A'!J43,"Observation")+COUNTIF(Servier!J43,"Observation")+COUNTIF(MEN!J43,"Observation")+COUNTIF(ADM!J43,"Observation")+COUNTIF('CDG DC'!J43,"Observation")+COUNTIF('CDG ITOC'!J43,"Observation")+COUNTIF(BPOST!J43,"Observation")+COUNTIF('Graphtalk AIA'!J43,"Observation")+COUNTIF('ONCF APPS'!J43,"Observation")+COUNTIF('ONCF MW'!J43,"Observation")+COUNTIF(ANEF!J43,"Observation")+COUNTIF(Carrefour!J43,"Observation")+COUNTIF('Vinci Construction'!J43,"Observation")+COUNTIF(AXA!J43,"Observation")+COUNTIF(OCP!J43,"Observation") -> 0 | G34: =COUNTIF('CDG Sécurité'!K43,"OFI")+COUNTIF(RAM!J43,"OFI")+COUNTIF('Min. Intérieur'!J43,"OFI")+COUNTIF('CDG Capital'!J43,"OFI")+COUNTIF(AtlanticRe!J43,"OFI")+COUNTIF('Client A'!J43,"OFI")+COUNTIF(Servier!J43,"OFI")+COUNTIF(MEN!J43,"OFI")+COUNTIF(ADM!J43,"OFI")+COUNTIF('CDG DC'!J43,"OFI")+COUNTIF('CDG ITOC'!J43,"OFI")+COUNTIF(BPOST!J43,"OFI")+COUNTIF('Graphtalk AIA'!J43,"OFI")+COUNTIF('ONCF APPS'!J43,"OFI")+COUNTIF('ONCF MW'!J43,"OFI")+COUNTIF(ANEF!J43,"OFI")+COUNTIF(Carrefour!J43,"OFI")+COUNTIF('Vinci Construction'!J43,"OFI")+COUNTIF(AXA!J43,"OFI")+COUNTIF(OCP!J43,"OFI") -> 0 | H34: =D34+E34+F34+G34 -> 0 | I34: =IFERROR(H34/H43,0) -> 0 | J34: =IF(D34>0,"🔴 Critique",IF(H34>5,"🟠 Fort",IF(H34>2,"🟡 Modéré",IF(H34>0,"🔵 Faible","✅ Aucun")))) -> ✅ Aucun
A35: 30 | B35: 8.7 | C35: Traitement des non-conformités | D35: =COUNTIF('CDG Sécurité'!K44,"NC Majeure")+COUNTIF(RAM!J44,"NC Majeure")+COUNTIF('Min. Intérieur'!J44,"NC Majeure")+COUNTIF('CDG Capital'!J44,"NC Majeure")+COUNTIF(AtlanticRe!J44,"NC Majeure")+COUNTIF('Client A'!J44,"NC Majeure")+COUNTIF(Servier!J44,"NC Majeure")+COUNTIF(MEN!J44,"NC Majeure")+COUNTIF(ADM!J44,"NC Majeure")+COUNTIF('CDG DC'!J44,"NC Majeure")+COUNTIF('CDG ITOC'!J44,"NC Majeure")+COUNTIF(BPOST!J44,"NC Majeure")+COUNTIF('Graphtalk AIA'!J44,"NC Majeure")+COUNTIF('ONCF APPS'!J44,"NC Majeure")+COUNTIF('ONCF MW'!J44,"NC Majeure")+COUNTIF(ANEF!J44,"NC Majeure")+COUNTIF(Carrefour!J44,"NC Majeure")+COUNTIF('Vinci Construction'!J44,"NC Majeure")+COUNTIF(AXA!J44,"NC Majeure")+COUNTIF(OCP!J44,"NC Majeure") -> 0 | E35: =COUNTIF('CDG Sécurité'!K44,"NC Mineure")+COUNTIF(RAM!J44,"NC Mineure")+COUNTIF('Min. Intérieur'!J44,"NC Mineure")+COUNTIF('CDG Capital'!J44,"NC Mineure")+COUNTIF(AtlanticRe!J44,"NC Mineure")+COUNTIF('Client A'!J44,"NC Mineure")+COUNTIF(Servier!J44,"NC Mineure")+COUNTIF(MEN!J44,"NC Mineure")+COUNTIF(ADM!J44,"NC Mineure")+COUNTIF('CDG DC'!J44,"NC Mineure")+COUNTIF('CDG ITOC'!J44,"NC Mineure")+COUNTIF(BPOST!J44,"NC Mineure")+COUNTIF('Graphtalk AIA'!J44,"NC Mineure")+COUNTIF('ONCF APPS'!J44,"NC Mineure")+COUNTIF('ONCF MW'!J44,"NC Mineure")+COUNTIF(ANEF!J44,"NC Mineure")+COUNTIF(Carrefour!J44,"NC Mineure")+COUNTIF('Vinci Construction'!J44,"NC Mineure")+COUNTIF(AXA!J44,"NC Mineure")+COUNTIF(OCP!J44,"NC Mineure") -> 0 | F35: =COUNTIF('CDG Sécurité'!K44,"Observation")+COUNTIF(RAM!J44,"Observation")+COUNTIF('Min. Intérieur'!J44,"Observation")+COUNTIF('CDG Capital'!J44,"Observation")+COUNTIF(AtlanticRe!J44,"Observation")+COUNTIF('Client A'!J44,"Observation")+COUNTIF(Servier!J44,"Observation")+COUNTIF(MEN!J44,"Observation")+COUNTIF(ADM!J44,"Observation")+COUNTIF('CDG DC'!J44,"Observation")+COUNTIF('CDG ITOC'!J44,"Observation")+COUNTIF(BPOST!J44,"Observation")+COUNTIF('Graphtalk AIA'!J44,"Observation")+COUNTIF('ONCF APPS'!J44,"Observation")+COUNTIF('ONCF MW'!J44,"Observation")+COUNTIF(ANEF!J44,"Observation")+COUNTIF(Carrefour!J44,"Observation")+COUNTIF('Vinci Construction'!J44,"Observation")+COUNTIF(AXA!J44,"Observation")+COUNTIF(OCP!J44,"Observation") -> 0 | G35: =COUNTIF('CDG Sécurité'!K44,"OFI")+COUNTIF(RAM!J44,"OFI")+COUNTIF('Min. Intérieur'!J44,"OFI")+COUNTIF('CDG Capital'!J44,"OFI")+COUNTIF(AtlanticRe!J44,"OFI")+COUNTIF('Client A'!J44,"OFI")+COUNTIF(Servier!J44,"OFI")+COUNTIF(MEN!J44,"OFI")+COUNTIF(ADM!J44,"OFI")+COUNTIF('CDG DC'!J44,"OFI")+COUNTIF('CDG ITOC'!J44,"OFI")+COUNTIF(BPOST!J44,"OFI")+COUNTIF('Graphtalk AIA'!J44,"OFI")+COUNTIF('ONCF APPS'!J44,"OFI")+COUNTIF('ONCF MW'!J44,"OFI")+COUNTIF(ANEF!J44,"OFI")+COUNTIF(Carrefour!J44,"OFI")+COUNTIF('Vinci Construction'!J44,"OFI")+COUNTIF(AXA!J44,"OFI")+COUNTIF(OCP!J44,"OFI") -> 0 | H35: =D35+E35+F35+G35 -> 0 | I35: =IFERROR(H35/H43,0) -> 0 | J35: =IF(D35>0,"🔴 Critique",IF(H35>5,"🟠 Fort",IF(H35>2,"🟡 Modéré",IF(H35>0,"🔵 Faible","✅ Aucun")))) -> ✅ Aucun
A36: 31 | B36: 9.1.1 | C36: Mesure de la performance | D36: =COUNTIF('CDG Sécurité'!K45,"NC Majeure")+COUNTIF(RAM!J45,"NC Majeure")+COUNTIF('Min. Intérieur'!J45,"NC Majeure")+COUNTIF('CDG Capital'!J45,"NC Majeure")+COUNTIF(AtlanticRe!J45,"NC Majeure")+COUNTIF('Client A'!J45,"NC Majeure")+COUNTIF(Servier!J45,"NC Majeure")+COUNTIF(MEN!J45,"NC Majeure")+COUNTIF(ADM!J45,"NC Majeure")+COUNTIF('CDG DC'!J45,"NC Majeure")+COUNTIF('CDG ITOC'!J45,"NC Majeure")+COUNTIF(BPOST!J45,"NC Majeure")+COUNTIF('Graphtalk AIA'!J45,"NC Majeure")+COUNTIF('ONCF APPS'!J45,"NC Majeure")+COUNTIF('ONCF MW'!J45,"NC Majeure")+COUNTIF(ANEF!J45,"NC Majeure")+COUNTIF(Carrefour!J45,"NC Majeure")+COUNTIF('Vinci Construction'!J45,"NC Majeure")+COUNTIF(AXA!J45,"NC Majeure")+COUNTIF(OCP!J45,"NC Majeure") -> 0 | E36: =COUNTIF('CDG Sécurité'!K45,"NC Mineure")+COUNTIF(RAM!J45,"NC Mineure")+COUNTIF('Min. Intérieur'!J45,"NC Mineure")+COUNTIF('CDG Capital'!J45,"NC Mineure")+COUNTIF(AtlanticRe!J45,"NC Mineure")+COUNTIF('Client A'!J45,"NC Mineure")+COUNTIF(Servier!J45,"NC Mineure")+COUNTIF(MEN!J45,"NC Mineure")+COUNTIF(ADM!J45,"NC Mineure")+COUNTIF('CDG DC'!J45,"NC Mineure")+COUNTIF('CDG ITOC'!J45,"NC Mineure")+COUNTIF(BPOST!J45,"NC Mineure")+COUNTIF('Graphtalk AIA'!J45,"NC Mineure")+COUNTIF('ONCF APPS'!J45,"NC Mineure")+COUNTIF('ONCF MW'!J45,"NC Mineure")+COUNTIF(ANEF!J45,"NC Mineure")+COUNTIF(Carrefour!J45,"NC Mineure")+COUNTIF('Vinci Construction'!J45,"NC Mineure")+COUNTIF(AXA!J45,"NC Mineure")+COUNTIF(OCP!J45,"NC Mineure") -> 0 | F36: =COUNTIF('CDG Sécurité'!K45,"Observation")+COUNTIF(RAM!J45,"Observation")+COUNTIF('Min. Intérieur'!J45,"Observation")+COUNTIF('CDG Capital'!J45,"Observation")+COUNTIF(AtlanticRe!J45,"Observation")+COUNTIF('Client A'!J45,"Observation")+COUNTIF(Servier!J45,"Observation")+COUNTIF(MEN!J45,"Observation")+COUNTIF(ADM!J45,"Observation")+COUNTIF('CDG DC'!J45,"Observation")+COUNTIF('CDG ITOC'!J45,"Observation")+COUNTIF(BPOST!J45,"Observation")+COUNTIF('Graphtalk AIA'!J45,"Observation")+COUNTIF('ONCF APPS'!J45,"Observation")+COUNTIF('ONCF MW'!J45,"Observation")+COUNTIF(ANEF!J45,"Observation")+COUNTIF(Carrefour!J45,"Observation")+COUNTIF('Vinci Construction'!J45,"Observation")+COUNTIF(AXA!J45,"Observation")+COUNTIF(OCP!J45,"Observation") -> 0 | G36: =COUNTIF('CDG Sécurité'!K45,"OFI")+COUNTIF(RAM!J45,"OFI")+COUNTIF('Min. Intérieur'!J45,"OFI")+COUNTIF('CDG Capital'!J45,"OFI")+COUNTIF(AtlanticRe!J45,"OFI")+COUNTIF('Client A'!J45,"OFI")+COUNTIF(Servier!J45,"OFI")+COUNTIF(MEN!J45,"OFI")+COUNTIF(ADM!J45,"OFI")+COUNTIF('CDG DC'!J45,"OFI")+COUNTIF('CDG ITOC'!J45,"OFI")+COUNTIF(BPOST!J45,"OFI")+COUNTIF('Graphtalk AIA'!J45,"OFI")+COUNTIF('ONCF APPS'!J45,"OFI")+COUNTIF('ONCF MW'!J45,"OFI")+COUNTIF(ANEF!J45,"OFI")+COUNTIF(Carrefour!J45,"OFI")+COUNTIF('Vinci Construction'!J45,"OFI")+COUNTIF(AXA!J45,"OFI")+COUNTIF(OCP!J45,"OFI") -> 0 | H36: =D36+E36+F36+G36 -> 0 | I36: =IFERROR(H36/H43,0) -> 0 | J36: =IF(D36>0,"🔴 Critique",IF(H36>5,"🟠 Fort",IF(H36>2,"🟡 Modéré",IF(H36>0,"🔵 Faible","✅ Aucun")))) -> ✅ Aucun
A37: 32 | B37: 9.1.2 | C37: Satisfaction client | D37: =COUNTIF('CDG Sécurité'!K46,"NC Majeure")+COUNTIF(RAM!J46,"NC Majeure")+COUNTIF('Min. Intérieur'!J46,"NC Majeure")+COUNTIF('CDG Capital'!J46,"NC Majeure")+COUNTIF(AtlanticRe!J46,"NC Majeure")+COUNTIF('Client A'!J46,"NC Majeure")+COUNTIF(Servier!J46,"NC Majeure")+COUNTIF(MEN!J46,"NC Majeure")+COUNTIF(ADM!J46,"NC Majeure")+COUNTIF('CDG DC'!J46,"NC Majeure")+COUNTIF('CDG ITOC'!J46,"NC Majeure")+COUNTIF(BPOST!J46,"NC Majeure")+COUNTIF('Graphtalk AIA'!J46,"NC Majeure")+COUNTIF('ONCF APPS'!J46,"NC Majeure")+COUNTIF('ONCF MW'!J46,"NC Majeure")+COUNTIF(ANEF!J46,"NC Majeure")+COUNTIF(Carrefour!J46,"NC Majeure")+COUNTIF('Vinci Construction'!J46,"NC Majeure")+COUNTIF(AXA!J46,"NC Majeure")+COUNTIF(OCP!J46,"NC Majeure") -> 0 | E37: =COUNTIF('CDG Sécurité'!K46,"NC Mineure")+COUNTIF(RAM!J46,"NC Mineure")+COUNTIF('Min. Intérieur'!J46,"NC Mineure")+COUNTIF('CDG Capital'!J46,"NC Mineure")+COUNTIF(AtlanticRe!J46,"NC Mineure")+COUNTIF('Client A'!J46,"NC Mineure")+COUNTIF(Servier!J46,"NC Mineure")+COUNTIF(MEN!J46,"NC Mineure")+COUNTIF(ADM!J46,"NC Mineure")+COUNTIF('CDG DC'!J46,"NC Mineure")+COUNTIF('CDG ITOC'!J46,"NC Mineure")+COUNTIF(BPOST!J46,"NC Mineure")+COUNTIF('Graphtalk AIA'!J46,"NC Mineure")+COUNTIF('ONCF APPS'!J46,"NC Mineure")+COUNTIF('ONCF MW'!J46,"NC Mineure")+COUNTIF(ANEF!J46,"NC Mineure")+COUNTIF(Carrefour!J46,"NC Mineure")+COUNTIF('Vinci Construction'!J46,"NC Mineure")+COUNTIF(AXA!J46,"NC Mineure")+COUNTIF(OCP!J46,"NC Mineure") -> 0 | F37: =COUNTIF('CDG Sécurité'!K46,"Observation")+COUNTIF(RAM!J46,"Observation")+COUNTIF('Min. Intérieur'!J46,"Observation")+COUNTIF('CDG Capital'!J46,"Observation")+COUNTIF(AtlanticRe!J46,"Observation")+COUNTIF('Client A'!J46,"Observation")+COUNTIF(Servier!J46,"Observation")+COUNTIF(MEN!J46,"Observation")+COUNTIF(ADM!J46,"Observation")+COUNTIF('CDG DC'!J46,"Observation")+COUNTIF('CDG ITOC'!J46,"Observation")+COUNTIF(BPOST!J46,"Observation")+COUNTIF('Graphtalk AIA'!J46,"Observation")+COUNTIF('ONCF APPS'!J46,"Observation")+COUNTIF('ONCF MW'!J46,"Observation")+COUNTIF(ANEF!J46,"Observation")+COUNTIF(Carrefour!J46,"Observation")+COUNTIF('Vinci Construction'!J46,"Observation")+COUNTIF(AXA!J46,"Observation")+COUNTIF(OCP!J46,"Observation") -> 0 | G37: =COUNTIF('CDG Sécurité'!K46,"OFI")+COUNTIF(RAM!J46,"OFI")+COUNTIF('Min. Intérieur'!J46,"OFI")+COUNTIF('CDG Capital'!J46,"OFI")+COUNTIF(AtlanticRe!J46,"OFI")+COUNTIF('Client A'!J46,"OFI")+COUNTIF(Servier!J46,"OFI")+COUNTIF(MEN!J46,"OFI")+COUNTIF(ADM!J46,"OFI")+COUNTIF('CDG DC'!J46,"OFI")+COUNTIF('CDG ITOC'!J46,"OFI")+COUNTIF(BPOST!J46,"OFI")+COUNTIF('Graphtalk AIA'!J46,"OFI")+COUNTIF('ONCF APPS'!J46,"OFI")+COUNTIF('ONCF MW'!J46,"OFI")+COUNTIF(ANEF!J46,"OFI")+COUNTIF(Carrefour!J46,"OFI")+COUNTIF('Vinci Construction'!J46,"OFI")+COUNTIF(AXA!J46,"OFI")+COUNTIF(OCP!J46,"OFI") -> 0 | H37: =D37+E37+F37+G37 -> 0 | I37: =IFERROR(H37/H43,0) -> 0 | J37: =IF(D37>0,"🔴 Critique",IF(H37>5,"🟠 Fort",IF(H37>2,"🟡 Modéré",IF(H37>0,"🔵 Faible","✅ Aucun")))) -> ✅ Aucun
A38: 33 | B38: 9.1.3 | C38: Analyse des résultats | D38: =COUNTIF('CDG Sécurité'!K47,"NC Majeure")+COUNTIF(RAM!J47,"NC Majeure")+COUNTIF('Min. Intérieur'!J47,"NC Majeure")+COUNTIF('CDG Capital'!J47,"NC Majeure")+COUNTIF(AtlanticRe!J47,"NC Majeure")+COUNTIF('Client A'!J47,"NC Majeure")+COUNTIF(Servier!J47,"NC Majeure")+COUNTIF(MEN!J47,"NC Majeure")+COUNTIF(ADM!J47,"NC Majeure")+COUNTIF('CDG DC'!J47,"NC Majeure")+COUNTIF('CDG ITOC'!J47,"NC Majeure")+COUNTIF(BPOST!J47,"NC Majeure")+COUNTIF('Graphtalk AIA'!J47,"NC Majeure")+COUNTIF('ONCF APPS'!J47,"NC Majeure")+COUNTIF('ONCF MW'!J47,"NC Majeure")+COUNTIF(ANEF!J47,"NC Majeure")+COUNTIF(Carrefour!J47,"NC Majeure")+COUNTIF('Vinci Construction'!J47,"NC Majeure")+COUNTIF(AXA!J47,"NC Majeure")+COUNTIF(OCP!J47,"NC Majeure") -> 0 | E38: =COUNTIF('CDG Sécurité'!K47,"NC Mineure")+COUNTIF(RAM!J47,"NC Mineure")+COUNTIF('Min. Intérieur'!J47,"NC Mineure")+COUNTIF('CDG Capital'!J47,"NC Mineure")+COUNTIF(AtlanticRe!J47,"NC Mineure")+COUNTIF('Client A'!J47,"NC Mineure")+COUNTIF(Servier!J47,"NC Mineure")+COUNTIF(MEN!J47,"NC Mineure")+COUNTIF(ADM!J47,"NC Mineure")+COUNTIF('CDG DC'!J47,"NC Mineure")+COUNTIF('CDG ITOC'!J47,"NC Mineure")+COUNTIF(BPOST!J47,"NC Mineure")+COUNTIF('Graphtalk AIA'!J47,"NC Mineure")+COUNTIF('ONCF APPS'!J47,"NC Mineure")+COUNTIF('ONCF MW'!J47,"NC Mineure")+COUNTIF(ANEF!J47,"NC Mineure")+COUNTIF(Carrefour!J47,"NC Mineure")+COUNTIF('Vinci Construction'!J47,"NC Mineure")+COUNTIF(AXA!J47,"NC Mineure")+COUNTIF(OCP!J47,"NC Mineure") -> 0 | F38: =COUNTIF('CDG Sécurité'!K47,"Observation")+COUNTIF(RAM!J47,"Observation")+COUNTIF('Min. Intérieur'!J47,"Observation")+COUNTIF('CDG Capital'!J47,"Observation")+COUNTIF(AtlanticRe!J47,"Observation")+COUNTIF('Client A'!J47,"Observation")+COUNTIF(Servier!J47,"Observation")+COUNTIF(MEN!J47,"Observation")+COUNTIF(ADM!J47,"Observation")+COUNTIF('CDG DC'!J47,"Observation")+COUNTIF('CDG ITOC'!J47,"Observation")+COUNTIF(BPOST!J47,"Observation")+COUNTIF('Graphtalk AIA'!J47,"Observation")+COUNTIF('ONCF APPS'!J47,"Observation")+COUNTIF('ONCF MW'!J47,"Observation")+COUNTIF(ANEF!J47,"Observation")+COUNTIF(Carrefour!J47,"Observation")+COUNTIF('Vinci Construction'!J47,"Observation")+COUNTIF(AXA!J47,"Observation")+COUNTIF(OCP!J47,"Observation") -> 0 | G38: =COUNTIF('CDG Sécurité'!K47,"OFI")+COUNTIF(RAM!J47,"OFI")+COUNTIF('Min. Intérieur'!J47,"OFI")+COUNTIF('CDG Capital'!J47,"OFI")+COUNTIF(AtlanticRe!J47,"OFI")+COUNTIF('Client A'!J47,"OFI")+COUNTIF(Servier!J47,"OFI")+COUNTIF(MEN!J47,"OFI")+COUNTIF(ADM!J47,"OFI")+COUNTIF('CDG DC'!J47,"OFI")+COUNTIF('CDG ITOC'!J47,"OFI")+COUNTIF(BPOST!J47,"OFI")+COUNTIF('Graphtalk AIA'!J47,"OFI")+COUNTIF('ONCF APPS'!J47,"OFI")+COUNTIF('ONCF MW'!J47,"OFI")+COUNTIF(ANEF!J47,"OFI")+COUNTIF(Carrefour!J47,"OFI")+COUNTIF('Vinci Construction'!J47,"OFI")+COUNTIF(AXA!J47,"OFI")+COUNTIF(OCP!J47,"OFI") -> 0 | H38: =D38+E38+F38+G38 -> 0 | I38: =IFERROR(H38/H43,0) -> 0 | J38: =IF(D38>0,"🔴 Critique",IF(H38>5,"🟠 Fort",IF(H38>2,"🟡 Modéré",IF(H38>0,"🔵 Faible","✅ Aucun")))) -> ✅ Aucun
A39: 34 | B39: 9.2 | C39: Audits internes (QHC) | D39: =COUNTIF('CDG Sécurité'!K48,"NC Majeure")+COUNTIF(RAM!J48,"NC Majeure")+COUNTIF('Min. Intérieur'!J48,"NC Majeure")+COUNTIF('CDG Capital'!J48,"NC Majeure")+COUNTIF(AtlanticRe!J48,"NC Majeure")+COUNTIF('Client A'!J48,"NC Majeure")+COUNTIF(Servier!J48,"NC Majeure")+COUNTIF(MEN!J48,"NC Majeure")+COUNTIF(ADM!J48,"NC Majeure")+COUNTIF('CDG DC'!J48,"NC Majeure")+COUNTIF('CDG ITOC'!J48,"NC Majeure")+COUNTIF(BPOST!J48,"NC Majeure")+COUNTIF('Graphtalk AIA'!J48,"NC Majeure")+COUNTIF('ONCF APPS'!J48,"NC Majeure")+COUNTIF('ONCF MW'!J48,"NC Majeure")+COUNTIF(ANEF!J48,"NC Majeure")+COUNTIF(Carrefour!J48,"NC Majeure")+COUNTIF('Vinci Construction'!J48,"NC Majeure")+COUNTIF(AXA!J48,"NC Majeure")+COUNTIF(OCP!J48,"NC Majeure") -> 0 | E39: =COUNTIF('CDG Sécurité'!K48,"NC Mineure")+COUNTIF(RAM!J48,"NC Mineure")+COUNTIF('Min. Intérieur'!J48,"NC Mineure")+COUNTIF('CDG Capital'!J48,"NC Mineure")+COUNTIF(AtlanticRe!J48,"NC Mineure")+COUNTIF('Client A'!J48,"NC Mineure")+COUNTIF(Servier!J48,"NC Mineure")+COUNTIF(MEN!J48,"NC Mineure")+COUNTIF(ADM!J48,"NC Mineure")+COUNTIF('CDG DC'!J48,"NC Mineure")+COUNTIF('CDG ITOC'!J48,"NC Mineure")+COUNTIF(BPOST!J48,"NC Mineure")+COUNTIF('Graphtalk AIA'!J48,"NC Mineure")+COUNTIF('ONCF APPS'!J48,"NC Mineure")+COUNTIF('ONCF MW'!J48,"NC Mineure")+COUNTIF(ANEF!J48,"NC Mineure")+COUNTIF(Carrefour!J48,"NC Mineure")+COUNTIF('Vinci Construction'!J48,"NC Mineure")+COUNTIF(AXA!J48,"NC Mineure")+COUNTIF(OCP!J48,"NC Mineure") -> 0 | F39: =COUNTIF('CDG Sécurité'!K48,"Observation")+COUNTIF(RAM!J48,"Observation")+COUNTIF('Min. Intérieur'!J48,"Observation")+COUNTIF('CDG Capital'!J48,"Observation")+COUNTIF(AtlanticRe!J48,"Observation")+COUNTIF('Client A'!J48,"Observation")+COUNTIF(Servier!J48,"Observation")+COUNTIF(MEN!J48,"Observation")+COUNTIF(ADM!J48,"Observation")+COUNTIF('CDG DC'!J48,"Observation")+COUNTIF('CDG ITOC'!J48,"Observation")+COUNTIF(BPOST!J48,"Observation")+COUNTIF('Graphtalk AIA'!J48,"Observation")+COUNTIF('ONCF APPS'!J48,"Observation")+COUNTIF('ONCF MW'!J48,"Observation")+COUNTIF(ANEF!J48,"Observation")+COUNTIF(Carrefour!J48,"Observation")+COUNTIF('Vinci Construction'!J48,"Observation")+COUNTIF(AXA!J48,"Observation")+COUNTIF(OCP!J48,"Observation") -> 0 | G39: =COUNTIF('CDG Sécurité'!K48,"OFI")+COUNTIF(RAM!J48,"OFI")+COUNTIF('Min. Intérieur'!J48,"OFI")+COUNTIF('CDG Capital'!J48,"OFI")+COUNTIF(AtlanticRe!J48,"OFI")+COUNTIF('Client A'!J48,"OFI")+COUNTIF(Servier!J48,"OFI")+COUNTIF(MEN!J48,"OFI")+COUNTIF(ADM!J48,"OFI")+COUNTIF('CDG DC'!J48,"OFI")+COUNTIF('CDG ITOC'!J48,"OFI")+COUNTIF(BPOST!J48,"OFI")+COUNTIF('Graphtalk AIA'!J48,"OFI")+COUNTIF('ONCF APPS'!J48,"OFI")+COUNTIF('ONCF MW'!J48,"OFI")+COUNTIF(ANEF!J48,"OFI")+COUNTIF(Carrefour!J48,"OFI")+COUNTIF('Vinci Construction'!J48,"OFI")+COUNTIF(AXA!J48,"OFI")+COUNTIF(OCP!J48,"OFI") -> 0 | H39: =D39+E39+F39+G39 -> 0 | I39: =IFERROR(H39/H43,0) -> 0 | J39: =IF(D39>0,"🔴 Critique",IF(H39>5,"🟠 Fort",IF(H39>2,"🟡 Modéré",IF(H39>0,"🔵 Faible","✅ Aucun")))) -> ✅ Aucun
A40: 35 | B40: 9.3 | C40: Revue de direction | D40: =COUNTIF('CDG Sécurité'!K49,"NC Majeure")+COUNTIF(RAM!J49,"NC Majeure")+COUNTIF('Min. Intérieur'!J49,"NC Majeure")+COUNTIF('CDG Capital'!J49,"NC Majeure")+COUNTIF(AtlanticRe!J49,"NC Majeure")+COUNTIF('Client A'!J49,"NC Majeure")+COUNTIF(Servier!J49,"NC Majeure")+COUNTIF(MEN!J49,"NC Majeure")+COUNTIF(ADM!J49,"NC Majeure")+COUNTIF('CDG DC'!J49,"NC Majeure")+COUNTIF('CDG ITOC'!J49,"NC Majeure")+COUNTIF(BPOST!J49,"NC Majeure")+COUNTIF('Graphtalk AIA'!J49,"NC Majeure")+COUNTIF('ONCF APPS'!J49,"NC Majeure")+COUNTIF('ONCF MW'!J49,"NC Majeure")+COUNTIF(ANEF!J49,"NC Majeure")+COUNTIF(Carrefour!J49,"NC Majeure")+COUNTIF('Vinci Construction'!J49,"NC Majeure")+COUNTIF(AXA!J49,"NC Majeure")+COUNTIF(OCP!J49,"NC Majeure") -> 0 | E40: =COUNTIF('CDG Sécurité'!K49,"NC Mineure")+COUNTIF(RAM!J49,"NC Mineure")+COUNTIF('Min. Intérieur'!J49,"NC Mineure")+COUNTIF('CDG Capital'!J49,"NC Mineure")+COUNTIF(AtlanticRe!J49,"NC Mineure")+COUNTIF('Client A'!J49,"NC Mineure")+COUNTIF(Servier!J49,"NC Mineure")+COUNTIF(MEN!J49,"NC Mineure")+COUNTIF(ADM!J49,"NC Mineure")+COUNTIF('CDG DC'!J49,"NC Mineure")+COUNTIF('CDG ITOC'!J49,"NC Mineure")+COUNTIF(BPOST!J49,"NC Mineure")+COUNTIF('Graphtalk AIA'!J49,"NC Mineure")+COUNTIF('ONCF APPS'!J49,"NC Mineure")+COUNTIF('ONCF MW'!J49,"NC Mineure")+COUNTIF(ANEF!J49,"NC Mineure")+COUNTIF(Carrefour!J49,"NC Mineure")+COUNTIF('Vinci Construction'!J49,"NC Mineure")+COUNTIF(AXA!J49,"NC Mineure")+COUNTIF(OCP!J49,"NC Mineure") -> 0 | F40: =COUNTIF('CDG Sécurité'!K49,"Observation")+COUNTIF(RAM!J49,"Observation")+COUNTIF('Min. Intérieur'!J49,"Observation")+COUNTIF('CDG Capital'!J49,"Observation")+COUNTIF(AtlanticRe!J49,"Observation")+COUNTIF('Client A'!J49,"Observation")+COUNTIF(Servier!J49,"Observation")+COUNTIF(MEN!J49,"Observation")+COUNTIF(ADM!J49,"Observation")+COUNTIF('CDG DC'!J49,"Observation")+COUNTIF('CDG ITOC'!J49,"Observation")+COUNTIF(BPOST!J49,"Observation")+COUNTIF('Graphtalk AIA'!J49,"Observation")+COUNTIF('ONCF APPS'!J49,"Observation")+COUNTIF('ONCF MW'!J49,"Observation")+COUNTIF(ANEF!J49,"Observation")+COUNTIF(Carrefour!J49,"Observation")+COUNTIF('Vinci Construction'!J49,"Observation")+COUNTIF(AXA!J49,"Observation")+COUNTIF(OCP!J49,"Observation") -> 0 | G40: =COUNTIF('CDG Sécurité'!K49,"OFI")+COUNTIF(RAM!J49,"OFI")+COUNTIF('Min. Intérieur'!J49,"OFI")+COUNTIF('CDG Capital'!J49,"OFI")+COUNTIF(AtlanticRe!J49,"OFI")+COUNTIF('Client A'!J49,"OFI")+COUNTIF(Servier!J49,"OFI")+COUNTIF(MEN!J49,"OFI")+COUNTIF(ADM!J49,"OFI")+COUNTIF('CDG DC'!J49,"OFI")+COUNTIF('CDG ITOC'!J49,"OFI")+COUNTIF(BPOST!J49,"OFI")+COUNTIF('Graphtalk AIA'!J49,"OFI")+COUNTIF('ONCF APPS'!J49,"OFI")+COUNTIF('ONCF MW'!J49,"OFI")+COUNTIF(ANEF!J49,"OFI")+COUNTIF(Carrefour!J49,"OFI")+COUNTIF('Vinci Construction'!J49,"OFI")+COUNTIF(AXA!J49,"OFI")+COUNTIF(OCP!J49,"OFI") -> 0 | H40: =D40+E40+F40+G40 -> 0 | I40: =IFERROR(H40/H43,0) -> 0 | J40: =IF(D40>0,"🔴 Critique",IF(H40>5,"🟠 Fort",IF(H40>2,"🟡 Modéré",IF(H40>0,"🔵 Faible","✅ Aucun")))) -> ✅ Aucun
A41: 36 | B41: 10.1 | C41: Amélioration continue | D41: =COUNTIF('CDG Sécurité'!K50,"NC Majeure")+COUNTIF(RAM!J50,"NC Majeure")+COUNTIF('Min. Intérieur'!J50,"NC Majeure")+COUNTIF('CDG Capital'!J50,"NC Majeure")+COUNTIF(AtlanticRe!J50,"NC Majeure")+COUNTIF('Client A'!J50,"NC Majeure")+COUNTIF(Servier!J50,"NC Majeure")+COUNTIF(MEN!J50,"NC Majeure")+COUNTIF(ADM!J50,"NC Majeure")+COUNTIF('CDG DC'!J50,"NC Majeure")+COUNTIF('CDG ITOC'!J50,"NC Majeure")+COUNTIF(BPOST!J50,"NC Majeure")+COUNTIF('Graphtalk AIA'!J50,"NC Majeure")+COUNTIF('ONCF APPS'!J50,"NC Majeure")+COUNTIF('ONCF MW'!J50,"NC Majeure")+COUNTIF(ANEF!J50,"NC Majeure")+COUNTIF(Carrefour!J50,"NC Majeure")+COUNTIF('Vinci Construction'!J50,"NC Majeure")+COUNTIF(AXA!J50,"NC Majeure")+COUNTIF(OCP!J50,"NC Majeure") -> 0 | E41: =COUNTIF('CDG Sécurité'!K50,"NC Mineure")+COUNTIF(RAM!J50,"NC Mineure")+COUNTIF('Min. Intérieur'!J50,"NC Mineure")+COUNTIF('CDG Capital'!J50,"NC Mineure")+COUNTIF(AtlanticRe!J50,"NC Mineure")+COUNTIF('Client A'!J50,"NC Mineure")+COUNTIF(Servier!J50,"NC Mineure")+COUNTIF(MEN!J50,"NC Mineure")+COUNTIF(ADM!J50,"NC Mineure")+COUNTIF('CDG DC'!J50,"NC Mineure")+COUNTIF('CDG ITOC'!J50,"NC Mineure")+COUNTIF(BPOST!J50,"NC Mineure")+COUNTIF('Graphtalk AIA'!J50,"NC Mineure")+COUNTIF('ONCF APPS'!J50,"NC Mineure")+COUNTIF('ONCF MW'!J50,"NC Mineure")+COUNTIF(ANEF!J50,"NC Mineure")+COUNTIF(Carrefour!J50,"NC Mineure")+COUNTIF('Vinci Construction'!J50,"NC Mineure")+COUNTIF(AXA!J50,"NC Mineure")+COUNTIF(OCP!J50,"NC Mineure") -> 0 | F41: =COUNTIF('CDG Sécurité'!K50,"Observation")+COUNTIF(RAM!J50,"Observation")+COUNTIF('Min. Intérieur'!J50,"Observation")+COUNTIF('CDG Capital'!J50,"Observation")+COUNTIF(AtlanticRe!J50,"Observation")+COUNTIF('Client A'!J50,"Observation")+COUNTIF(Servier!J50,"Observation")+COUNTIF(MEN!J50,"Observation")+COUNTIF(ADM!J50,"Observation")+COUNTIF('CDG DC'!J50,"Observation")+COUNTIF('CDG ITOC'!J50,"Observation")+COUNTIF(BPOST!J50,"Observation")+COUNTIF('Graphtalk AIA'!J50,"Observation")+COUNTIF('ONCF APPS'!J50,"Observation")+COUNTIF('ONCF MW'!J50,"Observation")+COUNTIF(ANEF!J50,"Observation")+COUNTIF(Carrefour!J50,"Observation")+COUNTIF('Vinci Construction'!J50,"Observation")+COUNTIF(AXA!J50,"Observation")+COUNTIF(OCP!J50,"Observation") -> 0 | G41: =COUNTIF('CDG Sécurité'!K50,"OFI")+COUNTIF(RAM!J50,"OFI")+COUNTIF('Min. Intérieur'!J50,"OFI")+COUNTIF('CDG Capital'!J50,"OFI")+COUNTIF(AtlanticRe!J50,"OFI")+COUNTIF('Client A'!J50,"OFI")+COUNTIF(Servier!J50,"OFI")+COUNTIF(MEN!J50,"OFI")+COUNTIF(ADM!J50,"OFI")+COUNTIF('CDG DC'!J50,"OFI")+COUNTIF('CDG ITOC'!J50,"OFI")+COUNTIF(BPOST!J50,"OFI")+COUNTIF('Graphtalk AIA'!J50,"OFI")+COUNTIF('ONCF APPS'!J50,"OFI")+COUNTIF('ONCF MW'!J50,"OFI")+COUNTIF(ANEF!J50,"OFI")+COUNTIF(Carrefour!J50,"OFI")+COUNTIF('Vinci Construction'!J50,"OFI")+COUNTIF(AXA!J50,"OFI")+COUNTIF(OCP!J50,"OFI") -> 0 | H41: =D41+E41+F41+G41 -> 0 | I41: =IFERROR(H41/H43,0) -> 0 | J41: =IF(D41>0,"🔴 Critique",IF(H41>5,"🟠 Fort",IF(H41>2,"🟡 Modéré",IF(H41>0,"🔵 Faible","✅ Aucun")))) -> ✅ Aucun
A42: 37 | B42: 10.2 | C42: Actions correctives | D42: =COUNTIF('CDG Sécurité'!K51,"NC Majeure")+COUNTIF(RAM!J51,"NC Majeure")+COUNTIF('Min. Intérieur'!J51,"NC Majeure")+COUNTIF('CDG Capital'!J51,"NC Majeure")+COUNTIF(AtlanticRe!J51,"NC Majeure")+COUNTIF('Client A'!J51,"NC Majeure")+COUNTIF(Servier!J51,"NC Majeure")+COUNTIF(MEN!J51,"NC Majeure")+COUNTIF(ADM!J51,"NC Majeure")+COUNTIF('CDG DC'!J51,"NC Majeure")+COUNTIF('CDG ITOC'!J51,"NC Majeure")+COUNTIF(BPOST!J51,"NC Majeure")+COUNTIF('Graphtalk AIA'!J51,"NC Majeure")+COUNTIF('ONCF APPS'!J51,"NC Majeure")+COUNTIF('ONCF MW'!J51,"NC Majeure")+COUNTIF(ANEF!J51,"NC Majeure")+COUNTIF(Carrefour!J51,"NC Majeure")+COUNTIF('Vinci Construction'!J51,"NC Majeure")+COUNTIF(AXA!J51,"NC Majeure")+COUNTIF(OCP!J51,"NC Majeure") -> 0 | E42: =COUNTIF('CDG Sécurité'!K51,"NC Mineure")+COUNTIF(RAM!J51,"NC Mineure")+COUNTIF('Min. Intérieur'!J51,"NC Mineure")+COUNTIF('CDG Capital'!J51,"NC Mineure")+COUNTIF(AtlanticRe!J51,"NC Mineure")+COUNTIF('Client A'!J51,"NC Mineure")+COUNTIF(Servier!J51,"NC Mineure")+COUNTIF(MEN!J51,"NC Mineure")+COUNTIF(ADM!J51,"NC Mineure")+COUNTIF('CDG DC'!J51,"NC Mineure")+COUNTIF('CDG ITOC'!J51,"NC Mineure")+COUNTIF(BPOST!J51,"NC Mineure")+COUNTIF('Graphtalk AIA'!J51,"NC Mineure")+COUNTIF('ONCF APPS'!J51,"NC Mineure")+COUNTIF('ONCF MW'!J51,"NC Mineure")+COUNTIF(ANEF!J51,"NC Mineure")+COUNTIF(Carrefour!J51,"NC Mineure")+COUNTIF('Vinci Construction'!J51,"NC Mineure")+COUNTIF(AXA!J51,"NC Mineure")+COUNTIF(OCP!J51,"NC Mineure") -> 0 | F42: =COUNTIF('CDG Sécurité'!K51,"Observation")+COUNTIF(RAM!J51,"Observation")+COUNTIF('Min. Intérieur'!J51,"Observation")+COUNTIF('CDG Capital'!J51,"Observation")+COUNTIF(AtlanticRe!J51,"Observation")+COUNTIF('Client A'!J51,"Observation")+COUNTIF(Servier!J51,"Observation")+COUNTIF(MEN!J51,"Observation")+COUNTIF(ADM!J51,"Observation")+COUNTIF('CDG DC'!J51,"Observation")+COUNTIF('CDG ITOC'!J51,"Observation")+COUNTIF(BPOST!J51,"Observation")+COUNTIF('Graphtalk AIA'!J51,"Observation")+COUNTIF('ONCF APPS'!J51,"Observation")+COUNTIF('ONCF MW'!J51,"Observation")+COUNTIF(ANEF!J51,"Observation")+COUNTIF(Carrefour!J51,"Observation")+COUNTIF('Vinci Construction'!J51,"Observation")+COUNTIF(AXA!J51,"Observation")+COUNTIF(OCP!J51,"Observation") -> 0 | G42: =COUNTIF('CDG Sécurité'!K51,"OFI")+COUNTIF(RAM!J51,"OFI")+COUNTIF('Min. Intérieur'!J51,"OFI")+COUNTIF('CDG Capital'!J51,"OFI")+COUNTIF(AtlanticRe!J51,"OFI")+COUNTIF('Client A'!J51,"OFI")+COUNTIF(Servier!J51,"OFI")+COUNTIF(MEN!J51,"OFI")+COUNTIF(ADM!J51,"OFI")+COUNTIF('CDG DC'!J51,"OFI")+COUNTIF('CDG ITOC'!J51,"OFI")+COUNTIF(BPOST!J51,"OFI")+COUNTIF('Graphtalk AIA'!J51,"OFI")+COUNTIF('ONCF APPS'!J51,"OFI")+COUNTIF('ONCF MW'!J51,"OFI")+COUNTIF(ANEF!J51,"OFI")+COUNTIF(Carrefour!J51,"OFI")+COUNTIF('Vinci Construction'!J51,"OFI")+COUNTIF(AXA!J51,"OFI")+COUNTIF(OCP!J51,"OFI") -> 0 | H42: =D42+E42+F42+G42 -> 0 | I42: =IFERROR(H42/H43,0) -> 0 | J42: =IF(D42>0,"🔴 Critique",IF(H42>5,"🟠 Fort",IF(H42>2,"🟡 Modéré",IF(H42>0,"🔵 Faible","✅ Aucun")))) -> ✅ Aucun
C43: TOTAL | D43: =SUM(D6:D42) -> 1 | E43: =SUM(E6:E42) -> 44 | F43: =SUM(F6:F42) -> 6 | G43: =SUM(G6:G42) -> 0 | H43: =SUM(H6:H42) -> 51
A46: 2. MATRICE FINDINGS PAR LIBELLÉ TERRAIN × COMPTE
A48: N° | B48: Clause | C48: Libellé Terrain | D48: CDG Sécu | E48: RAM | F48: Min. Int | G48: CDG Capi | H48: Atlantic | I48: Client A | J48: Servier | K48: MEN | L48: ADM | M48: CDG DC | N48: CDG ITOC | O48: BPOST | P48: Graphtal | Q48: ONCF APP | R48: OCP MW | S48: ANEF | T48: Carrefou | U48: Vinci Co | V48: AXA | W48: OCP | X48: TOTAL
A49: 1 | B49: 4.1 | C49: Connaissance de notre environnement | D49: =IF('CDG Sécurité'!K15<>"",1,0) -> 1 | E49: =IF(RAM!J15<>"",1,0) -> 1 | F49: =IF('Min. Intérieur'!J15<>"",1,0) -> 1 | G49: =IF('CDG Capital'!J15<>"",1,0) -> 1 | H49: =IF(AtlanticRe!J15<>"",1,0) -> 1 | I49: =IF('Client A'!J15<>"",1,0) -> 0 | J49: =IF(Servier!J15<>"",1,0) -> 1 | K49: =IF(MEN!J15<>"",1,0) -> 1 | L49: =IF(ADM!J15<>"",1,0) -> 0 | M49: =IF('CDG DC'!J15<>"",1,0) -> 0 | N49: =IF('CDG ITOC'!J15<>"",1,0) -> 0 | O49: =IF(BPOST!J15<>"",1,0) -> 0 | P49: =IF('Graphtalk AIA'!J15<>"",1,0) -> 0 | Q49: =IF('ONCF APPS'!J15<>"",1,0) -> 0 | R49: =IF('ONCF MW'!J15<>"",1,0) -> 1 | S49: =IF(ANEF!J15<>"",1,0) -> 0 | T49: =IF(Carrefour!J15<>"",1,0) -> 0 | U49: =IF('Vinci Construction'!J15<>"",1,0) -> 0 | V49: =IF(AXA!J15<>"",1,0) -> 0 | W49: =IF(OCP!J15<>"",1,0) -> 1 | X49: =SUM(D49:W49) -> 9
A50: 2 | B50: 4.2 | C50: Écoute des parties prenantes | D50: =IF('CDG Sécurité'!K16<>"",1,0) -> 0 | E50: =IF(RAM!J16<>"",1,0) -> 0 | F50: =IF('Min. Intérieur'!J16<>"",1,0) -> 0 | G50: =IF('CDG Capital'!J18<>"",1,0) -> 1 | H50: =IF(AtlanticRe!J16<>"",1,0) -> 0 | I50: =IF('Client A'!J16<>"",1,0) -> 0 | J50: =IF(Servier!J16<>"",1,0) -> 1 | K50: =IF(MEN!J16<>"",1,0) -> 0 | L50: =IF(ADM!J16<>"",1,0) -> 0 | M50: =IF('CDG DC'!J16<>"",1,0) -> 0 | N50: =IF('CDG ITOC'!J16<>"",1,0) -> 0 | O50: =IF(BPOST!J16<>"",1,0) -> 0 | P50: =IF('Graphtalk AIA'!J16<>"",1,0) -> 0 | Q50: =IF('ONCF APPS'!J16<>"",1,0) -> 0 | R50: =IF('ONCF MW'!J16<>"",1,0) -> 0 | S50: =IF(ANEF!J16<>"",1,0) -> 0 | T50: =IF(Carrefour!J16<>"",1,0) -> 0 | U50: =IF('Vinci Construction'!J16<>"",1,0) -> 0 | V50: =IF(AXA!J16<>"",1,0) -> 0 | W50: =IF(OCP!J16<>"",1,0) -> 0 | X50: =SUM(D50:W50) -> 2
A51: 3 | B51: 4.3 | C51: Périmètre de notre système qualité | D51: =IF('CDG Sécurité'!K17<>"",1,0) -> 0 | E51: =IF(RAM!J17<>"",1,0) -> 0 | F51: =IF('Min. Intérieur'!J17<>"",1,0) -> 0 | G51: =IF('CDG Capital'!J20<>"",1,0) -> 0 | H51: =IF(AtlanticRe!J17<>"",1,0) -> 0 | I51: =IF('Client A'!J17<>"",1,0) -> 0 | J51: =IF(Servier!J17<>"",1,0) -> 1 | K51: =IF(MEN!J17<>"",1,0) -> 0 | L51: =IF(ADM!J17<>"",1,0) -> 0 | M51: =IF('CDG DC'!J17<>"",1,0) -> 0 | N51: =IF('CDG ITOC'!J17<>"",1,0) -> 0 | O51: =IF(BPOST!J17<>"",1,0) -> 0 | P51: =IF('Graphtalk AIA'!J17<>"",1,0) -> 0 | Q51: =IF('ONCF APPS'!J17<>"",1,0) -> 0 | R51: =IF('ONCF MW'!J17<>"",1,0) -> 0 | S51: =IF(ANEF!J17<>"",1,0) -> 0 | T51: =IF(Carrefour!J17<>"",1,0) -> 0 | U51: =IF('Vinci Construction'!J17<>"",1,0) -> 0 | V51: =IF(AXA!J17<>"",1,0) -> 0 | W51: =IF(OCP!J17<>"",1,0) -> 0 | X51: =SUM(D51:W51) -> 1
A52: 4 | B52: 4.4 | C52: Cartographie de nos processus | D52: =IF('CDG Sécurité'!K18<>"",1,0) -> 1 | E52: =IF(RAM!J18<>"",1,0) -> 1 | F52: =IF('Min. Intérieur'!J18<>"",1,0) -> 0 | G52: =IF('CDG Capital'!J21<>"",1,0) -> 0 | H52: =IF(AtlanticRe!J18<>"",1,0) -> 1 | I52: =IF('Client A'!J18<>"",1,0) -> 0 | J52: =IF(Servier!J18<>"",1,0) -> 1 | K52: =IF(MEN!J18<>"",1,0) -> 1 | L52: =IF(ADM!J18<>"",1,0) -> 0 | M52: =IF('CDG DC'!J18<>"",1,0) -> 0 | N52: =IF('CDG ITOC'!J18<>"",1,0) -> 0 | O52: =IF(BPOST!J18<>"",1,0) -> 0 | P52: =IF('Graphtalk AIA'!J18<>"",1,0) -> 0 | Q52: =IF('ONCF APPS'!J18<>"",1,0) -> 0 | R52: =IF('ONCF MW'!J18<>"",1,0) -> 1 | S52: =IF(ANEF!J18<>"",1,0) -> 0 | T52: =IF(Carrefour!J18<>"",1,0) -> 0 | U52: =IF('Vinci Construction'!J18<>"",1,0) -> 0 | V52: =IF(AXA!J18<>"",1,0) -> 0 | W52: =IF(OCP!J18<>"",1,0) -> 1 | X52: =SUM(D52:W52) -> 7
A53: 5 | B53: 5.1 | C53: Engagement de la direction | D53: =IF('CDG Sécurité'!K19<>"",1,0) -> 0 | E53: =IF(RAM!J19<>"",1,0) -> 0 | F53: =IF('Min. Intérieur'!J19<>"",1,0) -> 0 | G53: =IF('CDG Capital'!J22<>"",1,0) -> 1 | H53: =IF(AtlanticRe!J19<>"",1,0) -> 0 | I53: =IF('Client A'!J19<>"",1,0) -> 0 | J53: =IF(Servier!J19<>"",1,0) -> 1 | K53: =IF(MEN!J19<>"",1,0) -> 0 | L53: =IF(ADM!J19<>"",1,0) -> 0 | M53: =IF('CDG DC'!J19<>"",1,0) -> 0 | N53: =IF('CDG ITOC'!J19<>"",1,0) -> 0 | O53: =IF(BPOST!J19<>"",1,0) -> 0 | P53: =IF('Graphtalk AIA'!J19<>"",1,0) -> 0 | Q53: =IF('ONCF APPS'!J19<>"",1,0) -> 0 | R53: =IF('ONCF MW'!J19<>"",1,0) -> 0 | S53: =IF(ANEF!J19<>"",1,0) -> 0 | T53: =IF(Carrefour!J19<>"",1,0) -> 0 | U53: =IF('Vinci Construction'!J19<>"",1,0) -> 0 | V53: =IF(AXA!J19<>"",1,0) -> 0 | W53: =IF(OCP!J19<>"",1,0) -> 0 | X53: =SUM(D53:W53) -> 2
A54: 6 | B54: 5.2 | C54: Notre politique qualité | D54: =IF('CDG Sécurité'!K20<>"",1,0) -> 0 | E54: =IF(RAM!J20<>"",1,0) -> 1 | F54: =IF('Min. Intérieur'!J20<>"",1,0) -> 0 | G54: =IF('CDG Capital'!J23<>"",1,0) -> 0 | H54: =IF(AtlanticRe!J20<>"",1,0) -> 1 | I54: =IF('Client A'!J20<>"",1,0) -> 0 | J54: =IF(Servier!J20<>"",1,0) -> 1 | K54: =IF(MEN!J20<>"",1,0) -> 1 | L54: =IF(ADM!J20<>"",1,0) -> 0 | M54: =IF('CDG DC'!J20<>"",1,0) -> 0 | N54: =IF('CDG ITOC'!J20<>"",1,0) -> 0 | O54: =IF(BPOST!J20<>"",1,0) -> 0 | P54: =IF('Graphtalk AIA'!J20<>"",1,0) -> 0 | Q54: =IF('ONCF APPS'!J20<>"",1,0) -> 0 | R54: =IF('ONCF MW'!J20<>"",1,0) -> 1 | S54: =IF(ANEF!J20<>"",1,0) -> 0 | T54: =IF(Carrefour!J20<>"",1,0) -> 0 | U54: =IF('Vinci Construction'!J20<>"",1,0) -> 0 | V54: =IF(AXA!J20<>"",1,0) -> 0 | W54: =IF(OCP!J20<>"",1,0) -> 1 | X54: =SUM(D54:W54) -> 6
A55: 7 | B55: 5.3 | C55: Qui fait quoi ? | D55: =IF('CDG Sécurité'!K21<>"",1,0) -> 0 | E55: =IF(RAM!J21<>"",1,0) -> 1 | F55: =IF('Min. Intérieur'!J21<>"",1,0) -> 0 | G55: =IF('CDG Capital'!J24<>"",1,0) -> 1 | H55: =IF(AtlanticRe!J21<>"",1,0) -> 1 | I55: =IF('Client A'!J21<>"",1,0) -> 0 | J55: =IF(Servier!J21<>"",1,0) -> 1 | K55: =IF(MEN!J21<>"",1,0) -> 1 | L55: =IF(ADM!J21<>"",1,0) -> 0 | M55: =IF('CDG DC'!J21<>"",1,0) -> 0 | N55: =IF('CDG ITOC'!J21<>"",1,0) -> 0 | O55: =IF(BPOST!J21<>"",1,0) -> 0 | P55: =IF('Graphtalk AIA'!J21<>"",1,0) -> 0 | Q55: =IF('ONCF APPS'!J21<>"",1,0) -> 0 | R55: =IF('ONCF MW'!J21<>"",1,0) -> 1 | S55: =IF(ANEF!J21<>"",1,0) -> 0 | T55: =IF(Carrefour!J21<>"",1,0) -> 0 | U55: =IF('Vinci Construction'!J21<>"",1,0) -> 0 | V55: =IF(AXA!J21<>"",1,0) -> 0 | W55: =IF(OCP!J21<>"",1,0) -> 1 | X55: =SUM(D55:W55) -> 7
A56: 8 | B56: 6.1 | C56: Gestion des risques et opportunités | D56: =IF('CDG Sécurité'!K22<>"",1,0) -> 1 | E56: =IF(RAM!J22<>"",1,0) -> 1 | F56: =IF('Min. Intérieur'!J22<>"",1,0) -> 1 | G56: =IF('CDG Capital'!J25<>"",1,0) -> 0 | H56: =IF(AtlanticRe!J22<>"",1,0) -> 1 | I56: =IF('Client A'!J22<>"",1,0) -> 0 | J56: =IF(Servier!J22<>"",1,0) -> 1 | K56: =IF(MEN!J22<>"",1,0) -> 1 | L56: =IF(ADM!J22<>"",1,0) -> 0 | M56: =IF('CDG DC'!J22<>"",1,0) -> 0 | N56: =IF('CDG ITOC'!J22<>"",1,0) -> 0 | O56: =IF(BPOST!J22<>"",1,0) -> 0 | P56: =IF('Graphtalk AIA'!J22<>"",1,0) -> 0 | Q56: =IF('ONCF APPS'!J22<>"",1,0) -> 0 | R56: =IF('ONCF MW'!J22<>"",1,0) -> 1 | S56: =IF(ANEF!J22<>"",1,0) -> 0 | T56: =IF(Carrefour!J22<>"",1,0) -> 0 | U56: =IF('Vinci Construction'!J22<>"",1,0) -> 0 | V56: =IF(AXA!J22<>"",1,0) -> 0 | W56: =IF(OCP!J22<>"",1,0) -> 1 | X56: =SUM(D56:W56) -> 8
A57: 9 | B57: 6.2 | C57: Planification des objectifs | D57: =IF('CDG Sécurité'!K23<>"",1,0) -> 0 | E57: =IF(RAM!J23<>"",1,0) -> 1 | F57: =IF('Min. Intérieur'!J23<>"",1,0) -> 1 | G57: =IF('CDG Capital'!J29<>"",1,0) -> 1 | H57: =IF(AtlanticRe!J23<>"",1,0) -> 1 | I57: =IF('Client A'!J23<>"",1,0) -> 0 | J57: =IF(Servier!J23<>"",1,0) -> 1 | K57: =IF(MEN!J23<>"",1,0) -> 1 | L57: =IF(ADM!J23<>"",1,0) -> 0 | M57: =IF('CDG DC'!J23<>"",1,0) -> 0 | N57: =IF('CDG ITOC'!J23<>"",1,0) -> 0 | O57: =IF(BPOST!J23<>"",1,0) -> 0 | P57: =IF('Graphtalk AIA'!J23<>"",1,0) -> 0 | Q57: =IF('ONCF APPS'!J23<>"",1,0) -> 0 | R57: =IF('ONCF MW'!J23<>"",1,0) -> 1 | S57: =IF(ANEF!J23<>"",1,0) -> 0 | T57: =IF(Carrefour!J23<>"",1,0) -> 0 | U57: =IF('Vinci Construction'!J23<>"",1,0) -> 0 | V57: =IF(AXA!J23<>"",1,0) -> 0 | W57: =IF(OCP!J23<>"",1,0) -> 1 | X57: =SUM(D57:W57) -> 8
A58: 10 | B58: 6.3 | C58: Gestion des changements | D58: =IF('CDG Sécurité'!K24<>"",1,0) -> 1 | E58: =IF(RAM!J24<>"",1,0) -> 1 | F58: =IF('Min. Intérieur'!J24<>"",1,0) -> 1 | G58: =IF('CDG Capital'!J30<>"",1,0) -> 0 | H58: =IF(AtlanticRe!J24<>"",1,0) -> 1 | I58: =IF('Client A'!J24<>"",1,0) -> 0 | J58: =IF(Servier!J24<>"",1,0) -> 1 | K58: =IF(MEN!J24<>"",1,0) -> 1 | L58: =IF(ADM!J24<>"",1,0) -> 0 | M58: =IF('CDG DC'!J24<>"",1,0) -> 0 | N58: =IF('CDG ITOC'!J24<>"",1,0) -> 0 | O58: =IF(BPOST!J24<>"",1,0) -> 0 | P58: =IF('Graphtalk AIA'!J24<>"",1,0) -> 0 | Q58: =IF('ONCF APPS'!J24<>"",1,0) -> 0 | R58: =IF('ONCF MW'!J24<>"",1,0) -> 1 | S58: =IF(ANEF!J24<>"",1,0) -> 0 | T58: =IF(Carrefour!J24<>"",1,0) -> 0 | U58: =IF('Vinci Construction'!J24<>"",1,0) -> 0 | V58: =IF(AXA!J24<>"",1,0) -> 0 | W58: =IF(OCP!J24<>"",1,0) -> 1 | X58: =SUM(D58:W58) -> 8
A59: 11 | B59: 7.1.1 | C59: Disponibilité des ressources humaines | D59: =IF('CDG Sécurité'!K25<>"",1,0) -> 0 | E59: =IF(RAM!J25<>"",1,0) -> 0 | F59: =IF('Min. Intérieur'!J25<>"",1,0) -> 0 | G59: =IF('CDG Capital'!J31<>"",1,0) -> 1 | H59: =IF(AtlanticRe!J25<>"",1,0) -> 0 | I59: =IF('Client A'!J25<>"",1,0) -> 0 | J59: =IF(Servier!J25<>"",1,0) -> 1 | K59: =IF(MEN!J25<>"",1,0) -> 0 | L59: =IF(ADM!J25<>"",1,0) -> 0 | M59: =IF('CDG DC'!J25<>"",1,0) -> 0 | N59: =IF('CDG ITOC'!J25<>"",1,0) -> 0 | O59: =IF(BPOST!J25<>"",1,0) -> 0 | P59: =IF('Graphtalk AIA'!J25<>"",1,0) -> 0 | Q59: =IF('ONCF APPS'!J25<>"",1,0) -> 0 | R59: =IF('ONCF MW'!J25<>"",1,0) -> 0 | S59: =IF(ANEF!J25<>"",1,0) -> 0 | T59: =IF(Carrefour!J25<>"",1,0) -> 0 | U59: =IF('Vinci Construction'!J25<>"",1,0) -> 0 | V59: =IF(AXA!J25<>"",1,0) -> 0 | W59: =IF(OCP!J25<>"",1,0) -> 0 | X59: =SUM(D59:W59) -> 2
A60: 12 | B60: 7.1.2 | C60: Disponibilité des infrastructures | D60: =IF('CDG Sécurité'!K26<>"",1,0) -> 0 | E60: =IF(RAM!J26<>"",1,0) -> 0 | F60: =IF('Min. Intérieur'!J26<>"",1,0) -> 0 | G60: =IF('CDG Capital'!J32<>"",1,0) -> 1 | H60: =IF(AtlanticRe!J26<>"",1,0) -> 0 | I60: =IF('Client A'!J26<>"",1,0) -> 0 | J60: =IF(Servier!J26<>"",1,0) -> 1 | K60: =IF(MEN!J26<>"",1,0) -> 0 | L60: =IF(ADM!J26<>"",1,0) -> 0 | M60: =IF('CDG DC'!J26<>"",1,0) -> 0 | N60: =IF('CDG ITOC'!J26<>"",1,0) -> 0 | O60: =IF(BPOST!J26<>"",1,0) -> 0 | P60: =IF('Graphtalk AIA'!J26<>"",1,0) -> 0 | Q60: =IF('ONCF APPS'!J26<>"",1,0) -> 0 | R60: =IF('ONCF MW'!J26<>"",1,0) -> 0 | S60: =IF(ANEF!J26<>"",1,0) -> 0 | T60: =IF(Carrefour!J26<>"",1,0) -> 0 | U60: =IF('Vinci Construction'!J26<>"",1,0) -> 0 | V60: =IF(AXA!J26<>"",1,0) -> 0 | W60: =IF(OCP!J26<>"",1,0) -> 0 | X60: =SUM(D60:W60) -> 2
A61: 13 | B61: 7.1.5 | C61: Outils de mesure et de contrôle | D61: =IF('CDG Sécurité'!K27<>"",1,0) -> 0 | E61: =IF(RAM!J27<>"",1,0) -> 0 | F61: =IF('Min. Intérieur'!J27<>"",1,0) -> 0 | G61: =IF('CDG Capital'!#REF!<>"",1,0) -> #REF! | H61: =IF(AtlanticRe!J27<>"",1,0) -> 0 | I61: =IF('Client A'!J27<>"",1,0) -> 0 | J61: =IF(Servier!J27<>"",1,0) -> 1 | K61: =IF(MEN!J27<>"",1,0) -> 0 | L61: =IF(ADM!J27<>"",1,0) -> 0 | M61: =IF('CDG DC'!J27<>"",1,0) -> 0 | N61: =IF('CDG ITOC'!J27<>"",1,0) -> 0 | O61: =IF(BPOST!J27<>"",1,0) -> 0 | P61: =IF('Graphtalk AIA'!J27<>"",1,0) -> 0 | Q61: =IF('ONCF APPS'!J27<>"",1,0) -> 0 | R61: =IF('ONCF MW'!J27<>"",1,0) -> 0 | S61: =IF(ANEF!J27<>"",1,0) -> 0 | T61: =IF(Carrefour!J27<>"",1,0) -> 0 | U61: =IF('Vinci Construction'!J27<>"",1,0) -> 0 | V61: =IF(AXA!J27<>"",1,0) -> 0 | W61: =IF(OCP!J27<>"",1,0) -> 0 | X61: =SUM(D61:W61) -> #REF!
A62: 14 | B62: 7.1.6 | C62: Gestion des connaissances | D62: =IF('CDG Sécurité'!K28<>"",1,0) -> 0 | E62: =IF(RAM!J28<>"",1,0) -> 0 | F62: =IF('Min. Intérieur'!J28<>"",1,0) -> 0 | G62: =IF('CDG Capital'!#REF!<>"",1,0) -> #REF! | H62: =IF(AtlanticRe!J28<>"",1,0) -> 0 | I62: =IF('Client A'!J28<>"",1,0) -> 0 | J62: =IF(Servier!J28<>"",1,0) -> 1 | K62: =IF(MEN!J28<>"",1,0) -> 0 | L62: =IF(ADM!J28<>"",1,0) -> 0 | M62: =IF('CDG DC'!J28<>"",1,0) -> 0 | N62: =IF('CDG ITOC'!J28<>"",1,0) -> 0 | O62: =IF(BPOST!J28<>"",1,0) -> 0 | P62: =IF('Graphtalk AIA'!J28<>"",1,0) -> 0 | Q62: =IF('ONCF APPS'!J28<>"",1,0) -> 0 | R62: =IF('ONCF MW'!J28<>"",1,0) -> 0 | S62: =IF(ANEF!J28<>"",1,0) -> 0 | T62: =IF(Carrefour!J28<>"",1,0) -> 0 | U62: =IF('Vinci Construction'!J28<>"",1,0) -> 0 | V62: =IF(AXA!J28<>"",1,0) -> 0 | W62: =IF(OCP!J28<>"",1,0) -> 0 | X62: =SUM(D62:W62) -> #REF!
A63: 15 | B63: 7.2 | C63: Compétences de l'équipe | D63: =IF('CDG Sécurité'!K29<>"",1,0) -> 1 | E63: =IF(RAM!J29<>"",1,0) -> 1 | F63: =IF('Min. Intérieur'!J29<>"",1,0) -> 1 | G63: =IF('CDG Capital'!#REF!<>"",1,0) -> #REF! | H63: =IF(AtlanticRe!J29<>"",1,0) -> 1 | I63: =IF('Client A'!J29<>"",1,0) -> 0 | J63: =IF(Servier!J29<>"",1,0) -> 1 | K63: =IF(MEN!J29<>"",1,0) -> 1 | L63: =IF(ADM!J29<>"",1,0) -> 0 | M63: =IF('CDG DC'!J29<>"",1,0) -> 0 | N63: =IF('CDG ITOC'!J29<>"",1,0) -> 0 | O63: =IF(BPOST!J29<>"",1,0) -> 0 | P63: =IF('Graphtalk AIA'!J29<>"",1,0) -> 0 | Q63: =IF('ONCF APPS'!J29<>"",1,0) -> 0 | R63: =IF('ONCF MW'!J29<>"",1,0) -> 1 | S63: =IF(ANEF!J29<>"",1,0) -> 0 | T63: =IF(Carrefour!J29<>"",1,0) -> 0 | U63: =IF('Vinci Construction'!J29<>"",1,0) -> 0 | V63: =IF(AXA!J29<>"",1,0) -> 0 | W63: =IF(OCP!J29<>"",1,0) -> 1 | X63: =SUM(D63:W63) -> #REF!
A64: 16 | B64: 7.3 | C64: Sensibilisation qualité | D64: =IF('CDG Sécurité'!K30<>"",1,0) -> 0 | E64: =IF(RAM!J30<>"",1,0) -> 1 | F64: =IF('Min. Intérieur'!J30<>"",1,0) -> 0 | G64: =IF('CDG Capital'!#REF!<>"",1,0) -> #REF! | H64: =IF(AtlanticRe!J30<>"",1,0) -> 1 | I64: =IF('Client A'!J30<>"",1,0) -> 0 | J64: =IF(Servier!J30<>"",1,0) -> 1 | K64: =IF(MEN!J30<>"",1,0) -> 1 | L64: =IF(ADM!J30<>"",1,0) -> 0 | M64: =IF('CDG DC'!J30<>"",1,0) -> 0 | N64: =IF('CDG ITOC'!J30<>"",1,0) -> 0 | O64: =IF(BPOST!J30<>"",1,0) -> 0 | P64: =IF('Graphtalk AIA'!J30<>"",1,0) -> 0 | Q64: =IF('ONCF APPS'!J30<>"",1,0) -> 0 | R64: =IF('ONCF MW'!J30<>"",1,0) -> 1 | S64: =IF(ANEF!J30<>"",1,0) -> 0 | T64: =IF(Carrefour!J30<>"",1,0) -> 0 | U64: =IF('Vinci Construction'!J30<>"",1,0) -> 0 | V64: =IF(AXA!J30<>"",1,0) -> 0 | W64: =IF(OCP!J30<>"",1,0) -> 1 | X64: =SUM(D64:W64) -> #REF!
A65: 17 | B65: 7.4 | C65: Plan de communication | D65: =IF('CDG Sécurité'!K31<>"",1,0) -> 1 | E65: =IF(RAM!J31<>"",1,0) -> 1 | F65: =IF('Min. Intérieur'!J31<>"",1,0) -> 1 | G65: =IF('CDG Capital'!#REF!<>"",1,0) -> #REF! | H65: =IF(AtlanticRe!J31<>"",1,0) -> 1 | I65: =IF('Client A'!J31<>"",1,0) -> 0 | J65: =IF(Servier!J31<>"",1,0) -> 1 | K65: =IF(MEN!J31<>"",1,0) -> 1 | L65: =IF(ADM!J31<>"",1,0) -> 0 | M65: =IF('CDG DC'!J31<>"",1,0) -> 0 | N65: =IF('CDG ITOC'!J31<>"",1,0) -> 0 | O65: =IF(BPOST!J31<>"",1,0) -> 0 | P65: =IF('Graphtalk AIA'!J31<>"",1,0) -> 0 | Q65: =IF('ONCF APPS'!J31<>"",1,0) -> 0 | R65: =IF('ONCF MW'!J31<>"",1,0) -> 1 | S65: =IF(ANEF!J31<>"",1,0) -> 0 | T65: =IF(Carrefour!J31<>"",1,0) -> 0 | U65: =IF('Vinci Construction'!J31<>"",1,0) -> 0 | V65: =IF(AXA!J31<>"",1,0) -> 0 | W65: =IF(OCP!J31<>"",1,0) -> 1 | X65: =SUM(D65:W65) -> #REF!
A66: 18 | B66: 7.5 | C66: Gestion documentaire | D66: =IF('CDG Sécurité'!K32<>"",1,0) -> 1 | E66: =IF(RAM!J32<>"",1,0) -> 1 | F66: =IF('Min. Intérieur'!J32<>"",1,0) -> 1 | G66: =IF('CDG Capital'!#REF!<>"",1,0) -> #REF! | H66: =IF(AtlanticRe!J32<>"",1,0) -> 1 | I66: =IF('Client A'!J32<>"",1,0) -> 0 | J66: =IF(Servier!J32<>"",1,0) -> 1 | K66: =IF(MEN!J32<>"",1,0) -> 1 | L66: =IF(ADM!J32<>"",1,0) -> 0 | M66: =IF('CDG DC'!J32<>"",1,0) -> 0 | N66: =IF('CDG ITOC'!J32<>"",1,0) -> 0 | O66: =IF(BPOST!J32<>"",1,0) -> 0 | P66: =IF('Graphtalk AIA'!J32<>"",1,0) -> 0 | Q66: =IF('ONCF APPS'!J32<>"",1,0) -> 0 | R66: =IF('ONCF MW'!J32<>"",1,0) -> 1 | S66: =IF(ANEF!J32<>"",1,0) -> 0 | T66: =IF(Carrefour!J32<>"",1,0) -> 0 | U66: =IF('Vinci Construction'!J32<>"",1,0) -> 0 | V66: =IF(AXA!J32<>"",1,0) -> 0 | W66: =IF(OCP!J32<>"",1,0) -> 1 | X66: =SUM(D66:W66) -> #REF!
A67: 19 | B67: 8.1 | C67: Planification des opérations | D67: =IF('CDG Sécurité'!K33<>"",1,0) -> 0 | E67: =IF(RAM!J33<>"",1,0) -> 1 | F67: =IF('Min. Intérieur'!J33<>"",1,0) -> 0 | G67: =IF('CDG Capital'!J33<>"",1,0) -> 0 | H67: =IF(AtlanticRe!J33<>"",1,0) -> 1 | I67: =IF('Client A'!J33<>"",1,0) -> 0 | J67: =IF(Servier!J33<>"",1,0) -> 1 | K67: =IF(MEN!J33<>"",1,0) -> 1 | L67: =IF(ADM!J33<>"",1,0) -> 0 | M67: =IF('CDG DC'!J33<>"",1,0) -> 0 | N67: =IF('CDG ITOC'!J33<>"",1,0) -> 0 | O67: =IF(BPOST!J33<>"",1,0) -> 0 | P67: =IF('Graphtalk AIA'!J33<>"",1,0) -> 0 | Q67: =IF('ONCF APPS'!J33<>"",1,0) -> 0 | R67: =IF('ONCF MW'!J33<>"",1,0) -> 1 | S67: =IF(ANEF!J33<>"",1,0) -> 0 | T67: =IF(Carrefour!J33<>"",1,0) -> 0 | U67: =IF('Vinci Construction'!J33<>"",1,0) -> 0 | V67: =IF(AXA!J33<>"",1,0) -> 0 | W67: =IF(OCP!J33<>"",1,0) -> 1 | X67: =SUM(D67:W67) -> 6
A68: 20 | B68: 8.2.1 | C68: Communication avec le client | D68: =IF('CDG Sécurité'!K34<>"",1,0) -> 0 | E68: =IF(RAM!J34<>"",1,0) -> 1 | F68: =IF('Min. Intérieur'!J34<>"",1,0) -> 0 | G68: =IF('CDG Capital'!J34<>"",1,0) -> 0 | H68: =IF(AtlanticRe!J34<>"",1,0) -> 1 | I68: =IF('Client A'!J34<>"",1,0) -> 0 | J68: =IF(Servier!J34<>"",1,0) -> 1 | K68: =IF(MEN!J34<>"",1,0) -> 1 | L68: =IF(ADM!J34<>"",1,0) -> 0 | M68: =IF('CDG DC'!J34<>"",1,0) -> 0 | N68: =IF('CDG ITOC'!J34<>"",1,0) -> 0 | O68: =IF(BPOST!J34<>"",1,0) -> 0 | P68: =IF('Graphtalk AIA'!J34<>"",1,0) -> 0 | Q68: =IF('ONCF APPS'!J34<>"",1,0) -> 0 | R68: =IF('ONCF MW'!J34<>"",1,0) -> 1 | S68: =IF(ANEF!J34<>"",1,0) -> 0 | T68: =IF(Carrefour!J34<>"",1,0) -> 0 | U68: =IF('Vinci Construction'!J34<>"",1,0) -> 0 | V68: =IF(AXA!J34<>"",1,0) -> 0 | W68: =IF(OCP!J34<>"",1,0) -> 1 | X68: =SUM(D68:W68) -> 6
A69: 21 | B69: 8.2.2 | C69: Recueil des exigences client | D69: =IF('CDG Sécurité'!K35<>"",1,0) -> 0 | E69: =IF(RAM!J35<>"",1,0) -> 1 | F69: =IF('Min. Intérieur'!J35<>"",1,0) -> 0 | G69: =IF('CDG Capital'!J35<>"",1,0) -> 0 | H69: =IF(AtlanticRe!J35<>"",1,0) -> 1 | I69: =IF('Client A'!J35<>"",1,0) -> 0 | J69: =IF(Servier!J35<>"",1,0) -> 1 | K69: =IF(MEN!J35<>"",1,0) -> 1 | L69: =IF(ADM!J35<>"",1,0) -> 0 | M69: =IF('CDG DC'!J35<>"",1,0) -> 0 | N69: =IF('CDG ITOC'!J35<>"",1,0) -> 0 | O69: =IF(BPOST!J35<>"",1,0) -> 0 | P69: =IF('Graphtalk AIA'!J35<>"",1,0) -> 0 | Q69: =IF('ONCF APPS'!J35<>"",1,0) -> 0 | R69: =IF('ONCF MW'!J35<>"",1,0) -> 1 | S69: =IF(ANEF!J35<>"",1,0) -> 0 | T69: =IF(Carrefour!J35<>"",1,0) -> 0 | U69: =IF('Vinci Construction'!J35<>"",1,0) -> 0 | V69: =IF(AXA!J35<>"",1,0) -> 0 | W69: =IF(OCP!J35<>"",1,0) -> 1 | X69: =SUM(D69:W69) -> 6
A70: 22 | B70: 8.2.3 | C70: Revue avant engagement | D70: =IF('CDG Sécurité'!K36<>"",1,0) -> 0 | E70: =IF(RAM!J36<>"",1,0) -> 1 | F70: =IF('Min. Intérieur'!J36<>"",1,0) -> 0 | G70: =IF('CDG Capital'!J36<>"",1,0) -> 0 | H70: =IF(AtlanticRe!J36<>"",1,0) -> 1 | I70: =IF('Client A'!J36<>"",1,0) -> 0 | J70: =IF(Servier!J36<>"",1,0) -> 1 | K70: =IF(MEN!J36<>"",1,0) -> 1 | L70: =IF(ADM!J36<>"",1,0) -> 0 | M70: =IF('CDG DC'!J36<>"",1,0) -> 0 | N70: =IF('CDG ITOC'!J36<>"",1,0) -> 0 | O70: =IF(BPOST!J36<>"",1,0) -> 0 | P70: =IF('Graphtalk AIA'!J36<>"",1,0) -> 0 | Q70: =IF('ONCF APPS'!J36<>"",1,0) -> 0 | R70: =IF('ONCF MW'!J36<>"",1,0) -> 1 | S70: =IF(ANEF!J36<>"",1,0) -> 0 | T70: =IF(Carrefour!J36<>"",1,0) -> 0 | U70: =IF('Vinci Construction'!J36<>"",1,0) -> 0 | V70: =IF(AXA!J36<>"",1,0) -> 0 | W70: =IF(OCP!J36<>"",1,0) -> 1 | X70: =SUM(D70:W70) -> 6
A71: 23 | B71: 8.2.4 | C71: Gestion des modifications contractuelles | D71: =IF('CDG Sécurité'!K37<>"",1,0) -> 0 | E71: =IF(RAM!J37<>"",1,0) -> 1 | F71: =IF('Min. Intérieur'!J37<>"",1,0) -> 0 | G71: =IF('CDG Capital'!J37<>"",1,0) -> 0 | H71: =IF(AtlanticRe!J37<>"",1,0) -> 1 | I71: =IF('Client A'!J37<>"",1,0) -> 0 | J71: =IF(Servier!J37<>"",1,0) -> 1 | K71: =IF(MEN!J37<>"",1,0) -> 1 | L71: =IF(ADM!J37<>"",1,0) -> 0 | M71: =IF('CDG DC'!J37<>"",1,0) -> 0 | N71: =IF('CDG ITOC'!J37<>"",1,0) -> 0 | O71: =IF(BPOST!J37<>"",1,0) -> 0 | P71: =IF('Graphtalk AIA'!J37<>"",1,0) -> 0 | Q71: =IF('ONCF APPS'!J37<>"",1,0) -> 0 | R71: =IF('ONCF MW'!J37<>"",1,0) -> 1 | S71: =IF(ANEF!J37<>"",1,0) -> 0 | T71: =IF(Carrefour!J37<>"",1,0) -> 0 | U71: =IF('Vinci Construction'!J37<>"",1,0) -> 0 | V71: =IF(AXA!J37<>"",1,0) -> 0 | W71: =IF(OCP!J37<>"",1,0) -> 1 | X71: =SUM(D71:W71) -> 6
A72: 24 | B72: 8.4 | C72: Maîtrise des sous-traitants | D72: =IF('CDG Sécurité'!K38<>"",1,0) -> 0 | E72: =IF(RAM!J38<>"",1,0) -> 1 | F72: =IF('Min. Intérieur'!J38<>"",1,0) -> 0 | G72: =IF('CDG Capital'!J38<>"",1,0) -> 0 | H72: =IF(AtlanticRe!J38<>"",1,0) -> 1 | I72: =IF('Client A'!J38<>"",1,0) -> 0 | J72: =IF(Servier!J38<>"",1,0) -> 1 | K72: =IF(MEN!J38<>"",1,0) -> 1 | L72: =IF(ADM!J38<>"",1,0) -> 0 | M72: =IF('CDG DC'!J38<>"",1,0) -> 0 | N72: =IF('CDG ITOC'!J38<>"",1,0) -> 0 | O72: =IF(BPOST!J38<>"",1,0) -> 0 | P72: =IF('Graphtalk AIA'!J38<>"",1,0) -> 0 | Q72: =IF('ONCF APPS'!J38<>"",1,0) -> 0 | R72: =IF('ONCF MW'!J38<>"",1,0) -> 1 | S72: =IF(ANEF!J38<>"",1,0) -> 0 | T72: =IF(Carrefour!J38<>"",1,0) -> 0 | U72: =IF('Vinci Construction'!J38<>"",1,0) -> 0 | V72: =IF(AXA!J38<>"",1,0) -> 0 | W72: =IF(OCP!J38<>"",1,0) -> 1 | X72: =SUM(D72:W72) -> 6
A73: 25 | B73: 8.5.1 | C73: Contrôle de la réalisation du service | D73: =IF('CDG Sécurité'!K39<>"",1,0) -> 0 | E73: =IF(RAM!J39<>"",1,0) -> 1 | F73: =IF('Min. Intérieur'!J39<>"",1,0) -> 0 | G73: =IF('CDG Capital'!J39<>"",1,0) -> 0 | H73: =IF(AtlanticRe!J39<>"",1,0) -> 1 | I73: =IF('Client A'!J39<>"",1,0) -> 0 | J73: =IF(Servier!J39<>"",1,0) -> 1 | K73: =IF(MEN!J39<>"",1,0) -> 1 | L73: =IF(ADM!J39<>"",1,0) -> 0 | M73: =IF('CDG DC'!J39<>"",1,0) -> 0 | N73: =IF('CDG ITOC'!J39<>"",1,0) -> 0 | O73: =IF(BPOST!J39<>"",1,0) -> 0 | P73: =IF('Graphtalk AIA'!J39<>"",1,0) -> 0 | Q73: =IF('ONCF APPS'!J39<>"",1,0) -> 0 | R73: =IF('ONCF MW'!J39<>"",1,0) -> 1 | S73: =IF(ANEF!J39<>"",1,0) -> 0 | T73: =IF(Carrefour!J39<>"",1,0) -> 0 | U73: =IF('Vinci Construction'!J39<>"",1,0) -> 0 | V73: =IF(AXA!J39<>"",1,0) -> 0 | W73: =IF(OCP!J39<>"",1,0) -> 1 | X73: =SUM(D73:W73) -> 6
A74: 26 | B74: 8.5.2 | C74: Identification et traçabilité | D74: =IF('CDG Sécurité'!K40<>"",1,0) -> 0 | E74: =IF(RAM!J40<>"",1,0) -> 1 | F74: =IF('Min. Intérieur'!J40<>"",1,0) -> 0 | G74: =IF('CDG Capital'!J40<>"",1,0) -> 0 | H74: =IF(AtlanticRe!J40<>"",1,0) -> 1 | I74: =IF('Client A'!J40<>"",1,0) -> 0 | J74: =IF(Servier!J40<>"",1,0) -> 1 | K74: =IF(MEN!J40<>"",1,0) -> 1 | L74: =IF(ADM!J40<>"",1,0) -> 0 | M74: =IF('CDG DC'!J40<>"",1,0) -> 0 | N74: =IF('CDG ITOC'!J40<>"",1,0) -> 0 | O74: =IF(BPOST!J40<>"",1,0) -> 0 | P74: =IF('Graphtalk AIA'!J40<>"",1,0) -> 0 | Q74: =IF('ONCF APPS'!J40<>"",1,0) -> 0 | R74: =IF('ONCF MW'!J40<>"",1,0) -> 1 | S74: =IF(ANEF!J40<>"",1,0) -> 0 | T74: =IF(Carrefour!J40<>"",1,0) -> 0 | U74: =IF('Vinci Construction'!J40<>"",1,0) -> 0 | V74: =IF(AXA!J40<>"",1,0) -> 0 | W74: =IF(OCP!J40<>"",1,0) -> 1 | X74: =SUM(D74:W74) -> 6
A75: 27 | B75: 8.5.4 | C75: Protection des données client | D75: =IF('CDG Sécurité'!K41<>"",1,0) -> 0 | E75: =IF(RAM!J41<>"",1,0) -> 1 | F75: =IF('Min. Intérieur'!J41<>"",1,0) -> 0 | G75: =IF('CDG Capital'!J41<>"",1,0) -> 0 | H75: =IF(AtlanticRe!J41<>"",1,0) -> 1 | I75: =IF('Client A'!J41<>"",1,0) -> 0 | J75: =IF(Servier!J41<>"",1,0) -> 1 | K75: =IF(MEN!J41<>"",1,0) -> 1 | L75: =IF(ADM!J41<>"",1,0) -> 0 | M75: =IF('CDG DC'!J41<>"",1,0) -> 0 | N75: =IF('CDG ITOC'!J41<>"",1,0) -> 0 | O75: =IF(BPOST!J41<>"",1,0) -> 0 | P75: =IF('Graphtalk AIA'!J41<>"",1,0) -> 0 | Q75: =IF('ONCF APPS'!J41<>"",1,0) -> 0 | R75: =IF('ONCF MW'!J41<>"",1,0) -> 1 | S75: =IF(ANEF!J41<>"",1,0) -> 0 | T75: =IF(Carrefour!J41<>"",1,0) -> 0 | U75: =IF('Vinci Construction'!J41<>"",1,0) -> 0 | V75: =IF(AXA!J41<>"",1,0) -> 0 | W75: =IF(OCP!J41<>"",1,0) -> 1 | X75: =SUM(D75:W75) -> 6
A76: 28 | B76: 8.5.6 | C76: Contrôle des modifications de service | D76: =IF('CDG Sécurité'!K42<>"",1,0) -> 0 | E76: =IF(RAM!J42<>"",1,0) -> 1 | F76: =IF('Min. Intérieur'!J42<>"",1,0) -> 0 | G76: =IF('CDG Capital'!J42<>"",1,0) -> 0 | H76: =IF(AtlanticRe!J42<>"",1,0) -> 1 | I76: =IF('Client A'!J42<>"",1,0) -> 0 | J76: =IF(Servier!J42<>"",1,0) -> 1 | K76: =IF(MEN!J42<>"",1,0) -> 1 | L76: =IF(ADM!J42<>"",1,0) -> 0 | M76: =IF('CDG DC'!J42<>"",1,0) -> 0 | N76: =IF('CDG ITOC'!J42<>"",1,0) -> 0 | O76: =IF(BPOST!J42<>"",1,0) -> 0 | P76: =IF('Graphtalk AIA'!J42<>"",1,0) -> 0 | Q76: =IF('ONCF APPS'!J42<>"",1,0) -> 0 | R76: =IF('ONCF MW'!J42<>"",1,0) -> 1 | S76: =IF(ANEF!J42<>"",1,0) -> 0 | T76: =IF(Carrefour!J42<>"",1,0) -> 0 | U76: =IF('Vinci Construction'!J42<>"",1,0) -> 0 | V76: =IF(AXA!J42<>"",1,0) -> 0 | W76: =IF(OCP!J42<>"",1,0) -> 1 | X76: =SUM(D76:W76) -> 6
A77: 29 | B77: 8.6 | C77: Contrôle avant livraison | D77: =IF('CDG Sécurité'!K43<>"",1,0) -> 0 | E77: =IF(RAM!J43<>"",1,0) -> 1 | F77: =IF('Min. Intérieur'!J43<>"",1,0) -> 0 | G77: =IF('CDG Capital'!J43<>"",1,0) -> 0 | H77: =IF(AtlanticRe!J43<>"",1,0) -> 1 | I77: =IF('Client A'!J43<>"",1,0) -> 0 | J77: =IF(Servier!J43<>"",1,0) -> 1 | K77: =IF(MEN!J43<>"",1,0) -> 1 | L77: =IF(ADM!J43<>"",1,0) -> 0 | M77: =IF('CDG DC'!J43<>"",1,0) -> 0 | N77: =IF('CDG ITOC'!J43<>"",1,0) -> 0 | O77: =IF(BPOST!J43<>"",1,0) -> 0 | P77: =IF('Graphtalk AIA'!J43<>"",1,0) -> 0 | Q77: =IF('ONCF APPS'!J43<>"",1,0) -> 0 | R77: =IF('ONCF MW'!J43<>"",1,0) -> 1 | S77: =IF(ANEF!J43<>"",1,0) -> 0 | T77: =IF(Carrefour!J43<>"",1,0) -> 0 | U77: =IF('Vinci Construction'!J43<>"",1,0) -> 0 | V77: =IF(AXA!J43<>"",1,0) -> 0 | W77: =IF(OCP!J43<>"",1,0) -> 1 | X77: =SUM(D77:W77) -> 6
A78: 30 | B78: 8.7 | C78: Traitement des non-conformités | D78: =IF('CDG Sécurité'!K44<>"",1,0) -> 0 | E78: =IF(RAM!J44<>"",1,0) -> 1 | F78: =IF('Min. Intérieur'!J44<>"",1,0) -> 1 | G78: =IF('CDG Capital'!J44<>"",1,0) -> 0 | H78: =IF(AtlanticRe!J44<>"",1,0) -> 1 | I78: =IF('Client A'!J44<>"",1,0) -> 0 | J78: =IF(Servier!J44<>"",1,0) -> 1 | K78: =IF(MEN!J44<>"",1,0) -> 1 | L78: =IF(ADM!J44<>"",1,0) -> 0 | M78: =IF('CDG DC'!J44<>"",1,0) -> 0 | N78: =IF('CDG ITOC'!J44<>"",1,0) -> 0 | O78: =IF(BPOST!J44<>"",1,0) -> 0 | P78: =IF('Graphtalk AIA'!J44<>"",1,0) -> 0 | Q78: =IF('ONCF APPS'!J44<>"",1,0) -> 0 | R78: =IF('ONCF MW'!J44<>"",1,0) -> 1 | S78: =IF(ANEF!J44<>"",1,0) -> 0 | T78: =IF(Carrefour!J44<>"",1,0) -> 0 | U78: =IF('Vinci Construction'!J44<>"",1,0) -> 0 | V78: =IF(AXA!J44<>"",1,0) -> 0 | W78: =IF(OCP!J44<>"",1,0) -> 1 | X78: =SUM(D78:W78) -> 7
... A85: 37 | B85: 10.2 | C85: Actions correctives | D85: =IF('CDG Sécurité'!K51<>"",1,0) -> 0 | E85: =IF(RAM!J51<>"",1,0) -> 1 | F85: =IF('Min. Intérieur'!J51<>"",1,0) -> 0 | G85: =IF('CDG Capital'!J51<>"",1,0) -> 0 | H85: =IF(AtlanticRe!J51<>"",1,0) -> 1 | I85: =IF('Client A'!J51<>"",1,0) -> 0 | J85: =IF(Servier!J51<>"",1,0) -> 1 | K85: =IF(MEN!J51<>"",1,0) -> 1 | L85: =IF(ADM!J51<>"",1,0) -> 0 | M85: =IF('CDG DC'!J51<>"",1,0) -> 0 | N85: =IF('CDG ITOC'!J51<>"",1,0) -> 0 | O85: =IF(BPOST!J51<>"",1,0) -> 0 | P85: =IF('Graphtalk AIA'!J51<>"",1,0) -> 0 | Q85: =IF('ONCF APPS'!J51<>"",1,0) -> 0 | R85: =IF('ONCF MW'!J51<>"",1,0) -> 1 | S85: =IF(ANEF!J51<>"",1,0) -> 0 | T85: =IF(Carrefour!J51<>"",1,0) -> 0 | U85: =IF('Vinci Construction'!J51<>"",1,0) -> 0 | V85: =IF(AXA!J51<>"",1,0) -> 0 | W85: =IF(OCP!J51<>"",1,0) -> 1 | X85: =SUM(D85:W85) -> 6
C86: TOTAL PAR COMPTE | D86: =SUM(D49:D85) -> 7 | E86: =SUM(E49:E85) -> 28 | F86: =SUM(F49:F85) -> 9 | G86: =SUM(G49:G85) -> #REF! | H86: =SUM(H49:H85) -> 28 | I86: =SUM(I49:I85) -> 0 | J86: =SUM(J49:J85) -> 37 | K86: =SUM(K49:K85) -> 28 | ... X86: =SUM(X49:X85) -> #REF!

Sheet Sheet1
B2: Libellé Terrain | C2: Total
B3: Gestion des incidents | C3: 6
B4: Gestion des risques et opportunités | C4: 5
B5: Gouvernance | C5: 5
B6: Gestion documentaire | C6: 4
B7: Compétences de l'équipe | C7: 4
B8: Gestion des changements | C8: 3
B9: Planification des objectifs | C9: 2

Sheet Min. Intérieur
A1: QHC ISO 9001:2015 — Min. Intérieur
A2: DXC Technology | Quality Health Check FY27
A4: Nom du Compte : Min. Intérieur | E4: N° QHC : QHC-05
A5: Date du QHC : 5/6/2026 | E5: Auditeur : Farah ABID
A6: Responsable Entité : EL JAOUHARI, Mohamed Amine | E6: Date QHC de Suivi :
A8: INDICATEURS CLÉS
A9: Score Maturité | B9: Badge | C9: NC Majeures | D9: NC Mineures | E9: Observations | F9: OFI | G9: BP | H9: TOTAL
A10: =IFERROR(AVERAGE(L15:L51),0) -> 3.3636364 | B10: =IF(A10<=0.5,"⏳ Non audité",IF(A10>=4.5,"Très Performant",IF(A10>=3.5,"Performant",IF(A10>=2.5,"A Surveiller",IF(A10>=1.5,"À Risque",IF(A10<=1.5,"Critique")))))) -> A Surveiller | C10: =COUNTIF(J15:J51,"NC Majeure") -> 0 | D10: =COUNTIF(J15:J51,"NC Mineure") -> 7 | E10: =COUNTIF(J15:J51,"Observation") -> 0 | F10: =COUNTIF(J15:J51,"OFI") -> 0 | G10: =COUNTIF(J15:J51,"Bonne Pratique") -> 2 | H10: =C10+D10+E10+F10 -> 7
A12: PARTIE A — CHECKLIST ISO 9001:2015
A13: ⚙️ Saisir le Score (1-4) dans col L → Niveau Maturité (col K) se calcule automatiquement
A14: N° | B14: Clause ISO | C14: Intitulé Officiel ISO 9001:2015 | D14: Libellé Terrain | E14: Ce qu'il faut contrôler | F14: Category | G14: Référence DXC EDGE | H14: Preuves Attendues | I14: Constat de l'Auditeur | J14: Catégorie Finding | K14: Niveau Maturité | L14: Score (1-5) | M14: Action Corrective | N14: Responsable | O14: Date de début | P14: Délai de clôture | Q14: Statut | R14: Âge (jours) | S14: Indicateur Âge | T14: Evidence | U14: Commentaires
A15: 1 | B15: 4.1 | C15: Compréhension de l'organisme et de son contexte | D15: Connaissance de notre environnement | E15: Revue de contexte, analyse SWOT, facteurs internes/externes | F15: Entité et Compte | G15: ESIMS - CTX01 | H15: Revue de contexte, analyse SWOT, facteurs internes/externes | I15: Tracabilté et Suivi des Incidents non formalisé | J15: NC Mineure | K15: =IF(L15="","",IF(L15=5,"Excellence/Meilleures pratiques",IF(L15=4,"Totalement en place/Proactif",IF(L15=3,"Largement en place/Stable",IF(L15=2,"Partiellement en place/Réactif",IF(L15=1,"Non en place/Elémentaire","")))))) -> Partiellement en place/Réactif | L15: 2 | M15: Formaliser est suivre les enjeux interne et externe | N15: EL JAOUHARI, Mohamed Amine | O15: 46218 | Q15: En cours | R15: =IF(O15="","",IF(P15<>"",P15-O15,TODAY()-O15)) -> 62 | S15: =IF(Q15="","",IF(P15="Clôturé","✅",IF(Q15<=30,"🟢",IF(Q15<=60,"🟠","🔴")))) -> 🔴 | T15: DXC_Risk and Opportunity and Issues Register (1).xlsx
A16: 2 | B16: 4.2 | C16: Compréhension des besoins et attentes des parties intéressées | D16: Écoute des parties prenantes | E16: Cartographie parties intéressées, besoins et attentes | F16: Entité et Compte | G16: ESIMS - CTX02 | H16: Cartographie parties intéressées, besoins et attentes | K16: =IF(L16="","",IF(L16=4,"Totalement en place",IF(L16=3,"Largement en place",IF(L16=2,"Partiellement en place",IF(L16=1,"Non en place",""))))) | R16: =IF(O16="","",IF(P16<>"",P16-O16,TODAY()-O16)) | S16: =IF(Q16="","",IF(P16="Clôturé","✅",IF(Q16<=30,"🟢",IF(Q16<=60,"🟠","🔴"))))
A17: 3 | B17: 4.3 | C17: Détermination du domaine d'application du SMQ | D17: Périmètre de notre système qualité | E17: Périmètre SMQ documenté, justifications exclusions | F17: Entité | G17: ESIMS - CTX03 | H17: Périmètre SMQ documenté, justifications exclusions | K17: =IF(L17="","",IF(L17=4,"Totalement en place",IF(L17=3,"Largement en place",IF(L17=2,"Partiellement en place",IF(L17=1,"Non en place",""))))) | R17: =IF(O17="","",IF(P17<>"",P17-O17,TODAY()-O17)) | S17: =IF(Q17="","",IF(P17="Clôturé","✅",IF(Q17<=30,"🟢",IF(Q17<=60,"🟠","🔴"))))
A18: 4 | B18: 4.4 | C18: Système de management de la qualité et ses processus | D18: Cartographie de nos processus | E18: Cartographie processus, interactions, entrées/sorties | F18: Entité et Compte | G18: ESIMS - CTX04 | H18: Cartographie processus, indicateurs, pilotes identifiés | I18: politique de surveillance en place PAQ Existant mais reste à migrer
A19: 5 | B19: 5.1 | C19: Leadership et engagement | D19: Engagement de la direction | E19: Engagement direction, revues, communication, ressources | F19: Entité | G19: ESIMS - LDR01 | H19: PV revue direction, communication qualité, allocation ressources | K19: =IF(L19="","",IF(L19=4,"Totalement en place",IF(L19=3,"Largement en place",IF(L19=2,"Partiellement en place",IF(L19=1,"Non en place",""))))) | R19: =IF(O19="","",IF(P19<>"",P19-O19,TODAY()-O19)) | S19: =IF(Q19="","",IF(P19="Clôturé","✅",IF(Q19<=30,"🟢",IF(Q19<=60,"🟠","🔴"))))
A20: 6 | B20: 5.2 | C20: Politique qualité | D20: Notre politique qualité | E20: Politique qualité diffusée, comprise, applicable | F20: Entité et Compte | G20: ESIMS - LDR02 | H20: Politique qualité affichée, diffusée, revue annuelle | K20: =IF(L20="","",IF(L20=5,"Excellence/Meilleures pratiques",IF(L20=4,"Totalement en place/Proactif",IF(L20=3,"Largement en place/Stable",IF(L20=2,"Partiellement en place/Réactif",IF(L20=1,"Non en place/Elémentaire","")))))) | R20: =IF(O20="","",IF(P20<>"",P20-O20,TODAY()-O20)) | S20: =IF(Q20="","",IF(P20="Clôturé","✅",IF(Q20<=30,"🟢",IF(Q20<=60,"🟠","🔴"))))
A21: 7 | B21: 5.3 | C21: Rôles, responsabilités et autorités | D21: Qui fait quoi ? | E21: Organigramme, fiches de poste, délégations | F21: Entité et Compte | G21: ESIMS - LDR03 | H21: Organigramme à jour, fiches de poste, matrice RACI | I21: Organigramme en place et validé avec le client | K21: =IF(L21="","",IF(L21=5,"Excellence/Meilleures pratiques",IF(L21=4,"Totalement en place/Proactif",IF(L21=3,"Largement en place/Stable",IF(L21=2,"Partiellement en place/Réactif",IF(L21=1,"Non en place/Elémentaire","")))))) -> Totalement en place/Proactif | L21: 4 | R21: =IF(O21="","",IF(P21<>"",P21-O21,TODAY()-O21)) | S21: =IF(Q21="","",IF(P21="Clôturé","✅",IF(Q21<=30,"🟢",IF(Q21<=60,"🟠","🔴")))) | T21: To be provided
A22: 8 | B22: 6.1 | C22: Actions à mettre en œuvre face aux risques et opportunités | D22: Gestion des risques et opportunités | E22: Registre des risques, actions préventives, revue efficacité | F22: Entité et Compte | G22: ESIMS - PLN01 | H22: Registre risques, plans action, suivi efficacité | I22: La gestion des risques est en place, alors que celle des opportunités reste à développer | J22: NC Mineure | K22: =IF(L22="","",IF(L22=5,"Excellence/Meilleures pratiques",IF(L22=4,"Totalement en place/Proactif",IF(L22=3,"Largement en place/Stable",IF(L22=2,"Partiellement en place/Réactif",IF(L22=1,"Non en place/Elémentaire","")))))) -> Partiellement en place/Réactif | L22: 2 | M22: Formaliser la gestion des risques et opportunités via le fichier dedié | N22: EL JAOUHARI, Mohamed Amine | O22: 46218 | Q22: En cours | R22: =IF(O22="","",IF(P22<>"",P22-O22,TODAY()-O22)) -> 62 | S22: =IF(Q22="","",IF(P22="Clôturé","✅",IF(Q22<=30,"🟢",IF(Q22<=60,"🟠","🔴")))) -> 🔴 | T22: DXC_Risk and Opportunity and Issues Register (1).xlsx
A23: 9 | B23: 6.2 | C23: Objectifs qualité et planification des actions | D23: Planification des objectifs | E23: Objectifs SMART, plans d'action, indicateurs, suivi | F23: Entité et Compte | G23: ESIMS - PLN02 | H23: Tableau objectifs SMART, plans action, revues périodiques | I23: Objectifs Qualité connus mais non tracés | J23: NC Mineure | K23: =IF(L23="","",IF(L23=5,"Excellence/Meilleures pratiques",IF(L23=4,"Totalement en place/Proactif",IF(L23=3,"Largement en place/Stable",IF(L23=2,"Partiellement en place/Réactif",IF(L23=1,"Non en place/Elémentaire","")))))) -> Partiellement en place/Réactif | L23: 2 | M23: Formaliser le suiv des objectis Qualité | N23: EL JAOUHARI, Mohamed Amine | O23: 46218 | Q23: En cours | R23: =IF(O23="","",IF(P23<>"",P23-O23,TODAY()-O23)) -> 62 | S23: =IF(Q23="","",IF(P23="Clôturé","✅",IF(Q23<=30,"🟢",IF(Q23<=60,"🟠","🔴")))) -> 🔴 | T23: DXC Measurement Plan Template (3).xlsx
A24: 10 | B24: 6.3 | C24: Planification des modifications | D24: Gestion des changements | E24: Processus de gestion des changements, impacts évalués | F24: Entité et Compte | G24: ESIMS - PLN03 | H24: Procédure changement, évaluation impacts, communication | I24: Gestion des changements en place mais non tracée | J24: NC Mineure | K24: =IF(L24="","",IF(L24=5,"Excellence/Meilleures pratiques",IF(L24=4,"Totalement en place/Proactif",IF(L24=3,"Largement en place/Stable",IF(L24=2,"Partiellement en place/Réactif",IF(L24=1,"Non en place/Elémentaire","")))))) -> Partiellement en place/Réactif | L24: 2 | M24: Formaliser la gestion des changements | N24: EL JAOUHARI, Mohamed Amine | O24: 46218 | Q24: En cours | R24: =IF(O24="","",IF(P24<>"",P24-O24,TODAY()-O24)) -> 62 | S24: =IF(Q24="","",IF(P24="Clôturé","✅",IF(Q24<=30,"🟢",IF(Q24<=60,"🟠","🔴")))) -> 🔴 | T24: DXC_Risk and Opportunity and Issues Register (1).xlsx
A25: 11 | B25: 7.1.1 | C25: Ressources humaines | D25: Disponibilité des ressources humaines | E25: Effectifs, recrutement, planification, disponibilité | F25: Entité et Compte | G25: ESIMS - SUP01 | H25: Plan effectifs, recrutement, planification congés | K25: =IF(L25="","",IF(L25=5,"Excellence/Meilleures pratiques",IF(L25=4,"Totalement en place/Proactif",IF(L25=3,"Largement en place/Stable",IF(L25=2,"Partiellement en place/Réactif",IF(L25=1,"Non en place/Elémentaire","")))))) | R25: =IF(O25="","",IF(P25<>"",P25-O25,TODAY()-O25)) | S25: =IF(Q25="","",IF(P25="Clôturé","✅",IF(Q25<=30,"🟢",IF(Q25<=60,"🟠","🔴"))))
A26: 12 | B26: 7.1.2 | C26: Infrastructure | D26: Disponibilité des infrastructures | E26: Locaux, équipements, IT, maintenance | F26: Entité et Compte | G26: ESIMS - SUP02 | H26: Inventaire équipements, plan maintenance, tickets infra | K26: =IF(L26="","",IF(L26=4,"Totalement en place",IF(L26=3,"Largement en place",IF(L26=2,"Partiellement en place",IF(L26=1,"Non en place",""))))) | R26: =IF(OR(O26="",Q26="Clôturé"),"",TODAY()-O26) | S26: =IF(R26="","",IF(Q26="Clôturé","✅",IF(R26<=30,"🟢",IF(R26<=60,"🟠","🔴"))))
A27: 13 | B27: 7.1.5 | C27: Ressources pour la surveillance et la mesure | D27: Outils de mesure et de contrôle | E27: Étalonnage, vérification instruments, traçabilité mesures | F27: Compte | G27: ESIMS - SUP03 | H27: Liste instruments, certificats étalonnage, planning vérification | K27: =IF(L27="","",IF(L27=4,"Totalement en place",IF(L27=3,"Largement en place",IF(L27=2,"Partiellement en place",IF(L27=1,"Non en place",""))))) | R27: =IF(OR(O27="",Q27="Clôturé"),"",TODAY()-O27) | S27: =IF(R27="","",IF(Q27="Clôturé","✅",IF(R27<=30,"🟢",IF(R27<=60,"🟠","🔴"))))
A28: 14 | B28: 7.1.6 | C28: Connaissances organisationnelles | D28: Gestion des connaissances | E28: Base de connaissances, capitalisation, partage, formation | F28: Entité et Compte | G28: ESIMS - SUP04 | H28: Base connaissances, wiki, REX, partage bonnes pratiques | K28: =IF(L28="","",IF(L28=4,"Totalement en place",IF(L28=3,"Largement en place",IF(L28=2,"Partiellement en place",IF(L28=1,"Non en place",""))))) | R28: =IF(OR(O28="",Q28="Clôturé"),"",TODAY()-O28) | S28: =IF(R28="","",IF(Q28="Clôturé","✅",IF(R28<=30,"🟢",IF(R28<=60,"🟠","🔴"))))
A29: 15 | B29: 7.2 | C29: Compétences | D29: Compétences de l'équipe | E29: Matrice compétences, plans formation, évaluations | F29: Entité et Compte | G29: ESIMS - SUP05 | H29: Matrice compétences, plan formation, attestations | I29: Gestion des competences de la SL Sécurité en place en revanche il est preferable de faire un suivi des ressources affectées au Min d'interieur | J29: NC Mineure | K29: =IF(L29="","",IF(L29=5,"Excellence/Meilleures pratiques",IF(L29=4,"Totalement en place/Proactif",IF(L29=3,"Largement en place/Stable",IF(L29=2,"Partiellement en place/Réactif",IF(L29=1,"Non en place/Elémentaire","")))))) -> Partiellement en place/Réactif | L29: 2 | M29: Mettre en place une matrice de compétences pour reflèter : l’état actuel des compétences des ressources l’avancement et la réalisation des actions mises en place pour le développement des compétences | N29: EL JAOUHARI, Mohamed Amine | O29: 46218 | Q29: En cours | R29: =IF(O29="","",IF(P29<>"",P29-O29,TODAY()-O29)) -> 62 | S29: =IF(Q29="","",IF(P29="Clôturé","✅",IF(Q29<=30,"🟢",IF(Q29<=60,"🟠","🔴")))) -> 🔴 | T29: Multiskill_Matrix Template (1).xlsx
A30: 16 | B30: 7.3 | C30: Sensibilisation | D30: Sensibilisation qualité | E30: Sensibilisation politique, objectifs, contribution qualité | F30: Entité et Compte | G30: ESIMS - SUP06 | H30: Supports sensibilisation, quiz, campagnes qualité | I30: NA | K30: =IF(L30="","",IF(L30=5,"Excellence/Meilleures pratiques",IF(L30=4,"Totalement en place/Proactif",IF(L30=3,"Largement en place/Stable",IF(L30=2,"Partiellement en place/Réactif",IF(L30=1,"Non en place/Elémentaire","")))))) | R30: =IF(O30="","",IF(P30<>"",P30-O30,TODAY()-O30)) | S30: =IF(Q30="","",IF(P30="Clôturé","✅",IF(Q30<=30,"🟢",IF(Q30<=60,"🟠","🔴"))))
A31: 17 | B31: 7.4 | C31: Communication | D31: Plan de communication | E31: Plan communication interne/externe, canaux, fréquence | F31: Entité et Compte | G31: ESIMS - SUP07 | H31: Plan communication, PV réunions, newsletters, Town Hall | I31: Plan de communication externe en place en revanche on note la manque de tracbilité des instance interne Stockage des MoM et support des réunions en place | J31: NC Mineure | K31: =IF(L31="","",IF(L31=5,"Excellence/Meilleures pratiques",IF(L31=4,"Totalement en place/Proactif",IF(L31=3,"Largement en place/Stable",IF(L31=2,"Partiellement en place/Réactif",IF(L31=1,"Non en place/Elémentaire","")))))) -> Partiellement en place/Réactif | L31: 2 | M31: Formaliser un plan de communication et rajouter les communication interne | N31: EL JAOUHARI, Mohamed Amine | O31: 46218 | Q31: En cours | R31: =IF(O31="","",IF(P31<>"",P31-O31,TODAY()-O31)) -> 62 | S31: =IF(Q31="","",IF(P31="Clôturé","✅",IF(Q31<=30,"🟢",IF(Q31<=60,"🟠","🔴")))) -> 🔴 | T31: Gouvernance et communication
A32: 18 | B32: 7.5 | C32: Informations documentées | D32: Gestion documentaire | E32: Maîtrise documents, versions, approbation, archivage | F32: Entité et Compte | G32: ESIMS - SUP08 | H32: Liste documents maîtrisés, procédure gestion documentaire | I32: Certains Documents non migré suite nouvelle image | J32: NC Mineure | K32: =IF(L32="","",IF(L32=5,"Excellence/Meilleures pratiques",IF(L32=4,"Totalement en place/Proactif",IF(L32=3,"Largement en place/Stable",IF(L32=2,"Partiellement en place/Réactif",IF(L32=1,"Non en place/Elémentaire","")))))) -> Partiellement en place/Réactif | L32: 2 | M32: Migrer les documents vers les nouvelles templates en priorisant ceux partagés avec le client (Support reunion, PAQ, Peocessus | N32: EL JAOUHARI, Mohamed Amine | O32: 46218 | Q32: En cours | R32: =IF(O32="","",IF(P32<>"",P32-O32,TODAY()-O32)) -> 62 | S32: =IF(Q32="","",IF(P32="Clôturé","✅",IF(Q32<=30,"🟢",IF(Q32<=60,"🟠","🔴")))) -> 🔴
A33: 19 | B33: 8.1 | C33: Planification et maîtrise opérationnelles | D33: Planification des opérations | E33: Planification opérationnelle, critères, ressources | F33: Compte | G33: ESIMS - OPS01 | H33: Plans opérationnels, critères acceptation, ressources allouées | I33: Planification des opérations et des ressources en place | K33: =IF(L33="","",IF(L33=5,"Excellence/Meilleures pratiques",IF(L33=4,"Totalement en place/Proactif",IF(L33=3,"Largement en place/Stable",IF(L33=2,"Partiellement en place/Réactif",IF(L33=1,"Non en place/Elémentaire","")))))) -> Totalement en place/Proactif | L33: 4 | R33: =IF(O33="","",IF(P33<>"",P33-O33,TODAY()-O33)) | S33: =IF(Q33="","",IF(P33="Clôturé","✅",IF(Q33<=30,"🟢",IF(Q33<=60,"🟠","🔴")))) | T33: Planification des ressources et des opérations
A34: 20 | B34: 8.2.1 | C34: Communication avec les clients | D34: Communication avec le client | E34: Canaux communication client, réclamations, feedback | F34: Compte | G34: ESIMS - OPS02 | H34: Canaux communication, SLA, escalade, réclamations | I34: Canaux de communication definis et honorés | K34: =IF(L34="","",IF(L34=5,"Excellence/Meilleures pratiques",IF(L34=4,"Totalement en place/Proactif",IF(L34=3,"Largement en place/Stable",IF(L34=2,"Partiellement en place/Réactif",IF(L34=1,"Non en place/Elémentaire","")))))) -> Totalement en place/Proactif | L34: 4 | R34: =IF(O34="","",IF(P34<>"",P34-O34,TODAY()-O34)) | S34: =IF(Q34="","",IF(P34="Clôturé","✅",IF(Q34<=30,"🟢",IF(Q34<=60,"🟠","🔴")))) | T34: Gouvernance et communication
A35: 21 | B35: 8.2.2 | C35: Détermination des exigences relatives aux produits et services | D35: Recueil des exigences client | E35: Recueil exigences, spécifications, critères acceptation | F35: Compte | G35: ESIMS - OPS03 | H35: Cahier des charges, spécifications, critères acceptation | I35: Disponible dans contrat et PAQ | K35: =IF(L35="","",IF(L35=5,"Excellence/Meilleures pratiques",IF(L35=4,"Totalement en place/Proactif",IF(L35=3,"Largement en place/Stable",IF(L35=2,"Partiellement en place/Réactif",IF(L35=1,"Non en place/Elémentaire","")))))) -> Totalement en place/Proactif | L35: 4 | R35: =IF(O35="","",IF(P35<>"",P35-O35,TODAY()-O35)) | S35: =IF(Q35="","",IF(P35="Clôturé","✅",IF(Q35<=30,"🟢",IF(Q35<=60,"🟠","🔴")))) | T35: Traçabilité des exigences et des modifications et validation du contrat
A36: 22 | B36: 8.2.3 | C36: Revue des exigences relatives aux produits et services | D36: Revue avant engagement | E36: Revue contrat, faisabilité, risques avant engagement | F36: Compte | G36: ESIMS - OPS04 | H36: Check-list revue contrat, PV validation, analyse faisabilité | I36: PV des validations disponibles | K36: =IF(L36="","",IF(L36=5,"Excellence/Meilleures pratiques",IF(L36=4,"Totalement en place/Proactif",IF(L36=3,"Largement en place/Stable",IF(L36=2,"Partiellement en place/Réactif",IF(L36=1,"Non en place/Elémentaire","")))))) -> Totalement en place/Proactif | L36: 4 | R36: =IF(O36="","",IF(P36<>"",P36-O36,TODAY()-O36)) | S36: =IF(Q36="","",IF(P36="Clôturé","✅",IF(Q36<=30,"🟢",IF(Q36<=60,"🟠","🔴")))) | T36: Traçabilité des exigences et des modifications et validation du contrat
A37: 23 | B37: 8.2.4 | C37: Modifications des exigences relatives aux produits et services | D37: Gestion des modifications contractuelles | E37: Processus avenants, traçabilité modifications contrat | F37: Compte | G37: ESIMS - OPS05 | H37: Processus avenant, traçabilité modifications, validation | I37: PV des validations disponibles | K37: =IF(L37="","",IF(L37=5,"Excellence/Meilleures pratiques",IF(L37=4,"Totalement en place/Proactif",IF(L37=3,"Largement en place/Stable",IF(L37=2,"Partiellement en place/Réactif",IF(L37=1,"Non en place/Elémentaire","")))))) -> Totalement en place/Proactif | L37: 4 | R37: =IF(O37="","",IF(P37<>"",P37-O37,TODAY()-O37)) | S37: =IF(Q37="","",IF(P37="Clôturé","✅",IF(Q37<=30,"🟢",IF(Q37<=60,"🟠","🔴")))) | T37: Traçabilité des exigences et des modifications et validation du contrat
A38: 24 | B38: 8.4 | C38: Maîtrise des processus, produits et services fournis par des prestataires externes | D38: Maîtrise des sous-traitants | E38: Évaluation fournisseurs, critères sélection, suivi performance | F38: Compte | G38: ESIMS - OPS06 | H38: Liste fournisseurs évalués, critères, audits fournisseurs | I38: NA | K38: =IF(L38="","",IF(L38=5,"Excellence/Meilleures pratiques",IF(L38=4,"Totalement en place/Proactif",IF(L38=3,"Largement en place/Stable",IF(L38=2,"Partiellement en place/Réactif",IF(L38=1,"Non en place/Elémentaire","")))))) | R38: =IF(O38="","",IF(P38<>"",P38-O38,TODAY()-O38)) | S38: =IF(Q38="","",IF(P38="Clôturé","✅",IF(Q38<=30,"🟢",IF(Q38<=60,"🟠","🔴"))))
A39: 25 | B39: 8.5.1 | C39: Maîtrise de la production et de la prestation de service | D39: Contrôle de la réalisation du service | E39: Maîtrise production/prestation, instructions, contrôles | F39: Compte | G39: ESIMS - OPS07 | H39: Instructions travail, contrôles en cours, check-lists | I39: Contôles en place est partagés avec le client | K39: =IF(L39="","",IF(L39=5,"Excellence/Meilleures pratiques",IF(L39=4,"Totalement en place/Proactif",IF(L39=3,"Largement en place/Stable",IF(L39=2,"Partiellement en place/Réactif",IF(L39=1,"Non en place/Elémentaire","")))))) -> Totalement en place/Proactif | L39: 4 | R39: =IF(O39="","",IF(P39<>"",P39-O39,TODAY()-O39)) | S39: =IF(Q39="","",IF(P39="Clôturé","✅",IF(Q39<=30,"🟢",IF(Q39<=60,"🟠","🔴")))) | T39: Check list des contrôles :
A40: 26 | B40: 8.5.2 | C40: Identification et traçabilité | D40: Identification et traçabilité | E40: Identification unique, traçabilité lots, historique | F40: Compte | G40: ESIMS - OPS08 | H40: Système identification, numéros lot, traçabilité | I40: Systeme d'identification et traçabilité en place | K40: =IF(L40="","",IF(L40=5,"Excellence/Meilleures pratiques",IF(L40=4,"Totalement en place/Proactif",IF(L40=3,"Largement en place/Stable",IF(L40=2,"Partiellement en place/Réactif",IF(L40=1,"Non en place/Elémentaire","")))))) -> Totalement en place/Proactif | L40: 4 | R40: =IF(O40="","",IF(P40<>"",P40-O40,TODAY()-O40)) | S40: =IF(Q40="","",IF(P40="Clôturé","✅",IF(Q40<=30,"🟢",IF(Q40<=60,"🟠","🔴")))) | T40: Traçabilité des logs
A41: 27 | B41: 8.5.4 | C41: Propriété des clients ou des prestataires externes | D41: Protection des données client | E41: Protection données client, confidentialité, RGPD | F41: Compte | G41: ESIMS - OPS09 | H41: Clauses confidentialité, mesures protection, registre RGPD | I41: NDA,Politique confidentialité stockage dans SP | K41: =IF(L41="","",IF(L41=5,"Excellence/Meilleures pratiques",IF(L41=4,"Totalement en place/Proactif",IF(L41=3,"Largement en place/Stable",IF(L41=2,"Partiellement en place/Réactif",IF(L41=1,"Non en place/Elémentaire","")))))) -> Totalement en place/Proactif | L41: 4 | R41: =IF(O41="","",IF(P41<>"",P41-O41,TODAY()-O41)) | S41: =IF(Q41="","",IF(P41="Clôturé","✅",IF(Q41<=30,"🟢",IF(Q41<=60,"🟠","🔴"))))
A42: 28 | B42: 8.5.6 | C42: Activités après livraison | D42: Contrôle des modifications de service | E42: Maîtrise modifications en cours de production | F42: Compte | G42: ESIMS - OPS10 | H42: Procédure modification, validation, communication client | I42: NA | K42: =IF(L42="","",IF(L42=5,"Excellence/Meilleures pratiques",IF(L42=4,"Totalement en place/Proactif",IF(L42=3,"Largement en place/Stable",IF(L42=2,"Partiellement en place/Réactif",IF(L42=1,"Non en place/Elémentaire","")))))) | R42: =IF(O42="","",IF(P42<>"",P42-O42,TODAY()-O42)) | S42: =IF(Q42="","",IF(P42="Clôturé","✅",IF(Q42<=30,"🟢",IF(Q42<=60,"🟠","🔴"))))
A43: 29 | B43: 8.6 | C43: Libération des produits et services | D43: Contrôle avant livraison | E43: Contrôle final, critères libération, autorisation | F43: Compte | G43: ESIMS - OPS11 | H43: PV contrôle final, check-list libération, autorisation | I43: NA | K43: =IF(L43="","",IF(L43=5,"Excellence/Meilleures pratiques",IF(L43=4,"Totalement en place/Proactif",IF(L43=3,"Largement en place/Stable",IF(L43=2,"Partiellement en place/Réactif",IF(L43=1,"Non en place/Elémentaire","")))))) | R43: =IF(O43="","",IF(P43<>"",P43-O43,TODAY()-O43)) | S43: =IF(Q43="","",IF(P43="Clôturé","✅",IF(Q43<=30,"🟢",IF(Q43<=60,"🟠","🔴"))))
A44: 30 | B44: 8.7 | C44: Maîtrise des éléments de sortie non conformes | D44: Traitement des non-conformités | E44: Détection NC, isolement, actions, enregistrements | F44: Compte | G44: ESIMS - OPS12 | H44: Registre NC, fiches NC, actions, vérification clôture | I44: Pilotage des non-conformités et des plans d’actions en collaboration avec le client jusqu’à clôture, avec capitalisation des enseignements auprès des équipes | J44: Bonne Pratique | K44: =IF(L44="","",IF(L44=5,"Excellence/Meilleures pratiques",IF(L44=4,"Totalement en place/Proactif",IF(L44=3,"Largement en place/Stable",IF(L44=2,"Partiellement en place/Réactif",IF(L44=1,"Non en place/Elémentaire","")))))) -> Totalement en place/Proactif | L44: 4 | R44: =IF(O44="","",IF(P44<>"",P44-O44,TODAY()-O44)) | S44: =IF(Q44="","",IF(P44="Clôturé","✅",IF(Q44<=30,"🟢",IF(Q44<=60,"🟠","🔴")))) | T44: Suivi des Non conformité et action correctives :
A45: 31 | B45: 9.1.1 | C45: Surveillance, mesure, analyse et évaluation | D45: Mesure de la performance | E45: Indicateurs performance, tableaux de bord, tendances | F45: Entité et Compte | G45: ESIMS - PRF01 | H45: Tableaux de bord, indicateurs KPI, tendances | I45: Dashboard de suivi de l'activite en place en note meme un Dashboard de suivi des actions d'amélioration par périmettre | K45: =IF(L45="","",IF(L45=5,"Excellence/Meilleures pratiques",IF(L45=4,"Totalement en place/Proactif",IF(L45=3,"Largement en place/Stable",IF(L45=2,"Partiellement en place/Réactif",IF(L45=1,"Non en place/Elémentaire","")))))) -> Totalement en place/Proactif | L45: 4 | R45: =IF(O45="","",IF(P45<>"",P45-O45,TODAY()-O45)) | S45: =IF(Q45="","",IF(P45="Clôturé","✅",IF(Q45<=30,"🟢",IF(Q45<=60,"🟠","🔴")))) | T45: Communication avec le client, analyse et suivi des réalisations
A46: 32 | B46: 9.1.2 | C46: Satisfaction du client | D46: Satisfaction client | E46: Enquêtes satisfaction, NPS, réclamations, tendances | F46: Compte | G46: ESIMS - PRF02 | H46: Enquêtes CSAT, analyse réclamations, plan amélioration | I46: Analyse des réclamations et plan d'amélioration en place | K46: =IF(L46="","",IF(L46=5,"Excellence/Meilleures pratiques",IF(L46=4,"Totalement en place/Proactif",IF(L46=3,"Largement en place/Stable",IF(L46=2,"Partiellement en place/Réactif",IF(L46=1,"Non en place/Elémentaire","")))))) -> Totalement en place/Proactif | L46: 4 | R46: =IF(O46="","",IF(P46<>"",P46-O46,TODAY()-O46)) | S46: =IF(Q46="","",IF(P46="Clôturé","✅",IF(Q46<=30,"🟢",IF(Q46<=60,"🟠","🔴")))) | T46: Suivi des Non conformité et action correctives :
A47: 33 | B47: 9.1.3 | C47: Analyse et évaluation | D47: Analyse des résultats | E47: Analyse données, revue indicateurs, actions | F47: Entité et Compte | G47: ESIMS - PRF03 | H47: Revue données, analyse tendances, benchmarks | K47: =IF(L47="","",IF(L47=5,"Excellence/Meilleures pratiques",IF(L47=4,"Totalement en place/Proactif",IF(L47=3,"Largement en place/Stable",IF(L47=2,"Partiellement en place/Réactif",IF(L47=1,"Non en place/Elémentaire","")))))) -> Totalement en place/Proactif | L47: 4 | R47: =IF(O47="","",IF(P47<>"",P47-O47,TODAY()-O47)) | S47: =IF(Q47="","",IF(P47="Clôturé","✅",IF(Q47<=30,"🟢",IF(Q47<=60,"🟠","🔴")))) | T47: Communication avec le client, analyse et suivi des réalisations
A48: 34 | B48: 9.2 | C48: Audit interne | D48: Audits internes (QHC) | E48: Programme audit, planification, réalisation, rapport | F48: Entité et Compte | G48: ESIMS - PRF04 | H48: Programme audit, rapports audit, suivi actions | K48: =IF(L48="","",IF(L48=4,"Totalement en place",IF(L48=3,"Largement en place",IF(L48=2,"Partiellement en place",IF(L48=1,"Non en place",""))))) | R48: =IF(O48="","",IF(P48<>"",P48-O48,TODAY()-O48)) | S48: =IF(Q48="","",IF(P48="Clôturé","✅",IF(Q48<=30,"🟢",IF(Q48<=60,"🟠","🔴"))))
A49: 35 | B49: 9.3 | C49: Revue de direction | D49: Revue de direction | E49: Revue direction, entrées/sorties, décisions, actions | F49: Entité | G49: ESIMS - PRF05 | H49: PV revue direction, plan actions, suivi décisions | K49: =IF(L49="","",IF(L49=4,"Totalement en place",IF(L49=3,"Largement en place",IF(L49=2,"Partiellement en place",IF(L49=1,"Non en place",""))))) | R49: =IF(O49="","",IF(P49<>"",P49-O49,TODAY()-O49)) | S49: =IF(Q49="","",IF(P49="Clôturé","✅",IF(Q49<=30,"🟢",IF(Q49<=60,"🟠","🔴"))))
A50: 36 | B50: 10.1 | C50: Amélioration continue | D50: Amélioration continue | E50: Identification opportunités, projets amélioration, suivi | F50: Entité et Compte | G50: ESIMS - IMP01 | H50: Registre améliorations, projets Kaizen, suivi gains | I50: Dashboard de suivi des actions d'amélioration par périmettre en place | J50: Bonne Pratique | K50: =IF(L50="","",IF(L50=5,"Excellence/Meilleures pratiques",IF(L50=4,"Totalement en place/Proactif",IF(L50=3,"Largement en place/Stable",IF(L50=2,"Partiellement en place/Réactif",IF(L50=1,"Non en place/Elémentaire","")))))) -> Totalement en place/Proactif | L50: 4 | R50: =IF(O50="","",IF(P50<>"",P50-O50,TODAY()-O50)) | S50: =IF(Q50="","",IF(P50="Clôturé","✅",IF(Q50<=30,"🟢",IF(Q50<=60,"🟠","🔴")))) | T50: Continouus improvement :
A51: 37 | B51: 10.2 | C51: Non-conformité et action corrective | D51: Actions correctives | E51: Analyse causes, actions correctives, vérification efficacité | F51: Entité et Compte | G51: ESIMS - IMP02 | H51: Fiches action corrective, analyse causes, preuve efficacité | I51: Pilotage des non-conformités et des plans d’actions en collaboration avec le client jusqu’à clôture | K51: =IF(L51="","",IF(L51=5,"Excellence/Meilleures pratiques",IF(L51=4,"Totalement en place/Proactif",IF(L51=3,"Largement en place/Stable",IF(L51=2,"Partiellement en place/Réactif",IF(L51=1,"Non en place/Elémentaire","")))))) -> Totalement en place/Proactif | L51: 4 | R51: =IF(O51="","",IF(P51<>"",P51-O51,TODAY()-O51)) | S51: =IF(Q51="","",IF(P51="Clôturé","✅",IF(Q51<=30,"🟢",IF(Q51<=60,"🟠","🔴"))))
A53: MATURITÉ PAR CHAPITRE
A54: Chapitre | B54: Libellé | C54: Nb Clauses | D54: Score Moyen | E54: Badge
A55: Chap 4 | B55: Contexte | C55: 4 | D55: =IFERROR(AVERAGE(L15:L18),0) -> 2 | E55: =IF(D55<=0.5,"⏳ Non audité",IF(D55>=4.5,"🟢 Très Performant",IF(D55>=3.5,"🔵 Performant",IF(D55>=2.5,"🟡 A surveiller",IF(D55>=1.5,"🟠 À Risque",IF(D55<=1.5,"🔴 Critique")))))) -> 🟠 À Risque
A56: Chap 5 | B56: Leadership | C56: 3 | D56: =IFERROR(AVERAGE(L19:L21),0) -> 4 | E56: =IF(D56<=0.5,"⏳ Non audité",IF(D56>=4.5,"🟢 Très Performant",IF(D56>=3.5,"🔵 Performant",IF(D56>=2.5,"🟡 A surveiller",IF(D56>=1.5,"🟠 À Risque",IF(D56<=1.5,"🔴 Critique")))))) -> 🔵 Performant
A57: Chap 6 | B57: Planification | C57: 3 | D57: =IFERROR(AVERAGE(L22:L24),0) -> 2 | E57: =IF(D57<=0.5,"⏳ Non audité",IF(D57>=4.5,"🟢 Très Performant",IF(D57>=3.5,"🔵 Performant",IF(D57>=2.5,"🟡 A surveiller",IF(D57>=1.5,"🟠 À Risque",IF(D57<=1.5,"🔴 Critique")))))) -> 🟠 À Risque
A58: Chap 7 | B58: Support | C58: 8 | D58: =IFERROR(AVERAGE(L25:L32),0) -> 2 | E58: =IF(D58<=0.5,"⏳ Non audité",IF(D58>=4.5,"🟢 Très Performant",IF(D58>=3.5,"🔵 Performant",IF(D58>=2.5,"🟡 A surveiller",IF(D58>=1.5,"🟠 À Risque",IF(D58<=1.5,"🔴 Critique")))))) -> 🟠 À Risque
A59: Chap 8 | B59: Réalisation | C59: 12 | D59: =IFERROR(AVERAGE(L33:L44),0) -> 4 | E59: =IF(D59<=0.5,"⏳ Non audité",IF(D59>=4.5,"🟢 Très Performant",IF(D59>=3.5,"🔵 Performant",IF(D59>=2.5,"🟡 A surveiller",IF(D59>=1.5,"🟠 À Risque",IF(D59<=1.5,"🔴 Critique")))))) -> 🔵 Performant
A60: Chap 9 | B60: Performance | C60: 5 | D60: =IFERROR(AVERAGE(L45:L49),0) -> 4 | E60: =IF(D60<=0.5,"⏳ Non audité",IF(D60>=4.5,"🟢 Très Performant",IF(D60>=3.5,"🔵 Performant",IF(D60>=2.5,"🟡 A surveiller",IF(D60>=1.5,"🟠 À Risque",IF(D60<=1.5,"🔴 Critique")))))) -> 🔵 Performant
A61: Chap 10 | B61: Amélioration | C61: 2 | D61: =IFERROR(AVERAGE(L50:L51),0) -> 4 | E61: =IF(D61<=0.5,"⏳ Non audité",IF(D61>=4.5,"🟢 Très Performant",IF(D61>=3.5,"🔵 Performant",IF(D61>=2.5,"🟡 A surveiller",IF(D61>=1.5,"🟠 À Risque",IF(D61<=1.5,"🔴 Critique")))))) -> 🔵 Performant
A63: CONCLUSION
A64: =IF(C10>0,"⚠️ NC MAJEURE — Action immédiate requise","✅ AUCUNE NC MAJEURE") -> ✅ AUCUNE NC MAJEURE

Sheet CDG Sécurité
B1: QHC ISO 9001:2015 — CDG Sécurité
B2: DXC Technology | Quality Health Check FY27
B4: Nom du Compte : | C4: CDG Sécurité | F4: N° QHC :
B5: Date du QHC : | F5: Auditeur : | G5: Farah ABID
B6: Responsable Entité : | F6: Date QHC de Suivi :
B8: INDICATEURS CLÉS
B9: Score Maturité | C9: Badge | D9: NC Majeures | E9: NC Mineures | F9: Observations | G9: OFI | H9: BP | I9: TOTAL
B10: =IFERROR(AVERAGE(M15:M51),0) -> 2.3636364 | C10: =IF(B10<=0.5,"⏳ Non audité",IF(B10>=4.5,"Très Performant",IF(B10>=3.5,"Performant",IF(B10>=2.5,"A Surveiller",IF(B10>=1.5,"À Risque",IF(B10<=1.5,"Critique")))))) -> À Risque | D10: =COUNTIF(K15:K51,"NC Majeure") -> 1 | E10: =COUNTIF(K15:K51,"NC Mineure") -> 5 | F10: =COUNTIF(K15:K51,"Observation") -> 1 | G10: =COUNTIF(K15:K51,"OFI") -> 0 | H10: =COUNTIF(K15:K51,"Bonne Pratique") -> 0 | I10: =D10+E10+F10+G10 -> 7
B12: PARTIE A — CHECKLIST ISO 9001:2015
B13: ⚙️ Saisir le Score (1-4) dans col L → Niveau Maturité (col K) se calcule automatiquement
B14: N° | C14: Clause ISO | D14: Intitulé Officiel ISO 9001:2015 | E14: Libellé Terrain | F14: Ce qu'il faut contrôler | G14: Category | H14: Référence DXC EDGE | I14: Preuves Attendues | J14: Constat de l'Auditeur | K14: Catégorie Finding | L14: Niveau Maturité | M14: Score (1-5) | N14: Action Corrective | O14: Responsable | P14: Date de début | Q14: Date de clôture | R14: Statut | S14: Âge (jours) | T14: Indicateur Âge | U14: Evidence | V14: Commentaires
B15: 1 | C15: 4.1 | D15: Compréhension de l'organisme et de son contexte | E15: Connaissance de notre environnement | F15: Revue de contexte, analyse SWOT, facteurs internes/externes | G15: Entité et Compte | H15: ESIMS - CTX01 | I15: Revue de contexte, analyse SWOT, facteurs internes/externes | J15: Tracabilté et Suivi des Incidents non formalisé | K15: NC Majeure | L15: =IF(M15="","",IF(M15=5,"Excellence/Meilleures pratiques",IF(M15=4,"Totalement en place/Proactif",IF(M15=3,"Largement en place/Stable",IF(M15=2,"Partiellement en place/Réactif",IF(M15=1,"Non en place/Elémentaire","")))))) -> Non en place/Elémentaire | M15: 1 | N15: Assurer la Tracabilté et le Suivi des Incidents interne et externe | O15: AFIFI FAISSAL | P15: 46234 | Q15: 46280 | R15: Ouvert | S15: =IF(OR(P15="",R15="Clôturé"),"",TODAY()-P15) -> 46 | T15: =IF(S15="","",IF(R15="Clôturé","✅",IF(S15<=30,"🟢",IF(S15<=60,"🟠","🔴")))) -> 🟠 | U15: DXC_Risk and Opportunity and Issues Register (2).xlsx
B16: 2 | C16: 4.2 | D16: Compréhension des besoins et attentes des parties intéressées | E16: Écoute des parties prenantes | F16: Cartographie parties intéressées, besoins et attentes | G16: Entité et Compte | H16: ESIMS - CTX02 | I16: Cartographie parties intéressées, besoins et attentes | L16: =IF(M16="","",IF(M16=5,"Excellence/Meilleures pratiques",IF(M16=4,"Totalement en place/Proactif",IF(M16=3,"Largement en place/Stable",IF(M16=2,"Partiellement en place/Réactif",IF(M16=1,"Non en place/Elémentaire","")))))) | S16: =IF(OR(P16="",R16="Clôturé"),"",TODAY()-P16) | T16: =IF(S16="","",IF(R16="Clôturé","✅",IF(S16<=30,"🟢",IF(S16<=60,"🟠","🔴"))))
